Workbook
Name Slicer_ACTUAL_OD: #N/A
Name Slicer_Bucket: #N/A
Name Slicer_CUSTOMER_NAME1: #N/A
Name Slicer_GRADE: #N/A
Name Slicer_Grade1: #N/A
Name Slicer_ID: #N/A
Name Slicer_ID1: #N/A
Name Slicer_Length: #N/A
Name Slicer_LENGTH1: #N/A
Name Slicer_Material_Type: #N/A
Name Slicer_OD: #N/A
Name Slicer_OD2: #N/A
Name Slicer_Plant: #N/A
Name Slicer_SCHEDULE: #N/A
Name Slicer_TDC: #N/A
Name Slicer_Thickness: #N/A
Name Slicer_THIK: #N/A
Name Slicer_THK: #N/A
Name Slicer_TICKNESS: #N/A

Sheet Sheet2
A1: Last refreshed: 9/28/2025, 5:30:27 AM

Sheet OEM_key_1_rev codes
A1: Customer | B1: OEM | C1: CAM
A2: A.R.Automotive And Engg Industries | B2: RE | C2: Abhishek
A3: BALAJI INDUSTRIES | B3: HMSIL | C3: Abhishek
A4: BALAJI PRESS PRODUCTS INDIA | B4: TVS | C4: Apoorv
A5: BCC PIPES & TUBES PRIVATE LIMITED | B5: GE | C5: Jitendra
A6: BHARAT TUBES CORPORATION | B6: Boiler | C6: Jitendra
A7: ELKAYEM AUTO ANCILLARIES (PVT) LTD. | B7: TVS | C7: Apoorv
A8: ELKAYEM AUTO ANCILLARIES PRIVATE LI | B8: TVS | C8: Apoorv
A9: ELKAYEM AUTO ANCILLARIES PVT LTD -U | B9: TVS | C9: Apoorv
A10: GANESH INDUSTRAIL SUPPLIES | B10: Boiler | C10: Jitendra
A11: Indo Autotech Limited (Unit V) | B11: HMSIL | C11: Abhishek
A12: JBM AUTO LIMITED | B12: RE | C12: Abhishek
... A175: A R AUTOMOTIVE INDUSTRIES PRIVATE L | B175: RE | C175: Abhishek

Sheet RM Coil
A1: Grade | B1: TDC | C1: THIK | D1: Key | E1: MATERIAL | F1: Material Description
A2: Micro alloy | B2: BR45 | C2: 1.6 | D2: =_xlfn.CONCAT(Table32[[#This Row],[TDC]],"-",Table32[[#This Row],[THIK]]) | E2: 3820031 | F2: CR COIL TATXHS BR45 1.600X1300
A3: Micro alloy | B3: BR03 | C3: 1.6 | D3: =_xlfn.CONCAT(Table32[[#This Row],[TDC]],"-",Table32[[#This Row],[THIK]]) | E3: 3717652 | F3: CR COIL TATXHS BR03 1.600X1300
A4: Micro alloy | B4: BR03 | C4: 1.6 | D4: =_xlfn.CONCAT(Table32[[#This Row],[TDC]],"-",Table32[[#This Row],[THIK]]) | E4: 3959449 | F4: CR COIL TATXHS BR03 1.600X1250
A5: Micro alloy | B5: BR45 | C5: 2 | D5: =_xlfn.CONCAT(Table32[[#This Row],[TDC]],"-",Table32[[#This Row],[THIK]]) | E5: 3820032 | F5: CR COIL TATXHS BR45 2X1300
A6: Micro alloy | B6: BR03 | C6: 2 | D6: =_xlfn.CONCAT(Table32[[#This Row],[TDC]],"-",Table32[[#This Row],[THIK]]) | E6: 3717653 | F6: CR COIL TATXHS BR03 2X1300
A7: Micro alloy | B7: BR03 | C7: 2 | D7: =_xlfn.CONCAT(Table32[[#This Row],[TDC]],"-",Table32[[#This Row],[THIK]]) | E7: 3959450 | F7: CR COIL TATXHS BR03 2X1250
A8: Micro alloy | B8: BR45 | C8: 2.3 | D8: =_xlfn.CONCAT(Table32[[#This Row],[TDC]],"-",Table32[[#This Row],[THIK]]) | E8: 3185984 | F8: CR COIL TSBHSL LA45 2.300X1300
A9: C20 | B9: TU99 | C9: 1.4 | D9: =_xlfn.CONCAT(Table32[[#This Row],[TDC]],"-",Table32[[#This Row],[THIK]]) | E9: 2279476 | F9: CRCA COIL TSBHSQ TU99 1.400X1270
A10: C20 | B10: TU99 | C10: 1.6 | D10: =_xlfn.CONCAT(Table32[[#This Row],[TDC]],"-",Table32[[#This Row],[THIK]]) | E10: 2279503 | F10: CRCA COIL TSBHSQ TU99 1.600X1270
A11: C20 | B11: TU99 | C11: 2 | D11: =_xlfn.CONCAT(Table32[[#This Row],[TDC]],"-",Table32[[#This Row],[THIK]]) | E11: 2279483 | F11: CRCA COIL TSBHSQ TU99 2 X1270
A12: C20 | B12: TU99 | C12: 2.3 | D12: =_xlfn.CONCAT(Table32[[#This Row],[TDC]],"-",Table32[[#This Row],[THIK]]) | E12: 3439077 | F12: CR COIL TSBHSQ TU99 2.300X1270
A13: CRCA | B13: TU98 | C13: 1 | D13: =_xlfn.CONCAT(Table32[[#This Row],[TDC]],"-",Table32[[#This Row],[THIK]]) | E13: 2150938 | F13: CRCA COIL SA1008 TU98 1X1250
... A18: CRCA | B18: TU98 | C18: 1.9 | D18: =_xlfn.CONCAT(Table32[[#This Row],[TDC]],"-",Table32[[#This Row],[THIK]]) | E18: 2150943 | F18: CRCA COIL SA1008 TU98 1.900X1250
A19: CRFH | B19: RE03 | C19: 1 | D19: =_xlfn.CONCAT(Table32[[#This Row],[Grade]],"-",Table32[[#This Row],[THIK]]) | E19: 2324172 | F19: CRFH COIL TATFHC RE03 1X1250
A20: CRFH | B20: RE04 | C20: 1 | D20: =_xlfn.CONCAT(Table32[[#This Row],[Grade]],"-",Table32[[#This Row],[THIK]]) | E20: 2390551 | F20: CRFH COIL TATFHC RE04 1X1250
A21: CRFH | B21: TI15 | C21: 1 | D21: =_xlfn.CONCAT(Table32[[#This Row],[Grade]],"-",Table32[[#This Row],[THIK]]) | E21: 3917262 | F21: CR COIL TATFHC TI15 1X500
A22: CRFH | B22: TI15 | C22: 1.2 | D22: =_xlfn.CONCAT(Table32[[#This Row],[Grade]],"-",Table32[[#This Row],[THIK]]) | E22: 3917263 | F22: CR COIL TATFHC TI15 1.150X500
A23: CRFH | B23: TI15 | C23: 1.2 | D23: =_xlfn.CONCAT(Table32[[#This Row],[Grade]],"-",Table32[[#This Row],[THIK]]) | E23: 3993061 | F23: CR COIL TATFHC TI15 1.200X500
A24: CRFH | B24: RE03 | C24: 1.2 | D24: =_xlfn.CONCAT(Table32[[#This Row],[TDC]],"-",Table32[[#This Row],[THIK]]) | E24: 2324181 | F24: CRFH COIL TATFHC RE03 1.200X1250
A25: HR | B25: TU02 | C25: 1.6 | D25: =_xlfn.CONCAT(Table32[[#This Row],[TDC]],"-",Table32[[#This Row],[THIK]]) | E25: 2271033 | F25: HRPO COIL T01579 TU02 1.60X1250
A26: HR | B26: HR99 | C26: 1.9 | D26: =_xlfn.CONCAT(Table32[[#This Row],[TDC]],"-",Table32[[#This Row],[THIK]]) | E26: 3226987 | F26: HR COILS-PO THR099 HR99 1.90X1250
A27: HR | B27: TU02 | C27: 1.9 | D27: =_xlfn.CONCAT(Table32[[#This Row],[TDC]],"-",Table32[[#This Row],[THIK]]) | E27: 4141061 | F27: HR COILS-PO T01579 1.90X1250
A28: HR | B28: HR99 | C28: 2 | D28: =_xlfn.CONCAT(Table32[[#This Row],[TDC]],"-",Table32[[#This Row],[THIK]]) | E28: 1210083 | F28: HR COILS-PO THR099 HR99 2X1250
A29: HR | B29: TU02 | C29: 2 | D29: =_xlfn.CONCAT(Table32[[#This Row],[TDC]],"-",Table32[[#This Row],[THIK]]) | E29: 2427980 | F29: HRPO COIL T01579 TU02 2X1250
A30: HR | B30: HR99 | C30: 2.3 | D30: =_xlfn.CONCAT(Table32[[#This Row],[TDC]],"-",Table32[[#This Row],[THIK]]) | E30: 1371338 | F30: HR COILS-PO IS 1079 HR2 2.30X1250
A31: HR | B31: TU02 | C31: 2.3 | D31: =_xlfn.CONCAT(Table32[[#This Row],[TDC]],"-",Table32[[#This Row],[THIK]]) | E31: 3433881 | F31: HR COILS-PO T01579 TU02 2.30X1250
A32: HR | B32: HR99 | C32: 2.5 | D32: =_xlfn.CONCAT(Table32[[#This Row],[TDC]],"-",Table32[[#This Row],[THIK]]) | E32: 1250221 | F32: HR COILS-POIS 1079 HR2 2.50X1250
A33: HR | B33: TU02 | C33: 2.5 | D33: =_xlfn.CONCAT(Table32[[#This Row],[TDC]],"-",Table32[[#This Row],[THIK]]) | E33: 1706343 | F33: HRPO COIL-T01579-TU02-2.5X1250
A34: HR | B34: TU02 | C34: 2.5 | D34: =_xlfn.CONCAT(Table32[[#This Row],[TDC]],"-",Table32[[#This Row],[THIK]]) | E34: 1328020 | F34: HR COILS-PO PT 2.50X1250
A35: HR | B35: HR99 | C35: 2.9 | D35: =_xlfn.CONCAT(Table32[[#This Row],[TDC]],"-",Table32[[#This Row],[THIK]]) | E35: 1294719 | F35: HR COILS-POIS 1079 HR2 2.90X1250
... A42: HR | B42: TU02 | C42: 3.4 | D42: =_xlfn.CONCAT(Table32[[#This Row],[TDC]],"-",Table32[[#This Row],[THIK]]) | E42: 3491196 | F42: HR COILS-PO T01579 3.40X1250
B44: TI15 | C44: 1 | D44: 3917262 | E44: CR COIL TATFHC TI15 1X500 | F44: 53 | G44: 20 | H44: 29
B45: TI15 | C45: 1.15 | D45: 3917263 | E45: CR COIL TATFHC TI15 1.150X500 | F45: 5
B46: TI15 | C46: 1.2 | D46: 3993061 | E46: CR COIL TATFHC TI15 1.200X500

Sheet saleswipstock_matnos
A1: Customer | B1: Mat Nos | C1: Mat Desc | D1: OEM | E1: Bucket
A2: Metalman Auto Private Limited | B2: 4229654 | C2: CUT-R-AW-AUT-50.00X30.00X2.500X0.7650 | D2: TVS | I2: 508988 | J2: {=_xlfn.UNIQUE(I2:I2507)} | L2: {=_xlfn._xlws.FILTER(_xlfn.ANCHORARRAY(J2),ISNA(_xlfn.XMATCH(_xlfn.ANCHORARRAY(J2),buckets[Material Codes])))}
A3: ELKAYEM AUTO ANCILLARIES PRIVA | B3: 4267147 | C3: TUB-E-O-AUT-AW-FC-22.23X2.000X0.7380 | D3: TVS | I3: 1442308 | J3: 1442308
A4: Rajsriya Automotive Industries | B4: 4020858 | C4: TUB-O-N-AUT-AW-FC-25.40X2.000X0.3230 | D4: TVS | I4: 2427711 | J4: 2427711
A5: Hosur Tube Plant | B5: 3999719 | C5: CR COIL TATFHC TI15 1.150X73.50 | D5: TVS | I5: 1188598 | J5: 1188598
A6: ELKAYEM AUTO ANCILLARIES PRIVA | B6: 4185618 | C6: TUB-O-N-AUT-AW-FC-28.58X1.600X0.4200 | D6: TVS | I6: 1399341 | J6: 1399341
I7: 3729146 | J7: 3729146
I8: 3910451 | J8: 3910451
I9: 3911993 | J9: 3911993
I10: 3911993 | J10: 1241174
I11: 3911993 | J11: 3520755
I12: 3911993 | J12: 460176
I13: 3911993 | J13: 3801263
I14: 1241174 | J14: 3746291
I15: 3520755 | J15: 1938127
I16: 3911993 | J16: 2396464
I17: 3911993 | J17: 1938125
I18: 3911993 | J18: 2359755
... I266: 3935313 | J266: 3617058
I267: 4100796
I268: 4104140
I269: 3571870
I270: 3571870
I271: 3572051
I272: 3572051
I273: 3572051
I274: 3572051
I275: 3572051
I276: 3572051
I277: 3572051
I278: 3572051
... I2507: 437147

Sheet Methodology
G2: Connection | I2: Connection | K2: Connection | N2: Connection | P2: Connection | R2: Connection
G3: Sales | I3: Stock | K3: Wip | N3: Sales | P3: Stock | R3: Wip
I5: Append | P5: Append
H6: Merge | I6: Customer | O6: Merge | P6: Material Codes
G9: Table | I9: OEM_Key Different Customer | N9: Table | P9: Material Codes different

Sheet saleswipstock_customer
A1: Customer | B1: OEM

Sheet OEM_key
A1: Customer | B1: OEM | C1: CAM
A2: A.R.Automotive And Engg Industries | B2: RE | C2: Abhishek
A3: BALAJI INDUSTRIES | B3: HMSIL | C3: Abhishek
A4: BALAJI PRESS PRODUCTS INDIA | B4: TVS | C4: Apoorv
A5: BCC PIPES & TUBES PRIVATE LIMITED | B5: GE | C5: Jitendra
A6: BHARAT TUBES CORPORATION | B6: Boiler | C6: Jitendra
A7: ELKAYEM AUTO ANCILLARIES (PVT) LTD. | B7: TVS | C7: Apoorv
A8: ELKAYEM AUTO ANCILLARIES PRIVATE LI | B8: TVS | C8: Apoorv
A9: ELKAYEM AUTO ANCILLARIES PVT LTD -U | B9: TVS | C9: Apoorv
A10: GANESH INDUSTRAIL SUPPLIES | B10: Boiler | C10: Jitendra
A11: Indo Autotech Limited (Unit V) | B11: HMSIL | C11: Abhishek
A12: JBM AUTO LIMITED | B12: RE | C12: Abhishek
... A162: SHIVAMPRIME STEELS PRIVATE LIMITED | B162: GE | C162: Jitendra

Sheet Pivot_schedule
A1: SCHEDULE | B1: (Multiple Items)
A3: Sum of SCHEDULE IN MT | I3: CUSTOMER NAME | J3: CUSTOMER CODE | K3: Sum of SCHEDULE IN MT
A4: 1716.4001 | I4: Balaji press product | J4: 189287 | K4: 82.236962
I5: ELKAYEM AUTO | J5: 129663|948721 | K5: 214.57233
I6: ELKAYEM AUTO | J6: 129663|948722 | K6: 0
I7: ELKAYEM AUTO MYSORE | J7: 940921 | K7: 145.13903
I8: KAY JAY | J8: 188934 | K8: 101.62486
I9: KNITVEL NEEDLES P LTD | J9: 819045 | K9: 14.667553
I10: Marathwada | J10: 189002 | K10: 169.05631
I11: Metalman | J11: 188647 | K11: 94.862777
I12: Narasipur Auto Component(P)Ltd | J12: 187546 | K12: 64.595236
I13: Rajsriya Automotive | J13: 129695|187884|188415|189239|189240 | K13: 0
I14: Rajsriya Mysore | J14: 930883|189481 | K14: 80.680238
I15: Rajsriya Unit 1 | J15: 129695|187884|188415|189239|189240 | K15: 55.249147
I16: Rajsriya Unit 2 | J16: 129695|187884|188415|189239|189240 | K16: 44.168937
I17: Rajsriya Unit 4 | J17: 129695|187884|188415|189239|189240 | K17: 6.2978864
I18: Rajsriya Unit 5 | J18: 129663|948721 | K18: 8.6266324
I19: Rajsriya Unit 5 | J19: 129695|187884|188415|189239|189240 | K19: 79.232149
I20: Rajsriya Unit 8 | J20: 129695|187884|188415|189239|189240 | K20: 155.45208
I21: RUCHA | J21: 188534 | K21: 0
I22: Sandhar Automach | J22: 187702 | K22: 143.98859
I23: Sandhar Engg Mysore | J23: 945539 | K23: 312.52478
I24: SANDHAR ENGINEERING PVT LTD. | J24: 941496 | K24: 154.59672
I25: SRI BALAJI GEARS V4 | J25: 188595 | K25: 14.696797
I26: SRIKAM HITECH | J26: 944141 | K26: 227.02088
I27: TVS MOTOR COMPANY LIMITED | J27: 187268 | K27: 0
I28: Laxmi | J28: 185254 | K28: 43.860601
I29: SRI BALAJI GEARS V7 | J29: 188595 | K29: 186.86168
I30: Marathwada v7 | J30: 189002 | K30: 201.9446
I31: Balaji Gears V3 | J31: 188595 | K31: 15.092951
I32: NMPL TVSM | J32: 189226 | K32: 0
I33: NMPL TVSM | J33: 189226|930794 | K33: 235.78584
I34: NMPL TVSM | J34: 930801|189227 | K34: 2.267357
I35: NMPL HUB | J35: 189226|930794 | K35: 0
I36: NMPL HUB | J36: 930801|189227 | K36: 198.42091

Sheet Schedule Pivot
A3: Sum of SCHEDULE IN MT
A4: CUSTOMER NAME | B4: Total
A5: Balaji press product | B5: 82.236962
A6: ELKAYEM AUTO | B6: 214.57233
A7: ELKAYEM AUTO MYSORE | B7: 145.13903
A8: KAY JAY | B8: 101.62486
A9: KNITVEL NEEDLES P LTD | B9: 14.667553
A10: Marathwada | B10: 169.05631
A11: Metalman | B11: 94.862777
A12: Narasipur Auto Component(P)Ltd | B12: 64.595236
A13: Rajsriya Automotive | B13: 0
A14: Rajsriya Mysore | B14: 80.680238
A15: Rajsriya Unit 1 | B15: 55.249147
A16: Rajsriya Unit 2 | B16: 44.168937
... A32: NMPL HUB | B32: 198.42091

Sheet nov indent
A1: OEM | B1: Customer Code | C1: Customer | D1: Metallurgy condition | E1: Material Type | F1: GRADE | G1: OD | H1: ID | I1: THK | J1: LENGTH | K1: Length in Mtrs | L1: Key | M1: Bucket | N1: Bucket CTL | O1: plant | P1: TSL Material Code | Q1: SCH SEP- 25 | R1: BALANCE TO BE SUPPLY | S1: Stock 22-09-25 | T1: intransist | U1: OPENIG STOCK FOR NOV-2025 | V1: order logg | W1: Opening stock including order logger | X1: INDENT FOR NOV-25 as per VSM | Y1: INDENT FOR NOV-25 recommended | Z1: Before 20th | AA1: ofter 20th | AB1: Total Indent | AC1: Total Supplied | AD1: Gap
A2: TVS | B2: 943209 | C2: RUCHA | D2: ERW1 | E2: NON FIN | F2: ERW | G2: 12.7 | I2: 1.2 | J2: 6000 | K2: 6 | L2: =_xlfn.CONCAT(G2,I2,K2,F2,E2) | M2: =VLOOKUP(Table27[[#This Row],[Key]],Table29[[#All],[Key]:[TSL Material Code3]],4,0) | N2: =VLOOKUP(Table27[[#This Row],[Key]],Table29[[#All],[Key]:[TSL Material Code3]],5,0) | O2: =VLOOKUP(Table27[[#This Row],[Key]],Table29[[#All],[Key]:[TSL Material Code3]],7,0) | P2: =VLOOKUP(Table27[[#This Row],[Key]],Table29[[#All],[Key]:[TSL Material Code3]],8,0) | Q2: 10 | R2: 3 | S2: 10 | T2: 0 | U2: =S2-R2 | W2: =U2+V2 | X2: =Q2-W2 | Y2: =IF(X2>0,X2,0)*150% | Z2: =ROUND(SUMIFS(meghsteelsales_previousmonth[Quantity],meghsteelsales_previousmonth[Length Bucket],Table27[[#This Row],[Bucket CTL]])/1000,0) | AA2: =ROUND(SUMIFS(meghsteelsales_currentmonth[Quantity],meghsteelsales_currentmonth[Length Bucket],Table27[[#This Row],[Bucket CTL]])/1000,0) | AB2: =Table27[[#This Row],[ INDENT FOR NOV-25 recommended]]+Table27[[#This Row],[order logg ]] | AC2: =Table27[[#This Row],[Before 20th]]+Table27[[#This Row],[ofter 20th]] | AD2: =IF(Table27[[#This Row],[Total Indent]]-Table27[[#This Row],[Total Supplied]]<0,0,Table27[[#This Row],[Total Indent]]-Table27[[#This Row],[Total Supplied]])
A3: HMSI | B3: 943210 | C3: BADVE | D3: ERW1 | E3: NON FIN | F3: ERW | G3: 12.7 | I3: 1.4 | J3: 6000 | K3: 6 | L3: =_xlfn.CONCAT(G3,I3,K3,F3,E3) | M3: =VLOOKUP(Table27[[#This Row],[Key]],Table29[[#All],[Key]:[TSL Material Code3]],4,0) | N3: =VLOOKUP(Table27[[#This Row],[Key]],Table29[[#All],[Key]:[TSL Material Code3]],5,0) | O3: =VLOOKUP(Table27[[#This Row],[Key]],Table29[[#All],[Key]:[TSL Material Code3]],7,0) | P3: =VLOOKUP(Table27[[#This Row],[Key]],Table29[[#All],[Key]:[TSL Material Code3]],8,0) | Q3: 5 | R3: 0 | S3: 5 | T3: 0 | U3: =S3-R3 | W3: =U3+V3 | X3: =Q3-W3 | Y3: =IF(X3>0,X3,0)*150% | Z3: =ROUND(SUMIFS(meghsteelsales_previousmonth[Quantity],meghsteelsales_previousmonth[Length Bucket],Table27[[#This Row],[Bucket CTL]])/1000,0) | AA3: =ROUND(SUMIFS(meghsteelsales_currentmonth[Quantity],meghsteelsales_currentmonth[Length Bucket],Table27[[#This Row],[Bucket CTL]])/1000,0) | AB3: =Table27[[#This Row],[ INDENT FOR NOV-25 recommended]]+Table27[[#This Row],[order logg ]] | AC3: =Table27[[#This Row],[Before 20th]]+Table27[[#This Row],[ofter 20th]] | AD3: =IF(Table27[[#This Row],[Total Indent]]-Table27[[#This Row],[Total Supplied]]<0,0,Table27[[#This Row],[Total Indent]]-Table27[[#This Row],[Total Supplied]])
A4: HMSI | B4: 943210 | C4: BADVE | D4: ERW1 | E4: NON FIN | F4: ERW | G4: 12.7 | I4: 1.6 | J4: 6000 | K4: 6 | L4: =_xlfn.CONCAT(G4,I4,K4,F4,E4) | M4: =VLOOKUP(Table27[[#This Row],[Key]],Table29[[#All],[Key]:[TSL Material Code3]],4,0) | N4: =VLOOKUP(Table27[[#This Row],[Key]],Table29[[#All],[Key]:[TSL Material Code3]],5,0) | O4: =VLOOKUP(Table27[[#This Row],[Key]],Table29[[#All],[Key]:[TSL Material Code3]],7,0) | P4: =VLOOKUP(Table27[[#This Row],[Key]],Table29[[#All],[Key]:[TSL Material Code3]],8,0) | Q4: 5 | R4: 1 | S4: 3 | T4: 0 | U4: =S4-R4 | W4: =U4+V4 | X4: =Q4-W4 | Y4: =IF(X4>0,X4,0)*150% | Z4: =ROUND(SUMIFS(meghsteelsales_previousmonth[Quantity],meghsteelsales_previousmonth[Length Bucket],Table27[[#This Row],[Bucket CTL]])/1000,0) | AA4: =ROUND(SUMIFS(meghsteelsales_currentmonth[Quantity],meghsteelsales_currentmonth[Length Bucket],Table27[[#This Row],[Bucket CTL]])/1000,0) | AB4: =Table27[[#This Row],[ INDENT FOR NOV-25 recommended]]+Table27[[#This Row],[order logg ]] | AC4: =Table27[[#This Row],[Before 20th]]+Table27[[#This Row],[ofter 20th]] | AD4: =IF(Table27[[#This Row],[Total Indent]]-Table27[[#This Row],[Total Supplied]]<0,0,Table27[[#This Row],[Total Indent]]-Table27[[#This Row],[Total Supplied]])
A5: HMSI | B5: 943210 | C5: BADVE | D5: ERW1 | E5: NON FIN | F5: ERW | G5: 15.88 | I5: 1 | J5: 6000 | K5: 6 | L5: =_xlfn.CONCAT(G5,I5,K5,F5,E5) | M5: =VLOOKUP(Table27[[#This Row],[Key]],Table29[[#All],[Key]:[TSL Material Code3]],4,0) | N5: =VLOOKUP(Table27[[#This Row],[Key]],Table29[[#All],[Key]:[TSL Material Code3]],5,0) | O5: =VLOOKUP(Table27[[#This Row],[Key]],Table29[[#All],[Key]:[TSL Material Code3]],7,0) | P5: =VLOOKUP(Table27[[#This Row],[Key]],Table29[[#All],[Key]:[TSL Material Code3]],8,0) | Q5: 1 | R5: 0 | S5: 1.4 | T5: 0 | U5: =S5-R5 | W5: =U5+V5 | X5: =Q5-W5 | Y5: =IF(X5>0,X5,0)*150% | Z5: =ROUND(SUMIFS(meghsteelsales_previousmonth[Quantity],meghsteelsales_previousmonth[Length Bucket],Table27[[#This Row],[Bucket CTL]])/1000,0) | AA5: =ROUND(SUMIFS(meghsteelsales_currentmonth[Quantity],meghsteelsales_currentmonth[Length Bucket],Table27[[#This Row],[Bucket CTL]])/1000,0) | AB5: =Table27[[#This Row],[ INDENT FOR NOV-25 recommended]]+Table27[[#This Row],[order logg ]] | AC5: =Table27[[#This Row],[Before 20th]]+Table27[[#This Row],[ofter 20th]] | AD5: =IF(Table27[[#This Row],[Total Indent]]-Table27[[#This Row],[Total Supplied]]<0,0,Table27[[#This Row],[Total Indent]]-Table27[[#This Row],[Total Supplied]])
A6: TVS | B6: 943209 | C6: RUCHA | D6: ERW1 | E6: NON FIN | F6: ERW | G6: 15.88 | I6: 1.2 | J6: 6000 | K6: 6 | L6: =_xlfn.CONCAT(G6,I6,K6,F6,E6) | M6: =VLOOKUP(Table27[[#This Row],[Key]],Table29[[#All],[Key]:[TSL Material Code3]],4,0) | N6: =VLOOKUP(Table27[[#This Row],[Key]],Table29[[#All],[Key]:[TSL Material Code3]],5,0) | O6: =VLOOKUP(Table27[[#This Row],[Key]],Table29[[#All],[Key]:[TSL Material Code3]],7,0) | P6: =VLOOKUP(Table27[[#This Row],[Key]],Table29[[#All],[Key]:[TSL Material Code3]],8,0) | Q6: 8 | R6: 4 | S6: 22.4 | T6: 0 | U6: =S6-R6 | W6: =U6+V6 | X6: =Q6-W6 | Y6: =IF(X6>0,X6,0)*150% | Z6: =ROUND(SUMIFS(meghsteelsales_previousmonth[Quantity],meghsteelsales_previousmonth[Length Bucket],Table27[[#This Row],[Bucket CTL]])/1000,0) | AA6: =ROUND(SUMIFS(meghsteelsales_currentmonth[Quantity],meghsteelsales_currentmonth[Length Bucket],Table27[[#This Row],[Bucket CTL]])/1000,0) | AB6: =Table27[[#This Row],[ INDENT FOR NOV-25 recommended]]+Table27[[#This Row],[order logg ]] | AC6: =Table27[[#This Row],[Before 20th]]+Table27[[#This Row],[ofter 20th]] | AD6: =IF(Table27[[#This Row],[Total Indent]]-Table27[[#This Row],[Total Supplied]]<0,0,Table27[[#This Row],[Total Indent]]-Table27[[#This Row],[Total Supplied]])
A7: HMSI | B7: 943210 | C7: BADVE | D7: ERW1 | E7: NON FIN | F7: ERW | G7: 15.88 | I7: 1.6 | J7: 6000 | K7: 6 | L7: =_xlfn.CONCAT(G7,I7,K7,F7,E7) | M7: =VLOOKUP(Table27[[#This Row],[Key]],Table29[[#All],[Key]:[TSL Material Code3]],4,0) | N7: =VLOOKUP(Table27[[#This Row],[Key]],Table29[[#All],[Key]:[TSL Material Code3]],5,0) | O7: =VLOOKUP(Table27[[#This Row],[Key]],Table29[[#All],[Key]:[TSL Material Code3]],7,0) | P7: =VLOOKUP(Table27[[#This Row],[Key]],Table29[[#All],[Key]:[TSL Material Code3]],8,0) | Q7: 5 | R7: 2 | S7: 0.5 | T7: 2.75 | U7: =S7-R7 | W7: =U7+V7 | X7: =Q7-W7 | Y7: =IF(X7>0,X7,0)*150% | Z7: =ROUND(SUMIFS(meghsteelsales_previousmonth[Quantity],meghsteelsales_previousmonth[Length Bucket],Table27[[#This Row],[Bucket CTL]])/1000,0) | AA7: =ROUND(SUMIFS(meghsteelsales_currentmonth[Quantity],meghsteelsales_currentmonth[Length Bucket],Table27[[#This Row],[Bucket CTL]])/1000,0) | AB7: =Table27[[#This Row],[ INDENT FOR NOV-25 recommended]]+Table27[[#This Row],[order logg ]] | AC7: =Table27[[#This Row],[Before 20th]]+Table27[[#This Row],[ofter 20th]] | AD7: =IF(Table27[[#This Row],[Total Indent]]-Table27[[#This Row],[Total Supplied]]<0,0,Table27[[#This Row],[Total Indent]]-Table27[[#This Row],[Total Supplied]])
A8: HMSI | B8: 943210 | C8: BADVE | D8: ERW1 | E8: NON FIN | F8: ERW | G8: 15.88 | I8: 2 | J8: 6000 | K8: 6 | L8: =_xlfn.CONCAT(G8,I8,K8,F8,E8) | M8: =VLOOKUP(Table27[[#This Row],[Key]],Table29[[#All],[Key]:[TSL Material Code3]],4,0) | N8: =VLOOKUP(Table27[[#This Row],[Key]],Table29[[#All],[Key]:[TSL Material Code3]],5,0) | O8: =VLOOKUP(Table27[[#This Row],[Key]],Table29[[#All],[Key]:[TSL Material Code3]],7,0) | P8: =VLOOKUP(Table27[[#This Row],[Key]],Table29[[#All],[Key]:[TSL Material Code3]],8,0) | Q8: 5 | R8: 1 | S8: 10 | T8: 0 | U8: =S8-R8 | W8: =U8+V8 | X8: =Q8-W8 | Y8: =IF(X8>0,X8,0)*150% | Z8: =ROUND(SUMIFS(meghsteelsales_previousmonth[Quantity],meghsteelsales_previousmonth[Length Bucket],Table27[[#This Row],[Bucket CTL]])/1000,0) | AA8: =ROUND(SUMIFS(meghsteelsales_currentmonth[Quantity],meghsteelsales_currentmonth[Length Bucket],Table27[[#This Row],[Bucket CTL]])/1000,0) | AB8: =Table27[[#This Row],[ INDENT FOR NOV-25 recommended]]+Table27[[#This Row],[order logg ]] | AC8: =Table27[[#This Row],[Before 20th]]+Table27[[#This Row],[ofter 20th]] | AD8: =IF(Table27[[#This Row],[Total Indent]]-Table27[[#This Row],[Total Supplied]]<0,0,Table27[[#This Row],[Total Indent]]-Table27[[#This Row],[Total Supplied]])
A9: TVS | B9: 943209 | C9: Rucha | D9: ERW1 | E9: NON FIN | F9: ERW | G9: 18.2 | I9: 1 | J9: 6000 | K9: 6 | L9: =_xlfn.CONCAT(G9,I9,K9,F9,E9) | M9: =VLOOKUP(Table27[[#This Row],[Key]],Table29[[#All],[Key]:[TSL Material Code3]],4,0) | N9: =VLOOKUP(Table27[[#This Row],[Key]],Table29[[#All],[Key]:[TSL Material Code3]],5,0) | O9: =VLOOKUP(Table27[[#This Row],[Key]],Table29[[#All],[Key]:[TSL Material Code3]],7,0) | P9: =VLOOKUP(Table27[[#This Row],[Key]],Table29[[#All],[Key]:[TSL Material Code3]],8,0) | Q9: 10 | R9: 5 | S9: 8.8 | T9: 0 | U9: =S9-R9 | W9: =U9+V9 | X9: =Q9-W9 | Y9: =IF(X9>0,X9,0)*150% | Z9: =ROUND(SUMIFS(meghsteelsales_previousmonth[Quantity],meghsteelsales_previousmonth[Length Bucket],Table27[[#This Row],[Bucket CTL]])/1000,0) | AA9: =ROUND(SUMIFS(meghsteelsales_currentmonth[Quantity],meghsteelsales_currentmonth[Length Bucket],Table27[[#This Row],[Bucket CTL]])/1000,0) | AB9: =Table27[[#This Row],[ INDENT FOR NOV-25 recommended]]+Table27[[#This Row],[order logg ]] | AC9: =Table27[[#This Row],[Before 20th]]+Table27[[#This Row],[ofter 20th]] | AD9: =IF(Table27[[#This Row],[Total Indent]]-Table27[[#This Row],[Total Supplied]]<0,0,Table27[[#This Row],[Total Indent]]-Table27[[#This Row],[Total Supplied]])
A10: HMSI | B10: 943210 | C10: BADVE | D10: ERW1 | E10: NON FIN | F10: ERW | G10: 19.05 | I10: 1.6 | J10: 6000 | K10: 6 | L10: =_xlfn.CONCAT(G10,I10,K10,F10,E10) | M10: =VLOOKUP(Table27[[#This Row],[Key]],Table29[[#All],[Key]:[TSL Material Code3]],4,0) | N10: =VLOOKUP(Table27[[#This Row],[Key]],Table29[[#All],[Key]:[TSL Material Code3]],5,0) | O10: =VLOOKUP(Table27[[#This Row],[Key]],Table29[[#All],[Key]:[TSL Material Code3]],7,0) | P10: =VLOOKUP(Table27[[#This Row],[Key]],Table29[[#All],[Key]:[TSL Material Code3]],8,0) | Q10: 10 | R10: 5 | S10: 14 | T10: 0 | U10: =S10-R10 | V10: 2.7 | W10: =U10+V10 | X10: =Q10-W10 | Y10: =IF(X10>0,X10,0)*150% | Z10: =ROUND(SUMIFS(meghsteelsales_previousmonth[Quantity],meghsteelsales_previousmonth[Length Bucket],Table27[[#This Row],[Bucket CTL]])/1000,0) | AA10: =ROUND(SUMIFS(meghsteelsales_currentmonth[Quantity],meghsteelsales_currentmonth[Length Bucket],Table27[[#This Row],[Bucket CTL]])/1000,0) | AB10: =Table27[[#This Row],[ INDENT FOR NOV-25 recommended]]+Table27[[#This Row],[order logg ]] | AC10: =Table27[[#This Row],[Before 20th]]+Table27[[#This Row],[ofter 20th]] | AD10: =IF(Table27[[#This Row],[Total Indent]]-Table27[[#This Row],[Total Supplied]]<0,0,Table27[[#This Row],[Total Indent]]-Table27[[#This Row],[Total Supplied]])
A11: HMSI | B11: 943210 | C11: BADVE | D11: ERW2 | E11: NON FIN | F11: ERW2 | G11: 19.05 | I11: 1.4 | J11: 6000 | K11: 6 | L11: =_xlfn.CONCAT(G11,I11,K11,F11,E11) | M11: =VLOOKUP(Table27[[#This Row],[Key]],Table29[[#All],[Key]:[TSL Material Code3]],4,0) | N11: =VLOOKUP(Table27[[#This Row],[Key]],Table29[[#All],[Key]:[TSL Material Code3]],5,0) | O11: =VLOOKUP(Table27[[#This Row],[Key]],Table29[[#All],[Key]:[TSL Material Code3]],7,0) | P11: =VLOOKUP(Table27[[#This Row],[Key]],Table29[[#All],[Key]:[TSL Material Code3]],8,0) | Q11: 10 | R11: 3 | S11: 0 | T11: 0 | U11: =S11-R11 | V11: 10 | W11: =U11+V11 | X11: =Q11-W11 | Y11: =IF(X11>0,X11,0)*150% | Z11: =ROUND(SUMIFS(meghsteelsales_previousmonth[Quantity],meghsteelsales_previousmonth[Length Bucket],Table27[[#This Row],[Bucket CTL]])/1000,0) | AA11: =ROUND(SUMIFS(meghsteelsales_currentmonth[Quantity],meghsteelsales_currentmonth[Length Bucket],Table27[[#This Row],[Bucket CTL]])/1000,0) | AB11: =Table27[[#This Row],[ INDENT FOR NOV-25 recommended]]+Table27[[#This Row],[order logg ]] | AC11: =Table27[[#This Row],[Before 20th]]+Table27[[#This Row],[ofter 20th]] | AD11: =IF(Table27[[#This Row],[Total Indent]]-Table27[[#This Row],[Total Supplied]]<0,0,Table27[[#This Row],[Total Indent]]-Table27[[#This Row],[Total Supplied]])
A12: TVS | B12: 943209 | C12: RUCHA | D12: ERW1 | E12: NON FIN | F12: ERW | G12: 19.05 | I12: 2 | J12: 5800 | K12: 5.8 | L12: =_xlfn.CONCAT(G12,I12,K12,F12,E12) | M12: =VLOOKUP(Table27[[#This Row],[Key]],Table29[[#All],[Key]:[TSL Material Code3]],4,0) | N12: =VLOOKUP(Table27[[#This Row],[Key]],Table29[[#All],[Key]:[TSL Material Code3]],5,0) | O12: 0789 | P12: =VLOOKUP(Table27[[#This Row],[Key]],Table29[[#All],[Key]:[TSL Material Code3]],8,0) | Q12: 35 | R12: 10 | S12: 6 | T12: 0 | U12: 0 | W12: =U12+V12 | X12: =Q12-W12 | Y12: =IF(X12>0,X12,0)*150% | Z12: =ROUND(SUMIFS(meghsteelsales_previousmonth[Quantity],meghsteelsales_previousmonth[Length Bucket],Table27[[#This Row],[Bucket CTL]])/1000,0) | AA12: =ROUND(SUMIFS(meghsteelsales_currentmonth[Quantity],meghsteelsales_currentmonth[Length Bucket],Table27[[#This Row],[Bucket CTL]])/1000,0) | AB12: =Table27[[#This Row],[ INDENT FOR NOV-25 recommended]]+Table27[[#This Row],[order logg ]] | AC12: =Table27[[#This Row],[Before 20th]]+Table27[[#This Row],[ofter 20th]] | AD12: =IF(Table27[[#This Row],[Total Indent]]-Table27[[#This Row],[Total Supplied]]<0,0,Table27[[#This Row],[Total Indent]]-Table27[[#This Row],[Total Supplied]])
A13: TVS | B13: 943209 | C13: RUCHA,METALMAN | D13: ERW1 | E13: NON FIN | F13: ERW | G13: 19.05 | I13: 2.3 | J13: 7000 | K13: 7 | L13: =_xlfn.CONCAT(G13,I13,K13,F13,E13) | M13: =VLOOKUP(Table27[[#This Row],[Key]],Table29[[#All],[Key]:[TSL Material Code3]],4,0) | N13: =VLOOKUP(Table27[[#This Row],[Key]],Table29[[#All],[Key]:[TSL Material Code3]],5,0) | O13: =VLOOKUP(Table27[[#This Row],[Key]],Table29[[#All],[Key]:[TSL Material Code3]],7,0) | P13: =VLOOKUP(Table27[[#This Row],[Key]],Table29[[#All],[Key]:[TSL Material Code3]],8,0) | Q13: 20 | R13: 10 | S13: 39 | T13: 0 | U13: =S13-R13 | W13: =U13+V13 | X13: =Q13-W13 | Y13: =IF(X13>0,X13,0)*150% | Z13: =ROUND(SUMIFS(meghsteelsales_previousmonth[Quantity],meghsteelsales_previousmonth[Length Bucket],Table27[[#This Row],[Bucket CTL]])/1000,0) | AA13: =ROUND(SUMIFS(meghsteelsales_currentmonth[Quantity],meghsteelsales_currentmonth[Length Bucket],Table27[[#This Row],[Bucket CTL]])/1000,0) | AB13: =Table27[[#This Row],[ INDENT FOR NOV-25 recommended]]+Table27[[#This Row],[order logg ]] | AC13: =Table27[[#This Row],[Before 20th]]+Table27[[#This Row],[ofter 20th]] | AD13: =IF(Table27[[#This Row],[Total Indent]]-Table27[[#This Row],[Total Supplied]]<0,0,Table27[[#This Row],[Total Indent]]-Table27[[#This Row],[Total Supplied]])
A14: TVS | B14: 943209 | C14: RUCHA | D14: ERW1 | E14: NON FIN | F14: ERW | G14: 21.4 | I14: 1.6 | J14: 6000 | K14: 6 | L14: =_xlfn.CONCAT(G14,I14,K14,F14,E14) | M14: =VLOOKUP(Table27[[#This Row],[Key]],Table29[[#All],[Key]:[TSL Material Code3]],4,0) | N14: =VLOOKUP(Table27[[#This Row],[Key]],Table29[[#All],[Key]:[TSL Material Code3]],5,0) | O14: =VLOOKUP(Table27[[#This Row],[Key]],Table29[[#All],[Key]:[TSL Material Code3]],7,0) | P14: =VLOOKUP(Table27[[#This Row],[Key]],Table29[[#All],[Key]:[TSL Material Code3]],8,0) | Q14: 10 | R14: 3 | S14: 14.3 | T14: 0 | U14: =S14-R14 | W14: =U14+V14 | X14: =Q14-W14 | Y14: =IF(X14>0,X14,0)*150% | Z14: =ROUND(SUMIFS(meghsteelsales_previousmonth[Quantity],meghsteelsales_previousmonth[Length Bucket],Table27[[#This Row],[Bucket CTL]])/1000,0) | AA14: =ROUND(SUMIFS(meghsteelsales_currentmonth[Quantity],meghsteelsales_currentmonth[Length Bucket],Table27[[#This Row],[Bucket CTL]])/1000,0) | AB14: =Table27[[#This Row],[ INDENT FOR NOV-25 recommended]]+Table27[[#This Row],[order logg ]] | AC14: =Table27[[#This Row],[Before 20th]]+Table27[[#This Row],[ofter 20th]] | AD14: =IF(Table27[[#This Row],[Total Indent]]-Table27[[#This Row],[Total Supplied]]<0,0,Table27[[#This Row],[Total Indent]]-Table27[[#This Row],[Total Supplied]])
A15: TVS | B15: 943209 | C15: RUCHA | D15: ERW1 | E15: NON FIN | F15: ERW | G15: 22.2 | I15: 1.2 | J15: 5870 | K15: 5.87 | L15: =_xlfn.CONCAT(G15,I15,K15,F15,E15) | M15: =VLOOKUP(Table27[[#This Row],[Key]],Table29[[#All],[Key]:[TSL Material Code3]],4,0) | N15: =VLOOKUP(Table27[[#This Row],[Key]],Table29[[#All],[Key]:[TSL Material Code3]],5,0) | O15: =VLOOKUP(Table27[[#This Row],[Key]],Table29[[#All],[Key]:[TSL Material Code3]],7,0) | P15: =VLOOKUP(Table27[[#This Row],[Key]],Table29[[#All],[Key]:[TSL Material Code3]],8,0) | Q15: 30 | R15: 10 | S15: 7 | T15: 15.8 | U15: =S15-R15 | V15: 6 | W15: =U15+V15 | X15: =Q15-W15 | Y15: =IF(X15>0,X15,0)*150% | Z15: =ROUND(SUMIFS(meghsteelsales_previousmonth[Quantity],meghsteelsales_previousmonth[Length Bucket],Table27[[#This Row],[Bucket CTL]])/1000,0) | AA15: =ROUND(SUMIFS(meghsteelsales_currentmonth[Quantity],meghsteelsales_currentmonth[Length Bucket],Table27[[#This Row],[Bucket CTL]])/1000,0) | AB15: =Table27[[#This Row],[ INDENT FOR NOV-25 recommended]]+Table27[[#This Row],[order logg ]] | AC15: =Table27[[#This Row],[Before 20th]]+Table27[[#This Row],[ofter 20th]] | AD15: =IF(Table27[[#This Row],[Total Indent]]-Table27[[#This Row],[Total Supplied]]<0,0,Table27[[#This Row],[Total Indent]]-Table27[[#This Row],[Total Supplied]])
A16: HMSI | B16: 943210 | C16: BADVE | D16: ERW2 | E16: NON FIN | F16: ERW-2 | G16: 22.2 | I16: 1.4 | J16: 6000 | K16: 6 | L16: =_xlfn.CONCAT(G16,I16,K16,F16,E16) | M16: =VLOOKUP(Table27[[#This Row],[Key]],Table29[[#All],[Key]:[TSL Material Code3]],4,0) | N16: =VLOOKUP(Table27[[#This Row],[Key]],Table29[[#All],[Key]:[TSL Material Code3]],5,0) | O16: =VLOOKUP(Table27[[#This Row],[Key]],Table29[[#All],[Key]:[TSL Material Code3]],7,0) | P16: =VLOOKUP(Table27[[#This Row],[Key]],Table29[[#All],[Key]:[TSL Material Code3]],8,0) | Q16: 10 | R16: 3 | S16: 19 | T16: 0 | U16: =S16-R16 | W16: =U16+V16 | X16: =Q16-W16 | Y16: =IF(X16>0,X16,0)*150% | Z16: =ROUND(SUMIFS(meghsteelsales_previousmonth[Quantity],meghsteelsales_previousmonth[Length Bucket],Table27[[#This Row],[Bucket CTL]])/1000,0) | AA16: =ROUND(SUMIFS(meghsteelsales_currentmonth[Quantity],meghsteelsales_currentmonth[Length Bucket],Table27[[#This Row],[Bucket CTL]])/1000,0) | AB16: =Table27[[#This Row],[ INDENT FOR NOV-25 recommended]]+Table27[[#This Row],[order logg ]] | AC16: =Table27[[#This Row],[Before 20th]]+Table27[[#This Row],[ofter 20th]] | AD16: =IF(Table27[[#This Row],[Total Indent]]-Table27[[#This Row],[Total Supplied]]<0,0,Table27[[#This Row],[Total Indent]]-Table27[[#This Row],[Total Supplied]])
A17: TVS | B17: 943209 | C17: RUCHA | D17: ERW1 | E17: NON FIN | F17: ERW | G17: 22.2 | I17: 1.6 | J17: 5270 | K17: 5.27 | L17: =_xlfn.CONCAT(G17,I17,K17,F17,E17) | M17: =VLOOKUP(Table27[[#This Row],[Key]],Table29[[#All],[Key]:[TSL Material Code3]],4,0) | N17: =VLOOKUP(Table27[[#This Row],[Key]],Table29[[#All],[Key]:[TSL Material Code3]],5,0) | O17: =VLOOKUP(Table27[[#This Row],[Key]],Table29[[#All],[Key]:[TSL Material Code3]],7,0) | P17: =VLOOKUP(Table27[[#This Row],[Key]],Table29[[#All],[Key]:[TSL Material Code3]],8,0) | Q17: 30 | R17: 15 | S17: 5 | T17: 0 | U17: =S17-R17 | W17: =U17+V17 | X17: =Q17-W17 | Y17: =IF(X17>0,X17,0)*150% | Z17: =ROUND(SUMIFS(meghsteelsales_previousmonth[Quantity],meghsteelsales_previousmonth[Length Bucket],Table27[[#This Row],[Bucket CTL]])/1000,0) | AA17: =ROUND(SUMIFS(meghsteelsales_currentmonth[Quantity],meghsteelsales_currentmonth[Length Bucket],Table27[[#This Row],[Bucket CTL]])/1000,0) | AB17: =Table27[[#This Row],[ INDENT FOR NOV-25 recommended]]+Table27[[#This Row],[order logg ]] | AC17: =Table27[[#This Row],[Before 20th]]+Table27[[#This Row],[ofter 20th]] | AD17: =IF(Table27[[#This Row],[Total Indent]]-Table27[[#This Row],[Total Supplied]]<0,0,Table27[[#This Row],[Total Indent]]-Table27[[#This Row],[Total Supplied]])
A18: TVS | B18: 943209 | C18: RUCHA | D18: ERW1 | E18: NON FIN | F18: ERW | G18: 22.2 | I18: 1.6 | J18: 5670 | K18: 5.67 | L18: =_xlfn.CONCAT(G18,I18,K18,F18,E18) | M18: =VLOOKUP(Table27[[#This Row],[Key]],Table29[[#All],[Key]:[TSL Material Code3]],4,0) | N18: =VLOOKUP(Table27[[#This Row],[Key]],Table29[[#All],[Key]:[TSL Material Code3]],5,0) | O18: =VLOOKUP(Table27[[#This Row],[Key]],Table29[[#All],[Key]:[TSL Material Code3]],7,0) | P18: =VLOOKUP(Table27[[#This Row],[Key]],Table29[[#All],[Key]:[TSL Material Code3]],8,0) | Q18: 30 | R18: 10 | S18: 25.6 | T18: 0 | U18: =S18-R18 | W18: =U18+V18 | X18: =Q18-W18 | Y18: =IF(X18>0,X18,0)*150% | Z18: =ROUND(SUMIFS(meghsteelsales_previousmonth[Quantity],meghsteelsales_previousmonth[Length Bucket],Table27[[#This Row],[Bucket CTL]])/1000,0) | AA18: =ROUND(SUMIFS(meghsteelsales_currentmonth[Quantity],meghsteelsales_currentmonth[Length Bucket],Table27[[#This Row],[Bucket CTL]])/1000,0) | AB18: =Table27[[#This Row],[ INDENT FOR NOV-25 recommended]]+Table27[[#This Row],[order logg ]] | AC18: =Table27[[#This Row],[Before 20th]]+Table27[[#This Row],[ofter 20th]] | AD18: =IF(Table27[[#This Row],[Total Indent]]-Table27[[#This Row],[Total Supplied]]<0,0,Table27[[#This Row],[Total Indent]]-Table27[[#This Row],[Total Supplied]])
A19: TVS | B19: 943209 | C19: RUCHA | D19: ERW1 | E19: NON FIN | F19: ERW | G19: 22.2 | I19: 2 | J19: 5950 | K19: 5.95 | L19: =_xlfn.CONCAT(G19,I19,K19,F19,E19) | M19: =VLOOKUP(Table27[[#This Row],[Key]],Table29[[#All],[Key]:[TSL Material Code3]],4,0) | N19: =VLOOKUP(Table27[[#This Row],[Key]],Table29[[#All],[Key]:[TSL Material Code3]],5,0) | O19: =VLOOKUP(Table27[[#This Row],[Key]],Table29[[#All],[Key]:[TSL Material Code3]],7,0) | P19: =VLOOKUP(Table27[[#This Row],[Key]],Table29[[#All],[Key]:[TSL Material Code3]],8,0) | Q19: 80 | R19: 30 | S19: 5.8 | T19: 0 | U19: =S19-R19 | V19: 46.6 | W19: =U19+V19 | X19: =Q19-W19 | Y19: =IF(X19>0,X19,0)*150% | Z19: =ROUND(SUMIFS(meghsteelsales_previousmonth[Quantity],meghsteelsales_previousmonth[Length Bucket],Table27[[#This Row],[Bucket CTL]])/1000,0) | AA19: =ROUND(SUMIFS(meghsteelsales_currentmonth[Quantity],meghsteelsales_currentmonth[Length Bucket],Table27[[#This Row],[Bucket CTL]])/1000,0) | AB19: =Table27[[#This Row],[ INDENT FOR NOV-25 recommended]]+Table27[[#This Row],[order logg ]] | AC19: =Table27[[#This Row],[Before 20th]]+Table27[[#This Row],[ofter 20th]] | AD19: =IF(Table27[[#This Row],[Total Indent]]-Table27[[#This Row],[Total Supplied]]<0,0,Table27[[#This Row],[Total Indent]]-Table27[[#This Row],[Total Supplied]])
A20: TVS | B20: 943209 | C20: RUCHA | D20: ERW1 | E20: NON FIN | F20: ERW | G20: 22.2 | I20: 2 | J20: 5100 | K20: 5.1 | L20: =_xlfn.CONCAT(G20,I20,K20,F20,E20) | M20: =VLOOKUP(Table27[[#This Row],[Key]],Table29[[#All],[Key]:[TSL Material Code3]],4,0) | N20: =VLOOKUP(Table27[[#This Row],[Key]],Table29[[#All],[Key]:[TSL Material Code3]],5,0) | O20: =VLOOKUP(Table27[[#This Row],[Key]],Table29[[#All],[Key]:[TSL Material Code3]],7,0) | P20: =VLOOKUP(Table27[[#This Row],[Key]],Table29[[#All],[Key]:[TSL Material Code3]],8,0) | Q20: 20 | R20: 5 | S20: 19 | T20: 0 | U20: =S20-R20 | V20: 7 | W20: =U20+V20 | X20: =Q20-W20 | Y20: =IF(X20>0,X20,0)*150% | Z20: =ROUND(SUMIFS(meghsteelsales_previousmonth[Quantity],meghsteelsales_previousmonth[Length Bucket],Table27[[#This Row],[Bucket CTL]])/1000,0) | AA20: =ROUND(SUMIFS(meghsteelsales_currentmonth[Quantity],meghsteelsales_currentmonth[Length Bucket],Table27[[#This Row],[Bucket CTL]])/1000,0) | AB20: =Table27[[#This Row],[ INDENT FOR NOV-25 recommended]]+Table27[[#This Row],[order logg ]] | AC20: =Table27[[#This Row],[Before 20th]]+Table27[[#This Row],[ofter 20th]] | AD20: =IF(Table27[[#This Row],[Total Indent]]-Table27[[#This Row],[Total Supplied]]<0,0,Table27[[#This Row],[Total Indent]]-Table27[[#This Row],[Total Supplied]])
A21: TVS | B21: 943209 | C21: RUCHA | D21: ERW2 | E21: FIN CUT | F21: HST | G21: 22.2 | I21: 2 | J21: 6000 | K21: 6000 | L21: =_xlfn.CONCAT(G21,I21,K21,F21,E21) | M21: =VLOOKUP(Table27[[#This Row],[Key]],Table29[[#All],[Key]:[TSL Material Code3]],4,0) | N21: =VLOOKUP(Table27[[#This Row],[Key]],Table29[[#All],[Key]:[TSL Material Code3]],5,0) | O21: =VLOOKUP(Table27[[#This Row],[Key]],Table29[[#All],[Key]:[TSL Material Code3]],7,0) | P21: =VLOOKUP(Table27[[#This Row],[Key]],Table29[[#All],[Key]:[TSL Material Code3]],8,0) | Q21: 40 | R21: 15 | S21: 57 | T21: 0 | U21: =S21-R21 | W21: =U21+V21 | X21: =Q21-W21 | Y21: =IF(X21>0,X21,0)*150% | Z21: =ROUND(SUMIFS(meghsteelsales_previousmonth[Quantity],meghsteelsales_previousmonth[Length Bucket],Table27[[#This Row],[Bucket CTL]])/1000,0) | AA21: =ROUND(SUMIFS(meghsteelsales_currentmonth[Quantity],meghsteelsales_currentmonth[Length Bucket],Table27[[#This Row],[Bucket CTL]])/1000,0) | AB21: =Table27[[#This Row],[ INDENT FOR NOV-25 recommended]]+Table27[[#This Row],[order logg ]] | AC21: =Table27[[#This Row],[Before 20th]]+Table27[[#This Row],[ofter 20th]] | AD21: =IF(Table27[[#This Row],[Total Indent]]-Table27[[#This Row],[Total Supplied]]<0,0,Table27[[#This Row],[Total Indent]]-Table27[[#This Row],[Total Supplied]])
A22: HMSI | B22: 943210 | C22: BADVE | D22: CR ERW 1 | E22: FIN CUT | F22: CR ERW | G22: 22.2 | I22: 2 | J22: 5390 | K22: 5.39 | L22: =_xlfn.CONCAT(G22,I22,K22,F22,E22) | M22: =VLOOKUP(Table27[[#This Row],[Key]],Table29[[#All],[Key]:[TSL Material Code3]],4,0) | N22: =VLOOKUP(Table27[[#This Row],[Key]],Table29[[#All],[Key]:[TSL Material Code3]],5,0) | O22: =VLOOKUP(Table27[[#This Row],[Key]],Table29[[#All],[Key]:[TSL Material Code3]],7,0) | P22: =VLOOKUP(Table27[[#This Row],[Key]],Table29[[#All],[Key]:[TSL Material Code3]],8,0) | Q22: 10 | R22: 5 | S22: 0 | T22: 0 | U22: =S22-R22 | W22: =U22+V22 | X22: =Q22-W22 | Y22: =IF(X22>0,X22,0)*150% | Z22: =ROUND(SUMIFS(meghsteelsales_previousmonth[Quantity],meghsteelsales_previousmonth[Length Bucket],Table27[[#This Row],[Bucket CTL]])/1000,0) | AA22: =ROUND(SUMIFS(meghsteelsales_currentmonth[Quantity],meghsteelsales_currentmonth[Length Bucket],Table27[[#This Row],[Bucket CTL]])/1000,0) | AB22: =Table27[[#This Row],[ INDENT FOR NOV-25 recommended]]+Table27[[#This Row],[order logg ]] | AC22: =Table27[[#This Row],[Before 20th]]+Table27[[#This Row],[ofter 20th]] | AD22: =IF(Table27[[#This Row],[Total Indent]]-Table27[[#This Row],[Total Supplied]]<0,0,Table27[[#This Row],[Total Indent]]-Table27[[#This Row],[Total Supplied]])
A23: HMSI | B23: 943210 | C23: BADVE | D23: ERW2 | E23: FIN CUT | F23: HST | G23: 25.4 | I23: 1.4 | J23: 5531 | K23: 5.531 | L23: =_xlfn.CONCAT(G23,I23,K23,F23,E23) | M23: =VLOOKUP(Table27[[#This Row],[Key]],Table29[[#All],[Key]:[TSL Material Code3]],4,0) | N23: =VLOOKUP(Table27[[#This Row],[Key]],Table29[[#All],[Key]:[TSL Material Code3]],5,0) | O23: =VLOOKUP(Table27[[#This Row],[Key]],Table29[[#All],[Key]:[TSL Material Code3]],7,0) | P23: =VLOOKUP(Table27[[#This Row],[Key]],Table29[[#All],[Key]:[TSL Material Code3]],8,0) | Q23: 15 | R23: 0 | S23: 0 | T23: 0 | U23: =S23-R23 | V23: 16 | W23: =U23+V23 | X23: =Q23-W23 | Y23: =IF(X23>0,X23,0)*150% | Z23: =ROUND(SUMIFS(meghsteelsales_previousmonth[Quantity],meghsteelsales_previousmonth[Length Bucket],Table27[[#This Row],[Bucket CTL]])/1000,0) | AA23: =ROUND(SUMIFS(meghsteelsales_currentmonth[Quantity],meghsteelsales_currentmonth[Length Bucket],Table27[[#This Row],[Bucket CTL]])/1000,0) | AB23: =Table27[[#This Row],[ INDENT FOR NOV-25 recommended]]+Table27[[#This Row],[order logg ]] | AC23: =Table27[[#This Row],[Before 20th]]+Table27[[#This Row],[ofter 20th]] | AD23: =IF(Table27[[#This Row],[Total Indent]]-Table27[[#This Row],[Total Supplied]]<0,0,Table27[[#This Row],[Total Indent]]-Table27[[#This Row],[Total Supplied]])
A24: HMSI | B24: 943210 | C24: BADVE | D24: ERW1 | E24: FIN CUT | F24: ERW | G24: 25.4 | I24: 1.4 | J24: 6060 | K24: 6.06 | L24: =_xlfn.CONCAT(G24,I24,K24,F24,E24) | M24: =VLOOKUP(Table27[[#This Row],[Key]],Table29[[#All],[Key]:[TSL Material Code3]],4,0) | N24: =VLOOKUP(Table27[[#This Row],[Key]],Table29[[#All],[Key]:[TSL Material Code3]],5,0) | O24: =VLOOKUP(Table27[[#This Row],[Key]],Table29[[#All],[Key]:[TSL Material Code3]],7,0) | P24: =VLOOKUP(Table27[[#This Row],[Key]],Table29[[#All],[Key]:[TSL Material Code3]],8,0) | Q24: 15 | R24: 15 | S24: 0 | T24: 22 | U24: =S24-R24 | W24: =U24+V24 | X24: =Q24-W24 | Y24: =IF(X24>0,X24,0)*150% | Z24: =ROUND(SUMIFS(meghsteelsales_previousmonth[Quantity],meghsteelsales_previousmonth[Length Bucket],Table27[[#This Row],[Bucket CTL]])/1000,0) | AA24: =ROUND(SUMIFS(meghsteelsales_currentmonth[Quantity],meghsteelsales_currentmonth[Length Bucket],Table27[[#This Row],[Bucket CTL]])/1000,0) | AB24: =Table27[[#This Row],[ INDENT FOR NOV-25 recommended]]+Table27[[#This Row],[order logg ]] | AC24: =Table27[[#This Row],[Before 20th]]+Table27[[#This Row],[ofter 20th]] | AD24: =IF(Table27[[#This Row],[Total Indent]]-Table27[[#This Row],[Total Supplied]]<0,0,Table27[[#This Row],[Total Indent]]-Table27[[#This Row],[Total Supplied]])
A25: TVS | B25: 943209 | C25: RUCHA | D25: ERW1 | E25: NON FIN | F25: ERW | G25: 25.4 | I25: 1.6 | J25: 6000 | K25: 6 | L25: =_xlfn.CONCAT(G25,I25,K25,F25,E25) | M25: =VLOOKUP(Table27[[#This Row],[Key]],Table29[[#All],[Key]:[TSL Material Code3]],4,0) | N25: =VLOOKUP(Table27[[#This Row],[Key]],Table29[[#All],[Key]:[TSL Material Code3]],5,0) | O25: =VLOOKUP(Table27[[#This Row],[Key]],Table29[[#All],[Key]:[TSL Material Code3]],7,0) | P25: =VLOOKUP(Table27[[#This Row],[Key]],Table29[[#All],[Key]:[TSL Material Code3]],8,0) | Q25: 30 | R25: 15 | S25: 10 | T25: 50 | U25: =S25-R25 | V25: 29 | W25: =U25+V25 | X25: =Q25-W25 | Y25: =IF(X25>0,X25,0)*150% | Z25: =ROUND(SUMIFS(meghsteelsales_previousmonth[Quantity],meghsteelsales_previousmonth[Length Bucket],Table27[[#This Row],[Bucket CTL]])/1000,0) | AA25: =ROUND(SUMIFS(meghsteelsales_currentmonth[Quantity],meghsteelsales_currentmonth[Length Bucket],Table27[[#This Row],[Bucket CTL]])/1000,0) | AB25: =Table27[[#This Row],[ INDENT FOR NOV-25 recommended]]+Table27[[#This Row],[order logg ]] | AC25: =Table27[[#This Row],[Before 20th]]+Table27[[#This Row],[ofter 20th]] | AD25: =IF(Table27[[#This Row],[Total Indent]]-Table27[[#This Row],[Total Supplied]]<0,0,Table27[[#This Row],[Total Indent]]-Table27[[#This Row],[Total Supplied]])
A26: RE | B26: 943211 | C26: BELRISE CHENNAI | D26: MICRO ALLOY | E26: NON FIN | F26: MICRO ALLOY | G26: 25.4 | I26: 1.6 | J26: 5840 | K26: 5.84 | L26: =_xlfn.CONCAT(G26,I26,K26,F26,E26) | M26: 25.4-0-1.6-ERW 2 MAHS-PE | N26: 25.4-0-1.6-ERW 2 MAHS-PE-5.84 | O26: 0789 | P26: 4149395 | Q26: 25 | R26: 10 | S26: 16.7 | T26: 0 | U26: =S26-R26 | V26: 21 | W26: =U26+V26 | X26: =Q26-W26 | Y26: =IF(X26>0,X26,0)*150% | Z26: =ROUND(SUMIFS(meghsteelsales_previousmonth[Quantity],meghsteelsales_previousmonth[Length Bucket],Table27[[#This Row],[Bucket CTL]])/1000,0) | AA26: =ROUND(SUMIFS(meghsteelsales_currentmonth[Quantity],meghsteelsales_currentmonth[Length Bucket],Table27[[#This Row],[Bucket CTL]])/1000,0) | AB26: =Table27[[#This Row],[ INDENT FOR NOV-25 recommended]]+Table27[[#This Row],[order logg ]] | AC26: =Table27[[#This Row],[Before 20th]]+Table27[[#This Row],[ofter 20th]] | AD26: =IF(Table27[[#This Row],[Total Indent]]-Table27[[#This Row],[Total Supplied]]<0,0,Table27[[#This Row],[Total Indent]]-Table27[[#This Row],[Total Supplied]])
A27: TVS | B27: 943209 | C27: RUCHA | D27: ERW1 | E27: NON FIN | F27: ERW | G27: 25.4 | I27: 2 | J27: 6050 | K27: 6.05 | L27: =_xlfn.CONCAT(G27,I27,K27,F27,E27) | M27: =VLOOKUP(Table27[[#This Row],[Key]],Table29[[#All],[Key]:[TSL Material Code3]],4,0) | N27: =VLOOKUP(Table27[[#This Row],[Key]],Table29[[#All],[Key]:[TSL Material Code3]],5,0) | O27: =VLOOKUP(Table27[[#This Row],[Key]],Table29[[#All],[Key]:[TSL Material Code3]],7,0) | P27: =VLOOKUP(Table27[[#This Row],[Key]],Table29[[#All],[Key]:[TSL Material Code3]],8,0) | Q27: 10 | R27: 0 | S27: 3 | T27: 0 | U27: =S27-R27 | W27: =U27+V27 | X27: =Q27-W27 | Y27: =IF(X27>0,X27,0)*150% | Z27: =ROUND(SUMIFS(meghsteelsales_previousmonth[Quantity],meghsteelsales_previousmonth[Length Bucket],Table27[[#This Row],[Bucket CTL]])/1000,0) | AA27: =ROUND(SUMIFS(meghsteelsales_currentmonth[Quantity],meghsteelsales_currentmonth[Length Bucket],Table27[[#This Row],[Bucket CTL]])/1000,0) | AB27: =Table27[[#This Row],[ INDENT FOR NOV-25 recommended]]+Table27[[#This Row],[order logg ]] | AC27: =Table27[[#This Row],[Before 20th]]+Table27[[#This Row],[ofter 20th]] | AD27: =IF(Table27[[#This Row],[Total Indent]]-Table27[[#This Row],[Total Supplied]]<0,0,Table27[[#This Row],[Total Indent]]-Table27[[#This Row],[Total Supplied]])
A28: TVS | B28: 943209 | C28: RUCHA | D28: ERW1 | E28: NON FIN | F28: ERW | G28: 25.4 | I28: 2.5 | J28: 5530 | K28: 5.53 | L28: =_xlfn.CONCAT(G28,I28,K28,F28,E28) | M28: =VLOOKUP(Table27[[#This Row],[Key]],Table29[[#All],[Key]:[TSL Material Code3]],4,0) | N28: =VLOOKUP(Table27[[#This Row],[Key]],Table29[[#All],[Key]:[TSL Material Code3]],5,0) | O28: =VLOOKUP(Table27[[#This Row],[Key]],Table29[[#All],[Key]:[TSL Material Code3]],7,0) | P28: =VLOOKUP(Table27[[#This Row],[Key]],Table29[[#All],[Key]:[TSL Material Code3]],8,0) | Q28: 40 | R28: 15 | S28: 5 | T28: 58 | U28: =S28-R28 | V28: 62 | W28: =U28+V28 | X28: =Q28-W28 | Y28: =IF(X28>0,X28,0)*150% | Z28: =ROUND(SUMIFS(meghsteelsales_previousmonth[Quantity],meghsteelsales_previousmonth[Length Bucket],Table27[[#This Row],[Bucket CTL]])/1000,0) | AA28: =ROUND(SUMIFS(meghsteelsales_currentmonth[Quantity],meghsteelsales_currentmonth[Length Bucket],Table27[[#This Row],[Bucket CTL]])/1000,0) | AB28: =Table27[[#This Row],[ INDENT FOR NOV-25 recommended]]+Table27[[#This Row],[order logg ]] | AC28: =Table27[[#This Row],[Before 20th]]+Table27[[#This Row],[ofter 20th]] | AD28: =IF(Table27[[#This Row],[Total Indent]]-Table27[[#This Row],[Total Supplied]]<0,0,Table27[[#This Row],[Total Indent]]-Table27[[#This Row],[Total Supplied]])
A29: TVS | B29: 943209 | C29: RUCHA,METALMAN | D29: ERW1 | E29: FIN CUT | F29: ERW | G29: 28.6 | I29: 1.2 | J29: 6000 | K29: 6 | L29: =_xlfn.CONCAT(G29,I29,K29,F29,E29) | M29: =VLOOKUP(Table27[[#This Row],[Key]],Table29[[#All],[Key]:[TSL Material Code3]],4,0) | N29: =VLOOKUP(Table27[[#This Row],[Key]],Table29[[#All],[Key]:[TSL Material Code3]],5,0) | O29: =VLOOKUP(Table27[[#This Row],[Key]],Table29[[#All],[Key]:[TSL Material Code3]],7,0) | P29: =VLOOKUP(Table27[[#This Row],[Key]],Table29[[#All],[Key]:[TSL Material Code3]],8,0) | Q29: 3 | R29: 0 | S29: 3.2 | T29: 0 | U29: =S29-R29 | W29: =U29+V29 | X29: =Q29-W29 | Y29: =IF(X29>0,X29,0)*150% | Z29: =ROUND(SUMIFS(meghsteelsales_previousmonth[Quantity],meghsteelsales_previousmonth[Length Bucket],Table27[[#This Row],[Bucket CTL]])/1000,0) | AA29: =ROUND(SUMIFS(meghsteelsales_currentmonth[Quantity],meghsteelsales_currentmonth[Length Bucket],Table27[[#This Row],[Bucket CTL]])/1000,0) | AB29: =Table27[[#This Row],[ INDENT FOR NOV-25 recommended]]+Table27[[#This Row],[order logg ]] | AC29: =Table27[[#This Row],[Before 20th]]+Table27[[#This Row],[ofter 20th]] | AD29: =IF(Table27[[#This Row],[Total Indent]]-Table27[[#This Row],[Total Supplied]]<0,0,Table27[[#This Row],[Total Indent]]-Table27[[#This Row],[Total Supplied]])
A30: TVS | B30: 943209 | C30: RUCHA | D30: CEW1 | E30: FIN CUT | F30: CEW | G30: 28.6 | I30: 2.65 | J30: 6000 | K30: 6 | L30: =_xlfn.CONCAT(G30,I30,K30,F30,E30) | M30: =VLOOKUP(Table27[[#This Row],[Key]],Table29[[#All],[Key]:[TSL Material Code3]],4,0) | N30: =VLOOKUP(Table27[[#This Row],[Key]],Table29[[#All],[Key]:[TSL Material Code3]],5,0) | O30: =VLOOKUP(Table27[[#This Row],[Key]],Table29[[#All],[Key]:[TSL Material Code3]],7,0) | P30: =VLOOKUP(Table27[[#This Row],[Key]],Table29[[#All],[Key]:[TSL Material Code3]],8,0) | Q30: 10 | R30: 0 | S30: 9 | T30: 0 | U30: =S30-R30 | W30: =U30+V30 | X30: =Q30-W30 | Y30: =IF(X30>0,X30,0)*150% | Z30: =ROUND(SUMIFS(meghsteelsales_previousmonth[Quantity],meghsteelsales_previousmonth[Length Bucket],Table27[[#This Row],[Bucket CTL]])/1000,0) | AA30: =ROUND(SUMIFS(meghsteelsales_currentmonth[Quantity],meghsteelsales_currentmonth[Length Bucket],Table27[[#This Row],[Bucket CTL]])/1000,0) | AB30: =Table27[[#This Row],[ INDENT FOR NOV-25 recommended]]+Table27[[#This Row],[order logg ]] | AC30: =Table27[[#This Row],[Before 20th]]+Table27[[#This Row],[ofter 20th]] | AD30: =IF(Table27[[#This Row],[Total Indent]]-Table27[[#This Row],[Total Supplied]]<0,0,Table27[[#This Row],[Total Indent]]-Table27[[#This Row],[Total Supplied]])
A31: TVS | B31: 943209 | C31: RUCHA,METALMAN | D31: ERW1 | E31: FIN CUT | F31: ERW | G31: 31.75 | I31: 1.2 | J31: 6000 | K31: 6 | L31: =_xlfn.CONCAT(G31,I31,K31,F31,E31) | M31: =VLOOKUP(Table27[[#This Row],[Key]],Table29[[#All],[Key]:[TSL Material Code3]],4,0) | N31: =VLOOKUP(Table27[[#This Row],[Key]],Table29[[#All],[Key]:[TSL Material Code3]],5,0) | O31: =VLOOKUP(Table27[[#This Row],[Key]],Table29[[#All],[Key]:[TSL Material Code3]],7,0) | P31: =VLOOKUP(Table27[[#This Row],[Key]],Table29[[#All],[Key]:[TSL Material Code3]],8,0) | Q31: 5 | R31: 0 | S31: 20 | T31: 8.8 | U31: =S31-R31 | V31: 1.7 | W31: =U31+V31 | X31: =Q31-W31 | Y31: =IF(X31>0,X31,0)*150% | Z31: =ROUND(SUMIFS(meghsteelsales_previousmonth[Quantity],meghsteelsales_previousmonth[Length Bucket],Table27[[#This Row],[Bucket CTL]])/1000,0) | AA31: =ROUND(SUMIFS(meghsteelsales_currentmonth[Quantity],meghsteelsales_currentmonth[Length Bucket],Table27[[#This Row],[Bucket CTL]])/1000,0) | AB31: =Table27[[#This Row],[ INDENT FOR NOV-25 recommended]]+Table27[[#This Row],[order logg ]] | AC31: =Table27[[#This Row],[Before 20th]]+Table27[[#This Row],[ofter 20th]] | AD31: =IF(Table27[[#This Row],[Total Indent]]-Table27[[#This Row],[Total Supplied]]<0,0,Table27[[#This Row],[Total Indent]]-Table27[[#This Row],[Total Supplied]])
A32: TVS | B32: 943209 | C32: RUCHA,METALMAN | D32: ERW1 | E32: FIN CUT | F32: ERW | G32: 31.75 | I32: 2 | J32: 6000 | K32: 6 | L32: =_xlfn.CONCAT(G32,I32,K32,F32,E32) | M32: =VLOOKUP(Table27[[#This Row],[Key]],Table29[[#All],[Key]:[TSL Material Code3]],4,0) | N32: =VLOOKUP(Table27[[#This Row],[Key]],Table29[[#All],[Key]:[TSL Material Code3]],5,0) | O32: =VLOOKUP(Table27[[#This Row],[Key]],Table29[[#All],[Key]:[TSL Material Code3]],7,0) | P32: =VLOOKUP(Table27[[#This Row],[Key]],Table29[[#All],[Key]:[TSL Material Code3]],8,0) | Q32: 10 | R32: 0 | S32: 10 | T32: 10 | U32: =S32-R32 | W32: =U32+V32 | X32: =Q32-W32 | Y32: =IF(X32>0,X32,0)*150% | Z32: =ROUND(SUMIFS(meghsteelsales_previousmonth[Quantity],meghsteelsales_previousmonth[Length Bucket],Table27[[#This Row],[Bucket CTL]])/1000,0) | AA32: =ROUND(SUMIFS(meghsteelsales_currentmonth[Quantity],meghsteelsales_currentmonth[Length Bucket],Table27[[#This Row],[Bucket CTL]])/1000,0) | AB32: =Table27[[#This Row],[ INDENT FOR NOV-25 recommended]]+Table27[[#This Row],[order logg ]] | AC32: =Table27[[#This Row],[Before 20th]]+Table27[[#This Row],[ofter 20th]] | AD32: =IF(Table27[[#This Row],[Total Indent]]-Table27[[#This Row],[Total Supplied]]<0,0,Table27[[#This Row],[Total Indent]]-Table27[[#This Row],[Total Supplied]])
A33: RE | B33: 943211 | C33: BELRISE | D33: ERW1 | E33: FIN CUT | F33: ERW | G33: 31.75 | I33: 2.3 | J33: 5920 | K33: 5.92 | L33: =_xlfn.CONCAT(G33,I33,K33,F33,E33) | M33: =VLOOKUP(Table27[[#This Row],[Key]],Table29[[#All],[Key]:[TSL Material Code3]],4,0) | N33: =VLOOKUP(Table27[[#This Row],[Key]],Table29[[#All],[Key]:[TSL Material Code3]],5,0) | O33: =VLOOKUP(Table27[[#This Row],[Key]],Table29[[#All],[Key]:[TSL Material Code3]],7,0) | P33: =VLOOKUP(Table27[[#This Row],[Key]],Table29[[#All],[Key]:[TSL Material Code3]],8,0) | Q33: 15 | R33: 5 | S33: 18 | T33: 0 | U33: =S33-R33 | W33: =U33+V33 | X33: =Q33-W33 | Y33: =IF(X33>0,X33,0)*150% | Z33: =ROUND(SUMIFS(meghsteelsales_previousmonth[Quantity],meghsteelsales_previousmonth[Length Bucket],Table27[[#This Row],[Bucket CTL]])/1000,0) | AA33: =ROUND(SUMIFS(meghsteelsales_currentmonth[Quantity],meghsteelsales_currentmonth[Length Bucket],Table27[[#This Row],[Bucket CTL]])/1000,0) | AB33: =Table27[[#This Row],[ INDENT FOR NOV-25 recommended]]+Table27[[#This Row],[order logg ]] | AC33: =Table27[[#This Row],[Before 20th]]+Table27[[#This Row],[ofter 20th]] | AD33: =IF(Table27[[#This Row],[Total Indent]]-Table27[[#This Row],[Total Supplied]]<0,0,Table27[[#This Row],[Total Indent]]-Table27[[#This Row],[Total Supplied]])
A34: TVS | B34: 943209 | C34: RUCHA,METALMAN | D34: ERW1 | E34: FIN CUT | F34: ERW | G34: 34.93 | I34: 1.2 | J34: 6000 | K34: 6 | L34: =_xlfn.CONCAT(G34,I34,K34,F34,E34) | M34: =VLOOKUP(Table27[[#This Row],[Key]],Table29[[#All],[Key]:[TSL Material Code3]],4,0) | N34: =VLOOKUP(Table27[[#This Row],[Key]],Table29[[#All],[Key]:[TSL Material Code3]],5,0) | O34: =VLOOKUP(Table27[[#This Row],[Key]],Table29[[#All],[Key]:[TSL Material Code3]],7,0) | P34: =VLOOKUP(Table27[[#This Row],[Key]],Table29[[#All],[Key]:[TSL Material Code3]],8,0) | Q34: 5 | R34: 1 | S34: 34 | T34: 0 | U34: =S34-R34 | V34: 62 | W34: =U34+V34 | X34: =Q34-W34 | Y34: =IF(X34>0,X34,0)*150% | Z34: =ROUND(SUMIFS(meghsteelsales_previousmonth[Quantity],meghsteelsales_previousmonth[Length Bucket],Table27[[#This Row],[Bucket CTL]])/1000,0) | AA34: =ROUND(SUMIFS(meghsteelsales_currentmonth[Quantity],meghsteelsales_currentmonth[Length Bucket],Table27[[#This Row],[Bucket CTL]])/1000,0) | AB34: =Table27[[#This Row],[ INDENT FOR NOV-25 recommended]]+Table27[[#This Row],[order logg ]] | AC34: =Table27[[#This Row],[Before 20th]]+Table27[[#This Row],[ofter 20th]] | AD34: =IF(Table27[[#This Row],[Total Indent]]-Table27[[#This Row],[Total Supplied]]<0,0,Table27[[#This Row],[Total Indent]]-Table27[[#This Row],[Total Supplied]])
A35: RE | B35: 943211 | C35: BELRISE | D35: ERW1 | E35: FIN CUT | F35: ERW | G35: 34.93 | I35: 1.2 | J35: 620 | K35: 0.62 | L35: =_xlfn.CONCAT(G35,I35,K35,F35,E35) | M35: =VLOOKUP(Table27[[#This Row],[Key]],Table29[[#All],[Key]:[TSL Material Code3]],4,0) | N35: =VLOOKUP(Table27[[#This Row],[Key]],Table29[[#All],[Key]:[TSL Material Code3]],5,0) | O35: =VLOOKUP(Table27[[#This Row],[Key]],Table29[[#All],[Key]:[TSL Material Code3]],7,0) | P35: =VLOOKUP(Table27[[#This Row],[Key]],Table29[[#All],[Key]:[TSL Material Code3]],8,0) | Q35: 10 | R35: 0 | S35: 0 | T35: 0 | U35: =S35-R35 | W35: =U35+V35 | X35: =Q35-W35 | Y35: =IF(X35>0,X35,0)*150% | Z35: =ROUND(SUMIFS(meghsteelsales_previousmonth[Quantity],meghsteelsales_previousmonth[Length Bucket],Table27[[#This Row],[Bucket CTL]])/1000,0) | AA35: =ROUND(SUMIFS(meghsteelsales_currentmonth[Quantity],meghsteelsales_currentmonth[Length Bucket],Table27[[#This Row],[Bucket CTL]])/1000,0) | AB35: =Table27[[#This Row],[ INDENT FOR NOV-25 recommended]]+Table27[[#This Row],[order logg ]] | AC35: =Table27[[#This Row],[Before 20th]]+Table27[[#This Row],[ofter 20th]] | AD35: =IF(Table27[[#This Row],[Total Indent]]-Table27[[#This Row],[Total Supplied]]<0,0,Table27[[#This Row],[Total Indent]]-Table27[[#This Row],[Total Supplied]])
A36: RE | B36: 943211 | C36: RAJSRIYA | D36: ERW1 | E36: FIN CUT | F36: ERW | G36: 34.93 | I36: 1.2 | J36: 650 | K36: 0.65 | L36: =_xlfn.CONCAT(G36,I36,K36,F36,E36) | M36: =VLOOKUP(Table27[[#This Row],[Key]],Table29[[#All],[Key]:[TSL Material Code3]],4,0) | N36: =VLOOKUP(Table27[[#This Row],[Key]],Table29[[#All],[Key]:[TSL Material Code3]],5,0) | O36: =VLOOKUP(Table27[[#This Row],[Key]],Table29[[#All],[Key]:[TSL Material Code3]],7,0) | P36: =VLOOKUP(Table27[[#This Row],[Key]],Table29[[#All],[Key]:[TSL Material Code3]],8,0) | Q36: 10 | R36: 0 | S36: 0 | T36: 0 | U36: =S36-R36 | W36: =U36+V36 | X36: =Q36-W36 | Y36: =IF(X36>0,X36,0)*150% | Z36: =ROUND(SUMIFS(meghsteelsales_previousmonth[Quantity],meghsteelsales_previousmonth[Length Bucket],Table27[[#This Row],[Bucket CTL]])/1000,0) | AA36: =ROUND(SUMIFS(meghsteelsales_currentmonth[Quantity],meghsteelsales_currentmonth[Length Bucket],Table27[[#This Row],[Bucket CTL]])/1000,0) | AB36: =Table27[[#This Row],[ INDENT FOR NOV-25 recommended]]+Table27[[#This Row],[order logg ]] | AC36: =Table27[[#This Row],[Before 20th]]+Table27[[#This Row],[ofter 20th]] | AD36: =IF(Table27[[#This Row],[Total Indent]]-Table27[[#This Row],[Total Supplied]]<0,0,Table27[[#This Row],[Total Indent]]-Table27[[#This Row],[Total Supplied]])
A37: HMSI | B37: 943210 | C37: BADVE | D37: ERW2 | E37: FIN CUT | F37: ERW | G37: 34 | I37: 1.4 | J37: 5660 | K37: 5.66 | L37: =_xlfn.CONCAT(G37,I37,K37,F37,E37) | M37: =VLOOKUP(Table27[[#This Row],[Key]],Table29[[#All],[Key]:[TSL Material Code3]],4,0) | N37: =VLOOKUP(Table27[[#This Row],[Key]],Table29[[#All],[Key]:[TSL Material Code3]],5,0) | O37: =VLOOKUP(Table27[[#This Row],[Key]],Table29[[#All],[Key]:[TSL Material Code3]],7,0) | P37: =VLOOKUP(Table27[[#This Row],[Key]],Table29[[#All],[Key]:[TSL Material Code3]],8,0) | Q37: 5 | R37: 0 | S37: 0 | T37: 0 | U37: =S37-R37 | W37: =U37+V37 | X37: =Q37-W37 | Y37: =IF(X37>0,X37,0)*150% | Z37: =ROUND(SUMIFS(meghsteelsales_previousmonth[Quantity],meghsteelsales_previousmonth[Length Bucket],Table27[[#This Row],[Bucket CTL]])/1000,0) | AA37: =ROUND(SUMIFS(meghsteelsales_currentmonth[Quantity],meghsteelsales_currentmonth[Length Bucket],Table27[[#This Row],[Bucket CTL]])/1000,0) | AB37: =Table27[[#This Row],[ INDENT FOR NOV-25 recommended]]+Table27[[#This Row],[order logg ]] | AC37: =Table27[[#This Row],[Before 20th]]+Table27[[#This Row],[ofter 20th]] | AD37: =IF(Table27[[#This Row],[Total Indent]]-Table27[[#This Row],[Total Supplied]]<0,0,Table27[[#This Row],[Total Indent]]-Table27[[#This Row],[Total Supplied]])
A38: TVS | B38: 943209 | C38: RUCHA,METALMAN | D38: ERW370 | E38: FIN CUT | F38: HST | G38: 38.1 | I38: 1.6 | J38: 6190 | K38: 6.19 | L38: =_xlfn.CONCAT(G38,I38,K38,F38,E38) | M38: =VLOOKUP(Table27[[#This Row],[Key]],Table29[[#All],[Key]:[TSL Material Code3]],4,0) | N38: =VLOOKUP(Table27[[#This Row],[Key]],Table29[[#All],[Key]:[TSL Material Code3]],5,0) | O38: =VLOOKUP(Table27[[#This Row],[Key]],Table29[[#All],[Key]:[TSL Material Code3]],7,0) | P38: =VLOOKUP(Table27[[#This Row],[Key]],Table29[[#All],[Key]:[TSL Material Code3]],8,0) | Q38: 40 | R38: 20 | S38: 23 | T38: 3.8 | U38: =S38-R38 | V38: 61 | W38: =U38+V38 | X38: =Q38-W38 | Y38: =IF(X38>0,X38,0)*150% | Z38: =ROUND(SUMIFS(meghsteelsales_previousmonth[Quantity],meghsteelsales_previousmonth[Length Bucket],Table27[[#This Row],[Bucket CTL]])/1000,0) | AA38: =ROUND(SUMIFS(meghsteelsales_currentmonth[Quantity],meghsteelsales_currentmonth[Length Bucket],Table27[[#This Row],[Bucket CTL]])/1000,0) | AB38: =Table27[[#This Row],[ INDENT FOR NOV-25 recommended]]+Table27[[#This Row],[order logg ]] | AC38: =Table27[[#This Row],[Before 20th]]+Table27[[#This Row],[ofter 20th]] | AD38: =IF(Table27[[#This Row],[Total Indent]]-Table27[[#This Row],[Total Supplied]]<0,0,Table27[[#This Row],[Total Indent]]-Table27[[#This Row],[Total Supplied]])
A39: TVS | B39: 943209 | C39: RUCHA,METALMAN | D39: ERW1 | E39: FIN CUT | F39: ERW | G39: 38.1 | I39: 2 | J39: 5650 | K39: 5.65 | L39: =_xlfn.CONCAT(G39,I39,K39,F39,E39) | M39: =VLOOKUP(Table27[[#This Row],[Key]],Table29[[#All],[Key]:[TSL Material Code3]],4,0) | N39: =VLOOKUP(Table27[[#This Row],[Key]],Table29[[#All],[Key]:[TSL Material Code3]],5,0) | O39: =VLOOKUP(Table27[[#This Row],[Key]],Table29[[#All],[Key]:[TSL Material Code3]],7,0) | P39: =VLOOKUP(Table27[[#This Row],[Key]],Table29[[#All],[Key]:[TSL Material Code3]],8,0) | Q39: 20 | R39: 10 | S39: 0 | T39: 0 | U39: =S39-R39 | V39: 49 | W39: =U39+V39 | X39: =Q39-W39 | Y39: =IF(X39>0,X39,0)*150% | Z39: =ROUND(SUMIFS(meghsteelsales_previousmonth[Quantity],meghsteelsales_previousmonth[Length Bucket],Table27[[#This Row],[Bucket CTL]])/1000,0) | AA39: =ROUND(SUMIFS(meghsteelsales_currentmonth[Quantity],meghsteelsales_currentmonth[Length Bucket],Table27[[#This Row],[Bucket CTL]])/1000,0) | AB39: =Table27[[#This Row],[ INDENT FOR NOV-25 recommended]]+Table27[[#This Row],[order logg ]] | AC39: =Table27[[#This Row],[Before 20th]]+Table27[[#This Row],[ofter 20th]] | AD39: =IF(Table27[[#This Row],[Total Indent]]-Table27[[#This Row],[Total Supplied]]<0,0,Table27[[#This Row],[Total Indent]]-Table27[[#This Row],[Total Supplied]])
A40: TVS | B40: 943209 | C40: RUCHA,METALMAN | D40: ERW2 | E40: FIN CUT | F40: HST | G40: 38.1 | I40: 2.5 | J40: 6190 | K40: 6.19 | L40: =_xlfn.CONCAT(G40,I40,K40,F40,E40) | M40: =VLOOKUP(Table27[[#This Row],[Key]],Table29[[#All],[Key]:[TSL Material Code3]],4,0) | N40: =VLOOKUP(Table27[[#This Row],[Key]],Table29[[#All],[Key]:[TSL Material Code3]],5,0) | O40: =VLOOKUP(Table27[[#This Row],[Key]],Table29[[#All],[Key]:[TSL Material Code3]],7,0) | P40: =VLOOKUP(Table27[[#This Row],[Key]],Table29[[#All],[Key]:[TSL Material Code3]],8,0) | Q40: 40 | R40: 20 | S40: 9 | T40: 16.99 | U40: =S40-R40 | V40: 98 | W40: =U40+V40 | X40: =Q40-W40 | Y40: =IF(X40>0,X40,0)*150% | Z40: =ROUND(SUMIFS(meghsteelsales_previousmonth[Quantity],meghsteelsales_previousmonth[Length Bucket],Table27[[#This Row],[Bucket CTL]])/1000,0) | AA40: =ROUND(SUMIFS(meghsteelsales_currentmonth[Quantity],meghsteelsales_currentmonth[Length Bucket],Table27[[#This Row],[Bucket CTL]])/1000,0) | AB40: =Table27[[#This Row],[ INDENT FOR NOV-25 recommended]]+Table27[[#This Row],[order logg ]] | AC40: =Table27[[#This Row],[Before 20th]]+Table27[[#This Row],[ofter 20th]] | AD40: =IF(Table27[[#This Row],[Total Indent]]-Table27[[#This Row],[Total Supplied]]<0,0,Table27[[#This Row],[Total Indent]]-Table27[[#This Row],[Total Supplied]])
A41: RE | B41: 943211 | C41: BELRISE | D41: ERW2 | E41: FIN CUT | F41: ERW -2 | G41: 38.1 | I41: 3.2 | J41: 6000 | K41: 6 | L41: =_xlfn.CONCAT(G41,I41,K41,F41,E41) | M41: =VLOOKUP(Table27[[#This Row],[Key]],Table29[[#All],[Key]:[TSL Material Code3]],4,0) | N41: =VLOOKUP(Table27[[#This Row],[Key]],Table29[[#All],[Key]:[TSL Material Code3]],5,0) | O41: 0788 | P41: 4156196 | Q41: 15 | R41: 0 | S41: 0 | T41: 0 | U41: =S41-R41 | W41: =U41+V41 | X41: =Q41-W41 | Y41: =IF(X41>0,X41,0)*150% | Z41: =ROUND(SUMIFS(meghsteelsales_previousmonth[Quantity],meghsteelsales_previousmonth[Length Bucket],Table27[[#This Row],[Bucket CTL]])/1000,0) | AA41: =ROUND(SUMIFS(meghsteelsales_currentmonth[Quantity],meghsteelsales_currentmonth[Length Bucket],Table27[[#This Row],[Bucket CTL]])/1000,0) | AB41: =Table27[[#This Row],[ INDENT FOR NOV-25 recommended]]+Table27[[#This Row],[order logg ]] | AC41: =Table27[[#This Row],[Before 20th]]+Table27[[#This Row],[ofter 20th]] | AD41: =IF(Table27[[#This Row],[Total Indent]]-Table27[[#This Row],[Total Supplied]]<0,0,Table27[[#This Row],[Total Indent]]-Table27[[#This Row],[Total Supplied]])
A42: TVS | B42: 943209 | C42: RUCHA | D42: ERW1 | E42: FIN CUT | F42: ERW | G42: 41.28 | I42: 2.6 | J42: 6000 | K42: 6 | L42: =_xlfn.CONCAT(G42,I42,K42,F42,E42) | M42: =VLOOKUP(Table27[[#This Row],[Key]],Table29[[#All],[Key]:[TSL Material Code3]],4,0) | N42: =VLOOKUP(Table27[[#This Row],[Key]],Table29[[#All],[Key]:[TSL Material Code3]],5,0) | O42: =VLOOKUP(Table27[[#This Row],[Key]],Table29[[#All],[Key]:[TSL Material Code3]],7,0) | P42: =VLOOKUP(Table27[[#This Row],[Key]],Table29[[#All],[Key]:[TSL Material Code3]],8,0) | Q42: 35 | R42: 20 | S42: 26 | T42: 0 | U42: =S42-R42 | V42: 15.7 | W42: =U42+V42 | X42: =Q42-W42 | Y42: =IF(X42>0,X42,0)*150% | Z42: =ROUND(SUMIFS(meghsteelsales_previousmonth[Quantity],meghsteelsales_previousmonth[Length Bucket],Table27[[#This Row],[Bucket CTL]])/1000,0) | AA42: =ROUND(SUMIFS(meghsteelsales_currentmonth[Quantity],meghsteelsales_currentmonth[Length Bucket],Table27[[#This Row],[Bucket CTL]])/1000,0) | AB42: =Table27[[#This Row],[ INDENT FOR NOV-25 recommended]]+Table27[[#This Row],[order logg ]] | AC42: =Table27[[#This Row],[Before 20th]]+Table27[[#This Row],[ofter 20th]] | AD42: =IF(Table27[[#This Row],[Total Indent]]-Table27[[#This Row],[Total Supplied]]<0,0,Table27[[#This Row],[Total Indent]]-Table27[[#This Row],[Total Supplied]])
A43: TVS | B43: 943209 | C43: RUCHA | D43: ERW1 | E43: FIN CUT | F43: ERW | G43: 40x25 | I43: 1.6 | J43: 5900 | K43: 6.13 | L43: =_xlfn.CONCAT(G43,I43,K43,F43,E43) | M43: =VLOOKUP(Table27[[#This Row],[Key]],Table29[[#All],[Key]:[TSL Material Code3]],4,0) | N43: =VLOOKUP(Table27[[#This Row],[Key]],Table29[[#All],[Key]:[TSL Material Code3]],5,0) | O43: =VLOOKUP(Table27[[#This Row],[Key]],Table29[[#All],[Key]:[TSL Material Code3]],7,0) | P43: =VLOOKUP(Table27[[#This Row],[Key]],Table29[[#All],[Key]:[TSL Material Code3]],8,0) | Q43: 5 | R43: 0 | S43: 0 | T43: 0 | U43: =S43-R43 | W43: =U43+V43 | X43: =Q43-W43 | Y43: =IF(X43>0,X43,0)*150% | Z43: =ROUND(SUMIFS(meghsteelsales_previousmonth[Quantity],meghsteelsales_previousmonth[Length Bucket],Table27[[#This Row],[Bucket CTL]])/1000,0) | AA43: =ROUND(SUMIFS(meghsteelsales_currentmonth[Quantity],meghsteelsales_currentmonth[Length Bucket],Table27[[#This Row],[Bucket CTL]])/1000,0) | AB43: =Table27[[#This Row],[ INDENT FOR NOV-25 recommended]]+Table27[[#This Row],[order logg ]] | AC43: =Table27[[#This Row],[Before 20th]]+Table27[[#This Row],[ofter 20th]] | AD43: =IF(Table27[[#This Row],[Total Indent]]-Table27[[#This Row],[Total Supplied]]<0,0,Table27[[#This Row],[Total Indent]]-Table27[[#This Row],[Total Supplied]])
A44: HMSI | B44: 943210 | C44: BADVE | D44: ERW1 | E44: FIN CUT | F44: ERW | G44: 41.28 | I44: 3.15 | J44: 5860 | K44: 5.86 | L44: =_xlfn.CONCAT(G44,I44,K44,F44,E44) | M44: =VLOOKUP(Table27[[#This Row],[Key]],Table29[[#All],[Key]:[TSL Material Code3]],4,0) | N44: =VLOOKUP(Table27[[#This Row],[Key]],Table29[[#All],[Key]:[TSL Material Code3]],5,0) | O44: =VLOOKUP(Table27[[#This Row],[Key]],Table29[[#All],[Key]:[TSL Material Code3]],7,0) | P44: =VLOOKUP(Table27[[#This Row],[Key]],Table29[[#All],[Key]:[TSL Material Code3]],8,0) | Q44: 40 | R44: 15 | S44: 77 | T44: 0 | U44: =S44-R44 | V44: 21 | W44: =U44+V44 | X44: =Q44-W44 | Y44: =IF(X44>0,X44,0)*150% | Z44: =ROUND(SUMIFS(meghsteelsales_previousmonth[Quantity],meghsteelsales_previousmonth[Length Bucket],Table27[[#This Row],[Bucket CTL]])/1000,0) | AA44: =ROUND(SUMIFS(meghsteelsales_currentmonth[Quantity],meghsteelsales_currentmonth[Length Bucket],Table27[[#This Row],[Bucket CTL]])/1000,0) | AB44: =Table27[[#This Row],[ INDENT FOR NOV-25 recommended]]+Table27[[#This Row],[order logg ]] | AC44: =Table27[[#This Row],[Before 20th]]+Table27[[#This Row],[ofter 20th]] | AD44: =IF(Table27[[#This Row],[Total Indent]]-Table27[[#This Row],[Total Supplied]]<0,0,Table27[[#This Row],[Total Indent]]-Table27[[#This Row],[Total Supplied]])
A45: TVS | B45: 943209 | C45: RUCHA,METALMAN | D45: ERW AN | E45: FIN CUT | F45: ERW | G45: 42.7 | I45: 3.5 | J45: 6000 | K45: 6 | L45: =_xlfn.CONCAT(G45,I45,K45,F45,E45) | M45: =VLOOKUP(Table27[[#This Row],[Key]],Table29[[#All],[Key]:[TSL Material Code3]],4,0) | N45: =VLOOKUP(Table27[[#This Row],[Key]],Table29[[#All],[Key]:[TSL Material Code3]],5,0) | O45: =VLOOKUP(Table27[[#This Row],[Key]],Table29[[#All],[Key]:[TSL Material Code3]],7,0) | P45: =VLOOKUP(Table27[[#This Row],[Key]],Table29[[#All],[Key]:[TSL Material Code3]],8,0) | Q45: 5 | R45: 2 | S45: 19 | T45: 0 | U45: =S45-R45 | W45: =U45+V45 | X45: =Q45-W45 | Y45: =IF(X45>0,X45,0)*150% | Z45: =ROUND(SUMIFS(meghsteelsales_previousmonth[Quantity],meghsteelsales_previousmonth[Length Bucket],Table27[[#This Row],[Bucket CTL]])/1000,0) | AA45: =ROUND(SUMIFS(meghsteelsales_currentmonth[Quantity],meghsteelsales_currentmonth[Length Bucket],Table27[[#This Row],[Bucket CTL]])/1000,0) | AB45: =Table27[[#This Row],[ INDENT FOR NOV-25 recommended]]+Table27[[#This Row],[order logg ]] | AC45: =Table27[[#This Row],[Before 20th]]+Table27[[#This Row],[ofter 20th]] | AD45: =IF(Table27[[#This Row],[Total Indent]]-Table27[[#This Row],[Total Supplied]]<0,0,Table27[[#This Row],[Total Indent]]-Table27[[#This Row],[Total Supplied]])
A46: TVS | B46: 943209 | C46: RUCHA,METALMAN | D46: ERW AN | E46: FIN CUT | F46: ERW | G46: 42.7 | I46: 4 | J46: 6000 | K46: 6 | L46: =_xlfn.CONCAT(G46,I46,K46,F46,E46) | M46: =VLOOKUP(Table27[[#This Row],[Key]],Table29[[#All],[Key]:[TSL Material Code3]],4,0) | N46: =VLOOKUP(Table27[[#This Row],[Key]],Table29[[#All],[Key]:[TSL Material Code3]],5,0) | O46: =VLOOKUP(Table27[[#This Row],[Key]],Table29[[#All],[Key]:[TSL Material Code3]],7,0) | P46: =VLOOKUP(Table27[[#This Row],[Key]],Table29[[#All],[Key]:[TSL Material Code3]],8,0) | Q46: 30 | R46: 10 | S46: 14 | T46: 0 | U46: =S46-R46 | W46: =U46+V46 | X46: =Q46-W46 | Y46: =IF(X46>0,X46,0)*150% | Z46: =ROUND(SUMIFS(meghsteelsales_previousmonth[Quantity],meghsteelsales_previousmonth[Length Bucket],Table27[[#This Row],[Bucket CTL]])/1000,0) | AA46: =ROUND(SUMIFS(meghsteelsales_currentmonth[Quantity],meghsteelsales_currentmonth[Length Bucket],Table27[[#This Row],[Bucket CTL]])/1000,0) | AB46: =Table27[[#This Row],[ INDENT FOR NOV-25 recommended]]+Table27[[#This Row],[order logg ]] | AC46: =Table27[[#This Row],[Before 20th]]+Table27[[#This Row],[ofter 20th]] | AD46: =IF(Table27[[#This Row],[Total Indent]]-Table27[[#This Row],[Total Supplied]]<0,0,Table27[[#This Row],[Total Indent]]-Table27[[#This Row],[Total Supplied]])
A47: TVS | B47: 943209 | C47: RUCHA,METALMAN | D47: ERW1 | E47: FIN CUT | F47: ERW | G47: 40x30 | I47: 1.6 | J47: 5900 | K47: 5.9 | L47: =_xlfn.CONCAT(G47,I47,K47,F47,E47) | M47: =VLOOKUP(Table27[[#This Row],[Key]],Table29[[#All],[Key]:[TSL Material Code3]],4,0) | N47: =VLOOKUP(Table27[[#This Row],[Key]],Table29[[#All],[Key]:[TSL Material Code3]],5,0) | O47: =VLOOKUP(Table27[[#This Row],[Key]],Table29[[#All],[Key]:[TSL Material Code3]],7,0) | P47: =VLOOKUP(Table27[[#This Row],[Key]],Table29[[#All],[Key]:[TSL Material Code3]],8,0) | Q47: 5 | R47: 3 | S47: 14 | T47: 0 | U47: =S47-R47 | W47: =U47+V47 | X47: =Q47-W47 | Y47: =IF(X47>0,X47,0)*150% | Z47: =ROUND(SUMIFS(meghsteelsales_previousmonth[Quantity],meghsteelsales_previousmonth[Length Bucket],Table27[[#This Row],[Bucket CTL]])/1000,0) | AA47: =ROUND(SUMIFS(meghsteelsales_currentmonth[Quantity],meghsteelsales_currentmonth[Length Bucket],Table27[[#This Row],[Bucket CTL]])/1000,0) | AB47: =Table27[[#This Row],[ INDENT FOR NOV-25 recommended]]+Table27[[#This Row],[order logg ]] | AC47: =Table27[[#This Row],[Before 20th]]+Table27[[#This Row],[ofter 20th]] | AD47: =IF(Table27[[#This Row],[Total Indent]]-Table27[[#This Row],[Total Supplied]]<0,0,Table27[[#This Row],[Total Indent]]-Table27[[#This Row],[Total Supplied]])
A48: HMSI | B48: 943210 | C48: BADVE | D48: ERW2 | E48: FIN CUT | F48: HST | G48: 45 | I48: 1.4 | J48: 6400 | K48: 6.42 | L48: =_xlfn.CONCAT(G48,I48,K48,F48,E48) | M48: =VLOOKUP(Table27[[#This Row],[Key]],Table29[[#All],[Key]:[TSL Material Code3]],4,0) | N48: =VLOOKUP(Table27[[#This Row],[Key]],Table29[[#All],[Key]:[TSL Material Code3]],5,0) | O48: =VLOOKUP(Table27[[#This Row],[Key]],Table29[[#All],[Key]:[TSL Material Code3]],7,0) | P48: =VLOOKUP(Table27[[#This Row],[Key]],Table29[[#All],[Key]:[TSL Material Code3]],8,0) | Q48: 5 | R48: 2 | S48: 40 | T48: 19.4 | U48: =S48-R48 | W48: =U48+V48 | X48: =Q48-W48 | Y48: =IF(X48>0,X48,0)*150% | Z48: =ROUND(SUMIFS(meghsteelsales_previousmonth[Quantity],meghsteelsales_previousmonth[Length Bucket],Table27[[#This Row],[Bucket CTL]])/1000,0) | AA48: =ROUND(SUMIFS(meghsteelsales_currentmonth[Quantity],meghsteelsales_currentmonth[Length Bucket],Table27[[#This Row],[Bucket CTL]])/1000,0) | AB48: =Table27[[#This Row],[ INDENT FOR NOV-25 recommended]]+Table27[[#This Row],[order logg ]] | AC48: =Table27[[#This Row],[Before 20th]]+Table27[[#This Row],[ofter 20th]] | AD48: =IF(Table27[[#This Row],[Total Indent]]-Table27[[#This Row],[Total Supplied]]<0,0,Table27[[#This Row],[Total Indent]]-Table27[[#This Row],[Total Supplied]])
A49: HMSI | B49: 943210 | C49: BADVE | D49: ERW1 | E49: FIN CUT | F49: ERW | G49: 45 | I49: 1.4 | J49: 5700 | K49: 5.7 | L49: =_xlfn.CONCAT(G49,I49,K49,F49,E49) | M49: =VLOOKUP(Table27[[#This Row],[Key]],Table29[[#All],[Key]:[TSL Material Code3]],4,0) | N49: =VLOOKUP(Table27[[#This Row],[Key]],Table29[[#All],[Key]:[TSL Material Code3]],5,0) | O49: =VLOOKUP(Table27[[#This Row],[Key]],Table29[[#All],[Key]:[TSL Material Code3]],7,0) | P49: =VLOOKUP(Table27[[#This Row],[Key]],Table29[[#All],[Key]:[TSL Material Code3]],8,0) | Q49: 5 | R49: 0 | S49: 2 | T49: 0 | U49: =S49-R49 | V49: 7 | W49: =U49+V49 | X49: =Q49-W49 | Y49: =IF(X49>0,X49,0)*150% | Z49: =ROUND(SUMIFS(meghsteelsales_previousmonth[Quantity],meghsteelsales_previousmonth[Length Bucket],Table27[[#This Row],[Bucket CTL]])/1000,0) | AA49: =ROUND(SUMIFS(meghsteelsales_currentmonth[Quantity],meghsteelsales_currentmonth[Length Bucket],Table27[[#This Row],[Bucket CTL]])/1000,0) | AB49: =Table27[[#This Row],[ INDENT FOR NOV-25 recommended]]+Table27[[#This Row],[order logg ]] | AC49: =Table27[[#This Row],[Before 20th]]+Table27[[#This Row],[ofter 20th]] | AD49: =IF(Table27[[#This Row],[Total Indent]]-Table27[[#This Row],[Total Supplied]]<0,0,Table27[[#This Row],[Total Indent]]-Table27[[#This Row],[Total Supplied]])
A50: HMSI | B50: 943210 | C50: BADVE | D50: ERW2 | E50: FIN CUT | F50: HST | G50: 45 | I50: 1.6 | J50: 6400 | K50: 6.42 | L50: =_xlfn.CONCAT(G50,I50,K50,F50,E50) | M50: =VLOOKUP(Table27[[#This Row],[Key]],Table29[[#All],[Key]:[TSL Material Code3]],4,0) | N50: =VLOOKUP(Table27[[#This Row],[Key]],Table29[[#All],[Key]:[TSL Material Code3]],5,0) | O50: =VLOOKUP(Table27[[#This Row],[Key]],Table29[[#All],[Key]:[TSL Material Code3]],7,0) | P50: =VLOOKUP(Table27[[#This Row],[Key]],Table29[[#All],[Key]:[TSL Material Code3]],8,0) | Q50: 5 | R50: 2 | S50: 11 | T50: 0 | U50: =S50-R50 | W50: =U50+V50 | X50: =Q50-W50 | Y50: =IF(X50>0,X50,0)*150% | Z50: =ROUND(SUMIFS(meghsteelsales_previousmonth[Quantity],meghsteelsales_previousmonth[Length Bucket],Table27[[#This Row],[Bucket CTL]])/1000,0) | AA50: =ROUND(SUMIFS(meghsteelsales_currentmonth[Quantity],meghsteelsales_currentmonth[Length Bucket],Table27[[#This Row],[Bucket CTL]])/1000,0) | AB50: =Table27[[#This Row],[ INDENT FOR NOV-25 recommended]]+Table27[[#This Row],[order logg ]] | AC50: =Table27[[#This Row],[Before 20th]]+Table27[[#This Row],[ofter 20th]] | AD50: =IF(Table27[[#This Row],[Total Indent]]-Table27[[#This Row],[Total Supplied]]<0,0,Table27[[#This Row],[Total Indent]]-Table27[[#This Row],[Total Supplied]])
A51: HMSI | B51: 943210 | C51: BADVE | D51: CEW-1 | E51: FIN CUT | F51: CEW-1 | G51: 45 | I51: 3.5 | J51: 6100 | L51: =_xlfn.CONCAT(G51,I51,K51,F51,E51) | M51: =VLOOKUP(Table27[[#This Row],[Key]],Table29[[#All],[Key]:[TSL Material Code3]],4,0) | N51: =VLOOKUP(Table27[[#This Row],[Key]],Table29[[#All],[Key]:[TSL Material Code3]],5,0) | O51: 056 | P51: 3500263 | Q51: 10 | R51: 3 | S51: 0 | T51: 0 | U51: =S51-R51 | V51: 1.3 | W51: =U51+V51 | X51: =Q51-W51 | Y51: =IF(X51>0,X51,0)*150% | Z51: =ROUND(SUMIFS(meghsteelsales_previousmonth[Quantity],meghsteelsales_previousmonth[Length Bucket],Table27[[#This Row],[Bucket CTL]])/1000,0) | AA51: =ROUND(SUMIFS(meghsteelsales_currentmonth[Quantity],meghsteelsales_currentmonth[Length Bucket],Table27[[#This Row],[Bucket CTL]])/1000,0) | AB51: =Table27[[#This Row],[ INDENT FOR NOV-25 recommended]]+Table27[[#This Row],[order logg ]] | AC51: =Table27[[#This Row],[Before 20th]]+Table27[[#This Row],[ofter 20th]] | AD51: =IF(Table27[[#This Row],[Total Indent]]-Table27[[#This Row],[Total Supplied]]<0,0,Table27[[#This Row],[Total Indent]]-Table27[[#This Row],[Total Supplied]])
A52: RE | B52: 943211 | C52: BELRISE | D52: CEW-1 | E52: FIN CUT | F52: CEW | G52: 47.63 | I52: 4 | J52: 6040 | K52: 6.04 | L52: =_xlfn.CONCAT(G52,I52,K52,F52,E52) | M52: =VLOOKUP(Table27[[#This Row],[Key]],Table29[[#All],[Key]:[TSL Material Code3]],4,0) | N52: =VLOOKUP(Table27[[#This Row],[Key]],Table29[[#All],[Key]:[TSL Material Code3]],5,0) | O52: =VLOOKUP(Table27[[#This Row],[Key]],Table29[[#All],[Key]:[TSL Material Code3]],7,0) | P52: =VLOOKUP(Table27[[#This Row],[Key]],Table29[[#All],[Key]:[TSL Material Code3]],8,0) | Q52: 10 | R52: 3 | S52: 4 | T52: 0 | U52: =S52-R52 | W52: =U52+V52 | X52: =Q52-W52 | Y52: =IF(X52>0,X52,0)*150% | Z52: =ROUND(SUMIFS(meghsteelsales_previousmonth[Quantity],meghsteelsales_previousmonth[Length Bucket],Table27[[#This Row],[Bucket CTL]])/1000,0) | AA52: =ROUND(SUMIFS(meghsteelsales_currentmonth[Quantity],meghsteelsales_currentmonth[Length Bucket],Table27[[#This Row],[Bucket CTL]])/1000,0) | AB52: =Table27[[#This Row],[ INDENT FOR NOV-25 recommended]]+Table27[[#This Row],[order logg ]] | AC52: =Table27[[#This Row],[Before 20th]]+Table27[[#This Row],[ofter 20th]] | AD52: =IF(Table27[[#This Row],[Total Indent]]-Table27[[#This Row],[Total Supplied]]<0,0,Table27[[#This Row],[Total Indent]]-Table27[[#This Row],[Total Supplied]])
A53: RE | B53: 943211 | C53: BELRISE | D53: ERW1 | E53: FIN CUT | F53: ERW | G53: 48 | I53: 1.2 | J53: 620 | K53: 0.62 | L53: =_xlfn.CONCAT(G53,I53,K53,F53,E53) | M53: =VLOOKUP(Table27[[#This Row],[Key]],Table29[[#All],[Key]:[TSL Material Code3]],4,0) | N53: =VLOOKUP(Table27[[#This Row],[Key]],Table29[[#All],[Key]:[TSL Material Code3]],5,0) | O53: =VLOOKUP(Table27[[#This Row],[Key]],Table29[[#All],[Key]:[TSL Material Code3]],7,0) | P53: =VLOOKUP(Table27[[#This Row],[Key]],Table29[[#All],[Key]:[TSL Material Code3]],8,0) | Q53: 10 | R53: 0 | S53: 0 | T53: 0 | U53: =S53-R53 | W53: =U53+V53 | X53: =Q53-W53 | Y53: =IF(X53>0,X53,0)*150% | Z53: =ROUND(SUMIFS(meghsteelsales_previousmonth[Quantity],meghsteelsales_previousmonth[Length Bucket],Table27[[#This Row],[Bucket CTL]])/1000,0) | AA53: =ROUND(SUMIFS(meghsteelsales_currentmonth[Quantity],meghsteelsales_currentmonth[Length Bucket],Table27[[#This Row],[Bucket CTL]])/1000,0) | AB53: =Table27[[#This Row],[ INDENT FOR NOV-25 recommended]]+Table27[[#This Row],[order logg ]] | AC53: =Table27[[#This Row],[Before 20th]]+Table27[[#This Row],[ofter 20th]] | AD53: =IF(Table27[[#This Row],[Total Indent]]-Table27[[#This Row],[Total Supplied]]<0,0,Table27[[#This Row],[Total Indent]]-Table27[[#This Row],[Total Supplied]])
A54: RE | B54: 943211 | C54: RAJSRIYA | D54: ERW1 | E54: FIN CUT | F54: ERW | G54: 48 | I54: 1.2 | J54: 650 | K54: 0.65 | L54: =_xlfn.CONCAT(G54,I54,K54,F54,E54) | M54: =VLOOKUP(Table27[[#This Row],[Key]],Table29[[#All],[Key]:[TSL Material Code3]],4,0) | N54: =VLOOKUP(Table27[[#This Row],[Key]],Table29[[#All],[Key]:[TSL Material Code3]],5,0) | O54: =VLOOKUP(Table27[[#This Row],[Key]],Table29[[#All],[Key]:[TSL Material Code3]],7,0) | P54: =VLOOKUP(Table27[[#This Row],[Key]],Table29[[#All],[Key]:[TSL Material Code3]],8,0) | Q54: 14 | R54: 0 | S54: 0 | T54: 0 | U54: =S54-R54 | W54: =U54+V54 | X54: =Q54-W54 | Y54: =IF(X54>0,X54,0)*150% | Z54: =ROUND(SUMIFS(meghsteelsales_previousmonth[Quantity],meghsteelsales_previousmonth[Length Bucket],Table27[[#This Row],[Bucket CTL]])/1000,0) | AA54: =ROUND(SUMIFS(meghsteelsales_currentmonth[Quantity],meghsteelsales_currentmonth[Length Bucket],Table27[[#This Row],[Bucket CTL]])/1000,0) | AB54: =Table27[[#This Row],[ INDENT FOR NOV-25 recommended]]+Table27[[#This Row],[order logg ]] | AC54: =Table27[[#This Row],[Before 20th]]+Table27[[#This Row],[ofter 20th]] | AD54: =IF(Table27[[#This Row],[Total Indent]]-Table27[[#This Row],[Total Supplied]]<0,0,Table27[[#This Row],[Total Indent]]-Table27[[#This Row],[Total Supplied]])
A55: HMSI | B55: 943210 | C55: BADVE | D55: ERW2 | E55: FIN CUT | F55: HST | G55: 48.6 | I55: 2 | J55: 6270 | K55: 6.27 | L55: =_xlfn.CONCAT(G55,I55,K55,F55,E55) | M55: =VLOOKUP(Table27[[#This Row],[Key]],Table29[[#All],[Key]:[TSL Material Code3]],4,0) | N55: =VLOOKUP(Table27[[#This Row],[Key]],Table29[[#All],[Key]:[TSL Material Code3]],5,0) | O55: =VLOOKUP(Table27[[#This Row],[Key]],Table29[[#All],[Key]:[TSL Material Code3]],7,0) | P55: =VLOOKUP(Table27[[#This Row],[Key]],Table29[[#All],[Key]:[TSL Material Code3]],8,0) | Q55: 5 | R55: 3 | S55: 30 | T55: 0 | U55: =S55-R55 | W55: =U55+V55 | X55: =Q55-W55 | Y55: =IF(X55>0,X55,0)*150% | Z55: =ROUND(SUMIFS(meghsteelsales_previousmonth[Quantity],meghsteelsales_previousmonth[Length Bucket],Table27[[#This Row],[Bucket CTL]])/1000,0) | AA55: =ROUND(SUMIFS(meghsteelsales_currentmonth[Quantity],meghsteelsales_currentmonth[Length Bucket],Table27[[#This Row],[Bucket CTL]])/1000,0) | AB55: =Table27[[#This Row],[ INDENT FOR NOV-25 recommended]]+Table27[[#This Row],[order logg ]] | AC55: =Table27[[#This Row],[Before 20th]]+Table27[[#This Row],[ofter 20th]] | AD55: =IF(Table27[[#This Row],[Total Indent]]-Table27[[#This Row],[Total Supplied]]<0,0,Table27[[#This Row],[Total Indent]]-Table27[[#This Row],[Total Supplied]])
A56: HMSI | B56: 943210 | C56: BADVE | D56: ERW2 | E56: FIN CUT | F56: HST | G56: 48.6 | I56: 2.3 | J56: 6270 | K56: 6.27 | L56: =_xlfn.CONCAT(G56,I56,K56,F56,E56) | M56: =VLOOKUP(Table27[[#This Row],[Key]],Table29[[#All],[Key]:[TSL Material Code3]],4,0) | N56: =VLOOKUP(Table27[[#This Row],[Key]],Table29[[#All],[Key]:[TSL Material Code3]],5,0) | O56: =VLOOKUP(Table27[[#This Row],[Key]],Table29[[#All],[Key]:[TSL Material Code3]],7,0) | P56: =VLOOKUP(Table27[[#This Row],[Key]],Table29[[#All],[Key]:[TSL Material Code3]],8,0) | Q56: 5 | R56: 3 | S56: 0 | T56: 0 | U56: =S56-R56 | V56: 23.5 | W56: =U56+V56 | X56: =Q56-W56 | Y56: =IF(X56>0,X56,0)*150% | Z56: =ROUND(SUMIFS(meghsteelsales_previousmonth[Quantity],meghsteelsales_previousmonth[Length Bucket],Table27[[#This Row],[Bucket CTL]])/1000,0) | AA56: =ROUND(SUMIFS(meghsteelsales_currentmonth[Quantity],meghsteelsales_currentmonth[Length Bucket],Table27[[#This Row],[Bucket CTL]])/1000,0) | AB56: =Table27[[#This Row],[ INDENT FOR NOV-25 recommended]]+Table27[[#This Row],[order logg ]] | AC56: =Table27[[#This Row],[Before 20th]]+Table27[[#This Row],[ofter 20th]] | AD56: =IF(Table27[[#This Row],[Total Indent]]-Table27[[#This Row],[Total Supplied]]<0,0,Table27[[#This Row],[Total Indent]]-Table27[[#This Row],[Total Supplied]])
A57: HMSI | B57: 943210 | C57: BADVE | D57: ERW1 | E57: FIN CUT | F57: ERW | G57: 48.6 | I57: 3.5 | J57: 6000 | K57: 6 | L57: =_xlfn.CONCAT(G57,I57,K57,F57,E57) | M57: =VLOOKUP(Table27[[#This Row],[Key]],Table29[[#All],[Key]:[TSL Material Code3]],4,0) | N57: =VLOOKUP(Table27[[#This Row],[Key]],Table29[[#All],[Key]:[TSL Material Code3]],5,0) | O57: =VLOOKUP(Table27[[#This Row],[Key]],Table29[[#All],[Key]:[TSL Material Code3]],7,0) | P57: =VLOOKUP(Table27[[#This Row],[Key]],Table29[[#All],[Key]:[TSL Material Code3]],8,0) | Q57: 20 | R57: 10 | S57: 8 | T57: 0 | U57: =S57-R57 | W57: =U57+V57 | X57: =Q57-W57 | Y57: =IF(X57>0,X57,0)*150% | Z57: =ROUND(SUMIFS(meghsteelsales_previousmonth[Quantity],meghsteelsales_previousmonth[Length Bucket],Table27[[#This Row],[Bucket CTL]])/1000,0) | AA57: =ROUND(SUMIFS(meghsteelsales_currentmonth[Quantity],meghsteelsales_currentmonth[Length Bucket],Table27[[#This Row],[Bucket CTL]])/1000,0) | AB57: =Table27[[#This Row],[ INDENT FOR NOV-25 recommended]]+Table27[[#This Row],[order logg ]] | AC57: =Table27[[#This Row],[Before 20th]]+Table27[[#This Row],[ofter 20th]] | AD57: =IF(Table27[[#This Row],[Total Indent]]-Table27[[#This Row],[Total Supplied]]<0,0,Table27[[#This Row],[Total Indent]]-Table27[[#This Row],[Total Supplied]])
A58: TVS | B58: 943209 | C58: RUCHA | D58: ERW1 | E58: FIN CUT | F58: ERW | G58: 59x30 | I58: 1.6 | J58: 6000 | K58: 6 | L58: =_xlfn.CONCAT(G58,I58,K58,F58,E58) | M58: =VLOOKUP(Table27[[#This Row],[Key]],Table29[[#All],[Key]:[TSL Material Code3]],4,0) | N58: =VLOOKUP(Table27[[#This Row],[Key]],Table29[[#All],[Key]:[TSL Material Code3]],5,0) | O58: =VLOOKUP(Table27[[#This Row],[Key]],Table29[[#All],[Key]:[TSL Material Code3]],7,0) | P58: =VLOOKUP(Table27[[#This Row],[Key]],Table29[[#All],[Key]:[TSL Material Code3]],8,0) | Q58: 5 | R58: 0 | S58: 1.5 | T58: 0 | U58: =S58-R58 | W58: =U58+V58 | X58: =Q58-W58 | Y58: =IF(X58>0,X58,0)*150% | Z58: =ROUND(SUMIFS(meghsteelsales_previousmonth[Quantity],meghsteelsales_previousmonth[Length Bucket],Table27[[#This Row],[Bucket CTL]])/1000,0) | AA58: =ROUND(SUMIFS(meghsteelsales_currentmonth[Quantity],meghsteelsales_currentmonth[Length Bucket],Table27[[#This Row],[Bucket CTL]])/1000,0) | AB58: =Table27[[#This Row],[ INDENT FOR NOV-25 recommended]]+Table27[[#This Row],[order logg ]] | AC58: =Table27[[#This Row],[Before 20th]]+Table27[[#This Row],[ofter 20th]] | AD58: =IF(Table27[[#This Row],[Total Indent]]-Table27[[#This Row],[Total Supplied]]<0,0,Table27[[#This Row],[Total Indent]]-Table27[[#This Row],[Total Supplied]])
A59: RE | B59: 943211 | C59: KUNAL | D59: ERW1 | E59: FIN CUT | F59: ERW | G59: 59x30 | I59: 1.6 | J59: 572.5 | K59: 0.5725 | L59: =_xlfn.CONCAT(G59,I59,K59,F59,E59) | M59: =VLOOKUP(Table27[[#This Row],[Key]],Table29[[#All],[Key]:[TSL Material Code3]],4,0) | N59: =VLOOKUP(Table27[[#This Row],[Key]],Table29[[#All],[Key]:[TSL Material Code3]],5,0) | O59: =VLOOKUP(Table27[[#This Row],[Key]],Table29[[#All],[Key]:[TSL Material Code3]],7,0) | P59: =VLOOKUP(Table27[[#This Row],[Key]],Table29[[#All],[Key]:[TSL Material Code3]],8,0) | Q59: 30 | R59: 0 | S59: 0 | T59: 0 | U59: =S59-R59 | W59: =U59+V59 | X59: =Q59-W59 | Y59: =IF(X59>0,X59,0)*150% | Z59: =ROUND(SUMIFS(meghsteelsales_previousmonth[Quantity],meghsteelsales_previousmonth[Length Bucket],Table27[[#This Row],[Bucket CTL]])/1000,0) | AA59: =ROUND(SUMIFS(meghsteelsales_currentmonth[Quantity],meghsteelsales_currentmonth[Length Bucket],Table27[[#This Row],[Bucket CTL]])/1000,0) | AB59: =Table27[[#This Row],[ INDENT FOR NOV-25 recommended]]+Table27[[#This Row],[order logg ]] | AC59: =Table27[[#This Row],[Before 20th]]+Table27[[#This Row],[ofter 20th]] | AD59: =IF(Table27[[#This Row],[Total Indent]]-Table27[[#This Row],[Total Supplied]]<0,0,Table27[[#This Row],[Total Indent]]-Table27[[#This Row],[Total Supplied]])
A60: RE | B60: 943211 | C60: BELRISE | D60: ERW1 | E60: FIN CUT | F60: ERW | G60: 50X50 | I60: 1.6 | J60: 6040 | K60: 6.04 | L60: =_xlfn.CONCAT(G60,I60,K60,F60,E60) | M60: =VLOOKUP(Table27[[#This Row],[Key]],Table29[[#All],[Key]:[TSL Material Code3]],4,0) | N60: =VLOOKUP(Table27[[#This Row],[Key]],Table29[[#All],[Key]:[TSL Material Code3]],5,0) | O60: =VLOOKUP(Table27[[#This Row],[Key]],Table29[[#All],[Key]:[TSL Material Code3]],7,0) | P60: =VLOOKUP(Table27[[#This Row],[Key]],Table29[[#All],[Key]:[TSL Material Code3]],8,0) | Q60: 10 | R60: 5 | S60: 0 | T60: 15 | U60: =S60-R60 | V60: 20 | W60: =U60+V60 | X60: =Q60-W60 | Y60: =IF(X60>0,X60,0)*150% | Z60: =ROUND(SUMIFS(meghsteelsales_previousmonth[Quantity],meghsteelsales_previousmonth[Length Bucket],Table27[[#This Row],[Bucket CTL]])/1000,0) | AA60: =ROUND(SUMIFS(meghsteelsales_currentmonth[Quantity],meghsteelsales_currentmonth[Length Bucket],Table27[[#This Row],[Bucket CTL]])/1000,0) | AB60: =Table27[[#This Row],[ INDENT FOR NOV-25 recommended]]+Table27[[#This Row],[order logg ]] | AC60: =Table27[[#This Row],[Before 20th]]+Table27[[#This Row],[ofter 20th]] | AD60: =IF(Table27[[#This Row],[Total Indent]]-Table27[[#This Row],[Total Supplied]]<0,0,Table27[[#This Row],[Total Indent]]-Table27[[#This Row],[Total Supplied]])
A61: RE | B61: 943211 | C61: BELRISE | D61: ERW1 | E61: FIN CUT | F61: ERW | G61: 50.8 | I61: 2.6 | J61: 6000 | K61: 6 | L61: =_xlfn.CONCAT(G61,I61,K61,F61,E61) | M61: =VLOOKUP(Table27[[#This Row],[Key]],Table29[[#All],[Key]:[TSL Material Code3]],4,0) | N61: =VLOOKUP(Table27[[#This Row],[Key]],Table29[[#All],[Key]:[TSL Material Code3]],5,0) | O61: =VLOOKUP(Table27[[#This Row],[Key]],Table29[[#All],[Key]:[TSL Material Code3]],7,0) | P61: =VLOOKUP(Table27[[#This Row],[Key]],Table29[[#All],[Key]:[TSL Material Code3]],8,0) | Q61: 10 | R61: 0 | S61: 17 | T61: 0 | U61: =S61-R61 | V61: 12.6 | W61: =U61+V61 | X61: 5 | Y61: =IF(X61>0,X61,0)*150% | Z61: =ROUND(SUMIFS(meghsteelsales_previousmonth[Quantity],meghsteelsales_previousmonth[Length Bucket],Table27[[#This Row],[Bucket CTL]])/1000,0) | AA61: =ROUND(SUMIFS(meghsteelsales_currentmonth[Quantity],meghsteelsales_currentmonth[Length Bucket],Table27[[#This Row],[Bucket CTL]])/1000,0) | AB61: =Table27[[#This Row],[ INDENT FOR NOV-25 recommended]]+Table27[[#This Row],[order logg ]] | AC61: =Table27[[#This Row],[Before 20th]]+Table27[[#This Row],[ofter 20th]] | AD61: =IF(Table27[[#This Row],[Total Indent]]-Table27[[#This Row],[Total Supplied]]<0,0,Table27[[#This Row],[Total Indent]]-Table27[[#This Row],[Total Supplied]])
A62: RE | B62: 943211 | C62: BELRISE | D62: CEW-1 | E62: FIN CUT | F62: CEW | G62: 50.8 | H62: 45.6 | I62: 2.6 | J62: 6000 | K62: 6 | L62: =_xlfn.CONCAT(G62,I62,K62,F62,E62) | M62: =VLOOKUP(Table27[[#This Row],[Key]],Table29[[#All],[Key]:[TSL Material Code3]],4,0) | N62: =VLOOKUP(Table27[[#This Row],[Key]],Table29[[#All],[Key]:[TSL Material Code3]],5,0) | O62: =VLOOKUP(Table27[[#This Row],[Key]],Table29[[#All],[Key]:[TSL Material Code3]],7,0) | P62: =VLOOKUP(Table27[[#This Row],[Key]],Table29[[#All],[Key]:[TSL Material Code3]],8,0) | Q62: 5 | R62: 0 | S62: 1.4 | T62: 0 | U62: =S62-R62 | V62: 24.5 | W62: =U62+V62 | X62: 5 | Y62: =IF(X62>0,X62,0)*150% | Z62: =ROUND(SUMIFS(meghsteelsales_previousmonth[Quantity],meghsteelsales_previousmonth[Length Bucket],Table27[[#This Row],[Bucket CTL]])/1000,0) | AA62: =ROUND(SUMIFS(meghsteelsales_currentmonth[Quantity],meghsteelsales_currentmonth[Length Bucket],Table27[[#This Row],[Bucket CTL]])/1000,0) | AB62: =Table27[[#This Row],[ INDENT FOR NOV-25 recommended]]+Table27[[#This Row],[order logg ]] | AC62: =Table27[[#This Row],[Before 20th]]+Table27[[#This Row],[ofter 20th]] | AD62: =IF(Table27[[#This Row],[Total Indent]]-Table27[[#This Row],[Total Supplied]]<0,0,Table27[[#This Row],[Total Indent]]-Table27[[#This Row],[Total Supplied]])
A63: TVS | B63: 943209 | C63: METALMAN | D63: ERW1 | E63: FIN CUT | F63: ERW | G63: 54 | I63: 3 | J63: 5910 | K63: 5.91 | L63: =_xlfn.CONCAT(G63,I63,K63,F63,E63) | M63: =VLOOKUP(Table27[[#This Row],[Key]],Table29[[#All],[Key]:[TSL Material Code3]],4,0) | N63: =VLOOKUP(Table27[[#This Row],[Key]],Table29[[#All],[Key]:[TSL Material Code3]],5,0) | O63: 788 | P63: 3500391 | Q63: 10 | R63: 0 | S63: 1.5 | T63: 0 | U63: =S63-R63 | W63: =U63+V63 | X63: 10 | Y63: =IF(X63>0,X63,0)*150% | Z63: =ROUND(SUMIFS(meghsteelsales_previousmonth[Quantity],meghsteelsales_previousmonth[Length Bucket],Table27[[#This Row],[Bucket CTL]])/1000,0) | AA63: =ROUND(SUMIFS(meghsteelsales_currentmonth[Quantity],meghsteelsales_currentmonth[Length Bucket],Table27[[#This Row],[Bucket CTL]])/1000,0) | AB63: =Table27[[#This Row],[ INDENT FOR NOV-25 recommended]]+Table27[[#This Row],[order logg ]] | AC63: =Table27[[#This Row],[Before 20th]]+Table27[[#This Row],[ofter 20th]] | AD63: =IF(Table27[[#This Row],[Total Indent]]-Table27[[#This Row],[Total Supplied]]<0,0,Table27[[#This Row],[Total Indent]]-Table27[[#This Row],[Total Supplied]])
A64: TVS | B64: 943209 | C64: RUCHA,METALMAN | D64: ERW1 | E64: FIN CUT | F64: ERW | G64: 57.15 | I64: 2.5 | J64: 5710 | K64: 5.71 | L64: =_xlfn.CONCAT(G64,I64,K64,F64,E64) | M64: =VLOOKUP(Table27[[#This Row],[Key]],Table29[[#All],[Key]:[TSL Material Code3]],4,0) | N64: =VLOOKUP(Table27[[#This Row],[Key]],Table29[[#All],[Key]:[TSL Material Code3]],5,0) | O64: =VLOOKUP(Table27[[#This Row],[Key]],Table29[[#All],[Key]:[TSL Material Code3]],7,0) | P64: =VLOOKUP(Table27[[#This Row],[Key]],Table29[[#All],[Key]:[TSL Material Code3]],8,0) | Q64: 70 | R64: 30 | S64: 93 | T64: 18.2 | U64: =S64-R64 | V64: 82.7 | W64: =U64+V64 | X64: =Q64-W64 | Y64: =IF(X64>0,X64,0)*150% | Z64: =ROUND(SUMIFS(meghsteelsales_previousmonth[Quantity],meghsteelsales_previousmonth[Length Bucket],Table27[[#This Row],[Bucket CTL]])/1000,0) | AA64: =ROUND(SUMIFS(meghsteelsales_currentmonth[Quantity],meghsteelsales_currentmonth[Length Bucket],Table27[[#This Row],[Bucket CTL]])/1000,0) | AB64: =Table27[[#This Row],[ INDENT FOR NOV-25 recommended]]+Table27[[#This Row],[order logg ]] | AC64: =Table27[[#This Row],[Before 20th]]+Table27[[#This Row],[ofter 20th]] | AD64: =IF(Table27[[#This Row],[Total Indent]]-Table27[[#This Row],[Total Supplied]]<0,0,Table27[[#This Row],[Total Indent]]-Table27[[#This Row],[Total Supplied]])
A65: TVS | B65: 943209 | C65: RUCHA,METALMAN | D65: ERW1 | E65: FIN CUT | F65: ERW | G65: 57.15 | I65: 2.5 | J65: 5750 | K65: 5.75 | L65: =_xlfn.CONCAT(G65,I65,K65,F65,E65) | M65: =VLOOKUP(Table27[[#This Row],[Key]],Table29[[#All],[Key]:[TSL Material Code3]],4,0) | N65: =VLOOKUP(Table27[[#This Row],[Key]],Table29[[#All],[Key]:[TSL Material Code3]],5,0) | O65: =VLOOKUP(Table27[[#This Row],[Key]],Table29[[#All],[Key]:[TSL Material Code3]],7,0) | P65: =VLOOKUP(Table27[[#This Row],[Key]],Table29[[#All],[Key]:[TSL Material Code3]],8,0) | Q65: 20 | R65: 0 | S65: 31 | T65: 18 | U65: =S65-R65 | V65: 43.4 | W65: =U65+V65 | X65: =Q65-W65 | Y65: =IF(X65>0,X65,0)*150% | Z65: =ROUND(SUMIFS(meghsteelsales_previousmonth[Quantity],meghsteelsales_previousmonth[Length Bucket],Table27[[#This Row],[Bucket CTL]])/1000,0) | AA65: =ROUND(SUMIFS(meghsteelsales_currentmonth[Quantity],meghsteelsales_currentmonth[Length Bucket],Table27[[#This Row],[Bucket CTL]])/1000,0) | AB65: =Table27[[#This Row],[ INDENT FOR NOV-25 recommended]]+Table27[[#This Row],[order logg ]] | AC65: =Table27[[#This Row],[Before 20th]]+Table27[[#This Row],[ofter 20th]] | AD65: =IF(Table27[[#This Row],[Total Indent]]-Table27[[#This Row],[Total Supplied]]<0,0,Table27[[#This Row],[Total Indent]]-Table27[[#This Row],[Total Supplied]])
A66: TVS | B66: 943209 | C66: RUCHA,METALMAN | D66: ERW1 | E66: FIN CUT | F66: ERW | G66: 57.15 | I66: 2.5 | J66: 6100 | K66: 6.1 | L66: =_xlfn.CONCAT(G66,I66,K66,F66,E66) | M66: =VLOOKUP(Table27[[#This Row],[Key]],Table29[[#All],[Key]:[TSL Material Code3]],4,0) | N66: =VLOOKUP(Table27[[#This Row],[Key]],Table29[[#All],[Key]:[TSL Material Code3]],5,0) | O66: =VLOOKUP(Table27[[#This Row],[Key]],Table29[[#All],[Key]:[TSL Material Code3]],7,0) | P66: =VLOOKUP(Table27[[#This Row],[Key]],Table29[[#All],[Key]:[TSL Material Code3]],8,0) | Q66: 70 | R66: 30 | S66: 79 | T66: 22.5 | U66: =S66-R66 | V66: 33.6 | W66: =U66+V66 | X66: =Q66-W66 | Y66: =IF(X66>0,X66,0)*150% | Z66: =ROUND(SUMIFS(meghsteelsales_previousmonth[Quantity],meghsteelsales_previousmonth[Length Bucket],Table27[[#This Row],[Bucket CTL]])/1000,0) | AA66: =ROUND(SUMIFS(meghsteelsales_currentmonth[Quantity],meghsteelsales_currentmonth[Length Bucket],Table27[[#This Row],[Bucket CTL]])/1000,0) | AB66: =Table27[[#This Row],[ INDENT FOR NOV-25 recommended]]+Table27[[#This Row],[order logg ]] | AC66: =Table27[[#This Row],[Before 20th]]+Table27[[#This Row],[ofter 20th]] | AD66: =IF(Table27[[#This Row],[Total Indent]]-Table27[[#This Row],[Total Supplied]]<0,0,Table27[[#This Row],[Total Indent]]-Table27[[#This Row],[Total Supplied]])
A67: HMSI | B67: 943210 | C67: BADVE | D67: ERW1 | E67: FIN CUT | F67: ERW | G67: 57.15 | I67: 3 | J67: 5650 | K67: 5.65 | L67: =_xlfn.CONCAT(G67,I67,K67,F67,E67) | M67: =VLOOKUP(Table27[[#This Row],[Key]],Table29[[#All],[Key]:[TSL Material Code3]],4,0) | N67: =VLOOKUP(Table27[[#This Row],[Key]],Table29[[#All],[Key]:[TSL Material Code3]],5,0) | O67: =VLOOKUP(Table27[[#This Row],[Key]],Table29[[#All],[Key]:[TSL Material Code3]],7,0) | P67: =VLOOKUP(Table27[[#This Row],[Key]],Table29[[#All],[Key]:[TSL Material Code3]],8,0) | Q67: 10 | R67: 0 | S67: 0 | T67: 0 | U67: =S67-R67 | V67: 15 | W67: =U67+V67 | X67: =Q67-W67 | Y67: =IF(X67>0,X67,0)*150% | Z67: =ROUND(SUMIFS(meghsteelsales_previousmonth[Quantity],meghsteelsales_previousmonth[Length Bucket],Table27[[#This Row],[Bucket CTL]])/1000,0) | AA67: =ROUND(SUMIFS(meghsteelsales_currentmonth[Quantity],meghsteelsales_currentmonth[Length Bucket],Table27[[#This Row],[Bucket CTL]])/1000,0) | AB67: =Table27[[#This Row],[ INDENT FOR NOV-25 recommended]]+Table27[[#This Row],[order logg ]] | AC67: =Table27[[#This Row],[Before 20th]]+Table27[[#This Row],[ofter 20th]] | AD67: =IF(Table27[[#This Row],[Total Indent]]-Table27[[#This Row],[Total Supplied]]<0,0,Table27[[#This Row],[Total Indent]]-Table27[[#This Row],[Total Supplied]])
A68: TVS | B68: 943209 | C68: METALMAN | D68: ERW1 | E68: FIN CUT | F68: ERW | G68: 60.3 | I68: 2 | J68: 5900 | K68: 5.9 | L68: =_xlfn.CONCAT(G68,I68,K68,F68,E68) | M68: =VLOOKUP(Table27[[#This Row],[Key]],Table29[[#All],[Key]:[TSL Material Code3]],4,0) | N68: =VLOOKUP(Table27[[#This Row],[Key]],Table29[[#All],[Key]:[TSL Material Code3]],5,0) | O68: =VLOOKUP(Table27[[#This Row],[Key]],Table29[[#All],[Key]:[TSL Material Code3]],7,0) | P68: =VLOOKUP(Table27[[#This Row],[Key]],Table29[[#All],[Key]:[TSL Material Code3]],8,0) | Q68: 30 | R68: 10 | S68: 25 | T68: 24.28 | U68: =S68-R68 | W68: =U68+V68 | X68: =Q68-W68 | Y68: =IF(X68>0,X68,0)*150% | Z68: =ROUND(SUMIFS(meghsteelsales_previousmonth[Quantity],meghsteelsales_previousmonth[Length Bucket],Table27[[#This Row],[Bucket CTL]])/1000,0) | AA68: =ROUND(SUMIFS(meghsteelsales_currentmonth[Quantity],meghsteelsales_currentmonth[Length Bucket],Table27[[#This Row],[Bucket CTL]])/1000,0) | AB68: =Table27[[#This Row],[ INDENT FOR NOV-25 recommended]]+Table27[[#This Row],[order logg ]] | AC68: =Table27[[#This Row],[Before 20th]]+Table27[[#This Row],[ofter 20th]] | AD68: =IF(Table27[[#This Row],[Total Indent]]-Table27[[#This Row],[Total Supplied]]<0,0,Table27[[#This Row],[Total Indent]]-Table27[[#This Row],[Total Supplied]])
I69: TOTAL | Q69: =SUM(R2:R68) | R69: =SUM(S2:S68) | S69: =SUM(T2:T68) | T69: =SUM(U2:U68) | U69: =SUM(V2:V68) | V69: =SUM(V2:V68) | W69: =SUM(X2:X68) | X69: =SUM(Y2:Y68) | Y69: =SUM(Y2:Y68) | Z69: =SUM(Z2:Z68) | AA69: =SUM(AA2:AA68) | AB69: =SUM(AB2:AB68) | AC69: =SUM(AC2:AC68) | AD69: =SUM(AD2:AD68)
A71: new sizes in nov
A72: {=_xlfn._xlws.FILTER(Table27[Key],ISNA(_xlfn.XMATCH(Table27[Key],Table29[Key])))} | AD72: =AB69-AD69
A73: 38.13.26ERW -2FIN CUT | AD73: =AC69-AD72
A74: 453.5CEW-1FIN CUT
A75: 5435.91ERWFIN CUT
A78: plant | B78: OEM | C78: Customer Code | D78: OD | E78: ID | F78: THK | G78: LENGTH | H78: Length in Mtrs | I78: TSL Material Code | J78: INDENT FOR NOV-25 recommended | K78: Metallurgy condition | L78: Material Type | M78: Material Description3 | N78: Spec | O78: FC/NFC | P78: SO | Q78: STATUS
A79: 056 | B79: HMSI | C79: 943210 | D79: 19.05 | E79: 0 | F79: 1.4 | G79: 6000 | H79: 6 | I79: 3891285 | J79: 15 | K79: ERW2 | L79: NON FIN | M79: =VLOOKUP(I79,[1]!zmat[#All],2,0) | N79: =VLOOKUP(I79,[1]!zmat[#All],21,0) | O79: =VLOOKUP(I79,[1]!zmat[#All],22,0)
A80: 056 | B80: HMSI | C80: 943210 | D80: 45 | E80: 0 | F80: 3.5 | G80: 6100 | H80: 6.1 | I80: 3500263 | J80: 17.55 | K80: CEW-1 | L80: FIN CUT | M80: =VLOOKUP(I80,[1]!zmat[#All],2,0) | N80: =VLOOKUP(I80,[1]!zmat[#All],21,0) | O80: =VLOOKUP(I80,[1]!zmat[#All],22,0)
A81: 056 | B81: RE | C81: 943211 | D81: 34.93 | E81: 0 | F81: 1.2 | G81: 620 | H81: 0.62 | I81: 3499589 | J81: 20 | K81: ERW1 | L81: FIN CUT | M81: =VLOOKUP(I81,[1]!zmat[#All],2,0) | N81: =VLOOKUP(I81,[1]!zmat[#All],21,0) | O81: =VLOOKUP(I81,[1]!zmat[#All],22,0)
A82: 056 | B82: RE | C82: 943211 | D82: 34.93 | E82: 0 | F82: 1.2 | G82: 650 | H82: 0.65 | I82: 3499396 | J82: 20 | K82: ERW1 | L82: FIN CUT | M82: =VLOOKUP(I82,[1]!zmat[#All],2,0) | N82: =VLOOKUP(I82,[1]!zmat[#All],21,0) | O82: =VLOOKUP(I82,[1]!zmat[#All],22,0)
A83: 056 | B83: RE | C83: 943211 | D83: 50.8 | E83: 0 | F83: 2.6 | G83: 6000 | H83: 6 | I83: 3518437 | J83: 7.5 | K83: ERW1 | L83: FIN CUT | M83: =VLOOKUP(I83,[1]!zmat[#All],2,0) | N83: =VLOOKUP(I83,[1]!zmat[#All],21,0) | O83: =VLOOKUP(I83,[1]!zmat[#All],22,0)
A84: 056 | B84: RE | C84: 943211 | D84: 50.8 | E84: 45.6 | F84: 2.6 | G84: 6000 | H84: 6 | I84: 3500695 | J84: 7.5 | K84: CEW-1 | L84: FIN CUT | M84: =VLOOKUP(I84,[1]!zmat[#All],2,0) | N84: =VLOOKUP(I84,[1]!zmat[#All],21,0) | O84: =VLOOKUP(I84,[1]!zmat[#All],22,0)
A85: 056 | B85: TVS | C85: 943209 | D85: 19.05 | E85: 0 | F85: 2 | G85: 5800 | H85: 5.8 | I85: 1940292 | J85: 52.5 | K85: ERW1 | L85: NON FIN | M85: =VLOOKUP(I85,[1]!zmat[#All],2,0) | N85: =VLOOKUP(I85,[1]!zmat[#All],21,0) | O85: =VLOOKUP(I85,[1]!zmat[#All],22,0)
A86: 056 | B86: TVS | C86: 943209 | D86: 22.2 | E86: 0 | F86: 1.2 | G86: 5870 | H86: 5.87 | I86: 3882110 | J86: 40.5 | K86: ERW1 | L86: NON FIN | M86: =VLOOKUP(I86,[1]!zmat[#All],2,0) | N86: =VLOOKUP(I86,[1]!zmat[#All],21,0) | O86: =VLOOKUP(I86,[1]!zmat[#All],22,0)
A87: 056 | B87: TVS | C87: 943209 | D87: 22.2 | E87: 0 | F87: 2 | G87: 5950 | H87: 5.95 | I87: 3905466 | J87: 86.4 | K87: ERW1 | L87: NON FIN | M87: =VLOOKUP(I87,[1]!zmat[#All],2,0) | N87: =VLOOKUP(I87,[1]!zmat[#All],21,0) | O87: =VLOOKUP(I87,[1]!zmat[#All],22,0)
A88: 056 | B88: TVS | C88: 943209 | D88: 25.4 | E88: 0 | F88: 1.6 | G88: 6000 | H88: 6 | I88: 3500097 | J88: 9 | K88: ERW1 | L88: NON FIN | M88: =VLOOKUP(I88,[1]!zmat[#All],2,0) | N88: =VLOOKUP(I88,[1]!zmat[#All],21,0) | O88: =VLOOKUP(I88,[1]!zmat[#All],22,0)
A89: 0788 | B89: HMSI | C89: 943210 | D89: 34 | E89: 0 | F89: 1.4 | G89: 5660 | H89: 5.66 | I89: 3702855 | J89: 7.5 | K89: ERW2 | L89: FIN CUT | M89: =VLOOKUP(I89,[1]!zmat[#All],2,0) | N89: =VLOOKUP(I89,[1]!zmat[#All],21,0) | O89: =VLOOKUP(I89,[1]!zmat[#All],22,0)
A90: 0788 | B90: RE | C90: 943211 | D90: 47.63 | E90: 0 | F90: 4 | G90: 6040 | H90: 6.04 | I90: 3500635 | J90: 13.5 | K90: CEW-1 | L90: FIN CUT | M90: =VLOOKUP(I90,[1]!zmat[#All],2,0) | N90: =VLOOKUP(I90,[1]!zmat[#All],21,0) | O90: =VLOOKUP(I90,[1]!zmat[#All],22,0)
... A96: 0789 | B96: HMSI | C96: 943210 | D96: 48.6 | E96: 0 | F96: 3.5 | G96: 6000 | H96: 6 | I96: 3502422 | J96: 33 | K96: ERW1 | L96: FIN CUT | M96: =VLOOKUP(I96,[1]!zmat[#All],2,0) | N96: =VLOOKUP(I96,[1]!zmat[#All],21,0) | O96: =VLOOKUP(I96,[1]!zmat[#All],22,0)
A97: 0789 | B97: RE | C97: 943211 | D97: 31.75 | E97: 0 | F97: 2.3 | G97: 5920 | H97: 5.92 | I97: MCR 42136 | J97: 3 | K97: ERW1 | L97: FIN CUT | M97: =VLOOKUP(I97,[1]!zmat[#All],2,0) | N97: =VLOOKUP(I97,[1]!zmat[#All],21,0) | O97: =VLOOKUP(I97,[1]!zmat[#All],22,0)
A98: 0789 | B98: RE | C98: 943211 | D98: 48 | E98: 0 | F98: 1.2 | G98: 620 | H98: 0.62 | I98: 2397072 | J98: 15 | K98: ERW1 | L98: FIN CUT | M98: =VLOOKUP(I98,[1]!zmat[#All],2,0) | N98: =VLOOKUP(I98,[1]!zmat[#All],21,0) | O98: =VLOOKUP(I98,[1]!zmat[#All],22,0)
A99: 0789 | B99: RE | C99: 943211 | D99: 48 | E99: 0 | F99: 1.2 | G99: 650 | H99: 0.65 | I99: 2397060 | J99: 21 | K99: ERW1 | L99: FIN CUT | M99: =VLOOKUP(I99,[1]!zmat[#All],2,0) | N99: =VLOOKUP(I99,[1]!zmat[#All],21,0) | O99: =VLOOKUP(I99,[1]!zmat[#All],22,0)
A100: 0789 | B100: RE | C100: 943211 | D100: 59x30 | E100: 0 | F100: 1.6 | G100: 572.5 | H100: 0.5725 | I100: 2420716 | J100: 45 | K100: ERW1 | L100: FIN CUT | M100: =VLOOKUP(I100,[1]!zmat[#All],2,0) | N100: =VLOOKUP(I100,[1]!zmat[#All],21,0) | O100: =VLOOKUP(I100,[1]!zmat[#All],22,0)
A101: 0789 | B101: TVS | C101: 943209 | D101: 12.7 | E101: 0 | F101: 1.2 | G101: 6000 | H101: 6 | I101: 1939985 | J101: 10 | K101: ERW1 | L101: NON FIN | M101: =VLOOKUP(I101,[1]!zmat[#All],2,0) | N101: =VLOOKUP(I101,[1]!zmat[#All],21,0) | O101: =VLOOKUP(I101,[1]!zmat[#All],22,0)
A102: 0789 | B102: TVS | C102: 943209 | D102: 18.2 | E102: 0 | F102: 1 | G102: 6000 | H102: 6 | I102: 2288945 | J102: 9.3 | K102: ERW1 | L102: NON FIN | M102: =VLOOKUP(I102,[1]!zmat[#All],2,0) | N102: =VLOOKUP(I102,[1]!zmat[#All],21,0) | O102: =VLOOKUP(I102,[1]!zmat[#All],22,0)
A103: 0789 | B103: TVS | C103: 943209 | D103: 22.2 | E103: 0 | F103: 1.6 | G103: 5270 | H103: 5.27 | I103: 3575894 | J103: 60 | K103: ERW1 | L103: NON FIN | M103: =VLOOKUP(I103,[1]!zmat[#All],2,0) | N103: =VLOOKUP(I103,[1]!zmat[#All],21,0) | O103: =VLOOKUP(I103,[1]!zmat[#All],22,0)
A104: 0789 | B104: TVS | C104: 943209 | D104: 22.2 | E104: 0 | F104: 1.6 | G104: 5670 | H104: 5.67 | I104: 3570690 | J104: 21.6 | K104: ERW1 | L104: NON FIN | M104: =VLOOKUP(I104,[1]!zmat[#All],2,0) | N104: =VLOOKUP(I104,[1]!zmat[#All],21,0) | O104: =VLOOKUP(I104,[1]!zmat[#All],22,0)
A105: 0789 | B105: TVS | C105: 943209 | D105: 25.4 | E105: 0 | F105: 2 | G105: 6050 | H105: 6.05 | I105: 4055021 | J105: 10.5 | K105: ERW1 | L105: NON FIN | M105: =VLOOKUP(I105,[1]!zmat[#All],2,0) | N105: =VLOOKUP(I105,[1]!zmat[#All],21,0) | O105: =VLOOKUP(I105,[1]!zmat[#All],22,0)
A106: 0789 | B106: TVS | C106: 943209 | D106: 41.28 | E106: 0 | F106: 2.6 | G106: 6000 | H106: 6 | I106: 3974563 | J106: 19.95 | K106: ERW1 | L106: FIN CUT | M106: =VLOOKUP(I106,[1]!zmat[#All],2,0) | N106: =VLOOKUP(I106,[1]!zmat[#All],21,0) | O106: =VLOOKUP(I106,[1]!zmat[#All],22,0)
A107: 0789 | B107: TVS | C107: 943209 | D107: 40x25 | E107: 0 | F107: 1.6 | G107: 5900 | H107: 6.13 | I107: 3919144 | J107: 10 | K107: ERW1 | L107: FIN CUT | M107: =VLOOKUP(I107,[1]!zmat[#All],2,0) | N107: =VLOOKUP(I107,[1]!zmat[#All],21,0) | O107: =VLOOKUP(I107,[1]!zmat[#All],22,0)
A108: 0789 | B108: TVS | C108: 943209 | D108: 59x30 | E108: 0 | F108: 1.6 | G108: 6000 | H108: 6 | I108: 1940925 | J108: 10 | K108: ERW1 | L108: FIN CUT | M108: =VLOOKUP(I108,[1]!zmat[#All],2,0) | N108: =VLOOKUP(I108,[1]!zmat[#All],21,0) | O108: =VLOOKUP(I108,[1]!zmat[#All],22,0)

Sheet salesTVS
A1: CUSTOMER CD | B1: CUSTOMER NAME | C1: SALES UNIT | D1: qty in no | E1: Domain for z_qty_meter | F1: MATERAIL NUMBER | G1: buckets.Bucket | H1: Quantity | I1: Material Description | J1: OEM_Key.OEM | K1: buckets.CTL Bucket
A2: 0000187546 | B2: Narasipur Auto Component(P)Ltd | C2: KG | D2: 158 | E2: 701.805 | F2: 3995629 | G2: 29.4-20.4-4.5-CEW-CEW | H2: 1940 | I2: TUB-O-C-AUT-AD-FC-29.40X4.500X4.4400 | J2: TVS | K2: 29.4-20.4-4.5-CEW-CEW-1
A3: 0000187546 | B3: Narasipur Auto Component(P)Ltd | C3: KG | D3: 152 | E3: 675.397 | F3: 3995629 | G3: 29.4-20.4-4.5-CEW-CEW | H3: 1867 | I3: TUB-O-C-AUT-AD-FC-29.40X4.500X4.4400 | J3: TVS | K3: 29.4-20.4-4.5-CEW-CEW-1
A4: 0000187546 | B4: Narasipur Auto Component(P)Ltd | C4: KG | D4: 157 | E4: 697.464 | F4: 3995629 | G4: 29.4-20.4-4.5-CEW-CEW | H4: 1928 | I4: TUB-O-C-AUT-AD-FC-29.40X4.500X4.4400 | J4: TVS | K4: 29.4-20.4-4.5-CEW-CEW-1
A5: 0000187546 | B5: Narasipur Auto Component(P)Ltd | C5: KG | D5: 148 | E5: 655.862 | F5: 3995629 | G5: 29.4-20.4-4.5-CEW-CEW | H5: 1813 | I5: TUB-O-C-AUT-AD-FC-29.40X4.500X4.4400 | J5: TVS | K5: 29.4-20.4-4.5-CEW-CEW-1
A6: 0000187546 | B6: Narasipur Auto Component(P)Ltd | C6: KG | D6: 169 | E6: 750.642 | F6: 3995629 | G6: 29.4-20.4-4.5-CEW-CEW | H6: 2075 | I6: TUB-O-C-AUT-AD-FC-29.40X4.500X4.4400 | J6: TVS | K6: 29.4-20.4-4.5-CEW-CEW-1
A7: 0000944141 | B7: SRIKAM HITECH ENGINEERING PRIVATE L | C7: NOS | D7: 23 | E7: 6.419 | F7: 1939963 | G7: 12.7-0-1.2-ERW 1-PE | H7: 2.185 | I7: TUB-O-O-AUT-AW-PE-12.70X1.200X0.2780 | J7: TVS | K7: 12.7-0-1.2-ERW 1-PE-0.278
A8: 0000944141 | B8: SRIKAM HITECH ENGINEERING PRIVATE L | C8: NOS | D8: 2589 | E8: 722.547 | F8: 1939963 | G8: 12.7-0-1.2-ERW 1-PE | H8: 245.955 | I8: TUB-O-O-AUT-AW-PE-12.70X1.200X0.2780 | J8: TVS | K8: 12.7-0-1.2-ERW 1-PE-0.278
A9: 0000944141 | B9: SRIKAM HITECH ENGINEERING PRIVATE L | C9: NOS | D9: 9088 | E9: 2536.31 | F9: 1939963 | G9: 12.7-0-1.2-ERW 1-PE | H9: 863.36 | I9: TUB-O-O-AUT-AW-PE-12.70X1.200X0.2780 | J9: TVS | K9: 12.7-0-1.2-ERW 1-PE-0.278
A10: 0000944141 | B10: SRIKAM HITECH ENGINEERING PRIVATE L | C10: NOS | D10: 3000 | E10: 837.25 | F10: 1939963 | G10: 12.7-0-1.2-ERW 1-PE | H10: 285 | I10: TUB-O-O-AUT-AW-PE-12.70X1.200X0.2780 | J10: TVS | K10: 12.7-0-1.2-ERW 1-PE-0.278
A11: 0000944141 | B11: SRIKAM HITECH ENGINEERING PRIVATE L | C11: NOS | D11: 8000 | E11: 2232.667 | F11: 1939963 | G11: 12.7-0-1.2-ERW 1-PE | H11: 760 | I11: TUB-O-O-AUT-AW-PE-12.70X1.200X0.2780 | J11: TVS | K11: 12.7-0-1.2-ERW 1-PE-0.278
A12: 0000129663 | B12: ELKAYEM AUTO ANCILLARIES (PVT) LTD. | C12: NOS | D12: 5194 | E12: 2120.934 | F12: 1939966 | G12: 12.7-0-1.2-ERW 1-PE | H12: 721.966 | I12: TUB-O-O-AUT-AW-PE-12.70X1.200X0.4080 | J12: TVS | K12: 12.7-0-1.2-ERW 1-PE-0.408
A13: 0000129663 | B13: ELKAYEM AUTO ANCILLARIES (PVT) LTD. | C13: NOS | D13: 2206 | E13: 900.805 | F13: 1939966 | G13: 12.7-0-1.2-ERW 1-PE | H13: 306.634 | I13: TUB-O-O-AUT-AW-PE-12.70X1.200X0.4080 | J13: TVS | K13: 12.7-0-1.2-ERW 1-PE-0.408
... A189: 0000189002 | B189: Marathwada Auto Compo Pvt. Ltd. | C189: NOS | D189: 4 | E189: 6.865 | F189: 3672607 | G189: 15.88-0-1-ERW 1-PE | H189: 2.52 | I189: TUB-O-N-AUT-AW-PE-15.88X1.000X1.7150 | J189: TVS | K189: 15.88-0-1-ERW 1-PE-1.715
A190: 0000188595 | B190: Sri Balaji Gears | C190: KG | D190: 400 | E190: 2125.863 | F190: 3731692 | G190: 40-20-1.2-CRFH-PE | H190: 2341 | I190: TUB-R-AW-AUT-40.00X20.00X1.210X5.3100 | J190: TVS
A191: 0000188595 | B191: Sri Balaji Gears | C191: KG | D191: 226 | E191: 1197.784 | F191: 3731692 | G191: 40-20-1.2-CRFH-PE | H191: 1319 | I191: TUB-R-AW-AUT-40.00X20.00X1.210X5.3100 | J191: TVS
A192: 0000188595 | B192: Sri Balaji Gears | C192: KG | D192: 149 | E192: 790.047 | F192: 3731692 | G192: 40-20-1.2-CRFH-PE | H192: 870 | I192: TUB-R-AW-AUT-40.00X20.00X1.210X5.3100 | J192: TVS
A193: 0000188595 | B193: Sri Balaji Gears | C193: KG | D193: 396 | E193: 2103.16 | F193: 3731692 | G193: 40-20-1.2-CRFH-PE | H193: 2316 | I193: TUB-R-AW-AUT-40.00X20.00X1.210X5.3100 | J193: TVS
A194: 0000188595 | B194: Sri Balaji Gears | C194: KG | D194: 47 | E194: 248.819 | F194: 3731692 | G194: 40-20-1.2-CRFH-PE | H194: 274 | I194: TUB-R-AW-AUT-40.00X20.00X1.210X5.3100 | J194: TVS
A195: 0000188595 | B195: Sri Balaji Gears | C195: KG | D195: 210 | E195: 1116.055 | F195: 3731692 | G195: 40-20-1.2-CRFH-PE | H195: 1229 | I195: TUB-R-AW-AUT-40.00X20.00X1.210X5.3100 | J195: TVS
A196: 0000188595 | B196: Sri Balaji Gears | C196: KG | D196: 361 | E196: 1917 | F196: 3731692 | G196: 40-20-1.2-CRFH-PE | H196: 2111 | I196: TUB-R-AW-AUT-40.00X20.00X1.210X5.3100 | J196: TVS
A197: 0000189002 | B197: Marathwada Auto Compo Pvt. Ltd. | C197: NOS | D197: 1154 | E197: 2700.316 | F197: 3672608 | G197: 15.88-0-1-ERW 1-PE | H197: 991.286 | I197: TUB-O-N-AUT-AW-PE-15.88X1.000X2.3400 | J197: TVS | K197: 15.88-0-1-ERW 1-PE-2.34
A198: 0000189002 | B198: Marathwada Auto Compo Pvt. Ltd. | C198: NOS | D198: 471 | E198: 1102.122 | F198: 3672608 | G198: 15.88-0-1-ERW 1-PE | H198: 404.589 | I198: TUB-O-N-AUT-AW-PE-15.88X1.000X2.3400 | J198: TVS | K198: 15.88-0-1-ERW 1-PE-2.34
A199: 0000189287 | B199: BALAJI PRESS PRODUCTS INDIA | C199: NOS | D199: 3000 | E199: 1620.034 | F199: 1940034 | G199: 15.88-0-1.2-ERW 1-PE | H199: 704.067 | I199: TUB-O-O-AUT-AW-PE-15.88X1.200X0.5400 | J199: TVS | K199: 15.88-0-1.2-ERW 1-PE-0.54
A200: 0000189226 | B200: Neel Metal Products Limited | C200: NOS | D200: 1358 | E200: 3947.115 | F200: 3541434 | G200: 15.88-0-1-ERW 1-PE | H200: 1448.986 | I200: TUB-O-N-AUT-AW-PE-15.88X1.000X2.9050 | J200: TVS | K200: 15.88-0-1-ERW 1-PE-2.905
A201: 0000189226 | B201: Neel Metal Products Limited | C201: NOS | D201: 442 | E201: 1284.702 | F201: 3541434 | G201: 15.88-0-1-ERW 1-PE | H201: 471.614 | I201: TUB-O-N-AUT-AW-PE-15.88X1.000X2.9050 | J201: TVS | K201: 15.88-0-1-ERW 1-PE-2.905
A202: 0000189287 | B202: BALAJI PRESS PRODUCTS INDIA | C202: NOS | D202: 3000 | E202: 3926.777 | F202: 1940046 | G202: 15.88-0-1.2-ERW 1-PE | H202: 1641 | I202: TUB-O-O-AUT-AW-PE-15.88X1.200X1.3100 | J202: TVS | K202: 15.88-0-1.2-ERW 1-PE-1.31
A203: 0000189287 | B203: BALAJI PRESS PRODUCTS INDIA | C203: NOS | D203: 924 | E203: 2393.844 | F203: 2409618 | G203: 25.4-0-1.6-ERW 1-PE | H203: 2249.016 | I203: TUB-O-N-AUT-AW-PE-25.40X1.600X2.5900 | J203: TVS | K203: 25.4-0-1.6-ERW 1-PE-2.59
A204: 0000189287 | B204: BALAJI PRESS PRODUCTS INDIA | C204: NOS | D204: 76 | E204: 196.896 | F204: 2409618 | G204: 25.4-0-1.6-ERW 1-PE | H204: 184.984 | I204: TUB-O-N-AUT-AW-PE-25.40X1.600X2.5900 | J204: TVS | K204: 25.4-0-1.6-ERW 1-PE-2.59
A205: 0000189287 | B205: BALAJI PRESS PRODUCTS INDIA | C205: NOS | D205: 88 | E205: 227.985 | F205: 2409618 | G205: 25.4-0-1.6-ERW 1-PE | H205: 214.192 | I205: TUB-O-N-AUT-AW-PE-25.40X1.600X2.5900 | J205: TVS | K205: 25.4-0-1.6-ERW 1-PE-2.59
A206: 0000189287 | B206: BALAJI PRESS PRODUCTS INDIA | C206: NOS | D206: 220 | E206: 569.963 | F206: 2409618 | G206: 25.4-0-1.6-ERW 1-PE | H206: 535.48 | I206: TUB-O-N-AUT-AW-PE-25.40X1.600X2.5900 | J206: TVS | K206: 25.4-0-1.6-ERW 1-PE-2.59
A207: 0000189287 | B207: BALAJI PRESS PRODUCTS INDIA | C207: NOS | D207: 2 | E207: 5.181 | F207: 2409618 | G207: 25.4-0-1.6-ERW 1-PE | H207: 4.868 | I207: TUB-O-N-AUT-AW-PE-25.40X1.600X2.5900 | J207: TVS | K207: 25.4-0-1.6-ERW 1-PE-2.59
A208: 0000189287 | B208: BALAJI PRESS PRODUCTS INDIA | C208: NOS | D208: 325 | E208: 349.373 | F208: 3229740 | G208: 19.05-0-1.2-ERW 1-PE | H208: 177.446 | I208: TUB-O-N-AUT-AW-PE-19.05X1.200X1.0750 | J208: TVS | K208: 19.05-0-1.2-ERW 1-PE-1.075
... A216: 0000189287 | B216: BALAJI PRESS PRODUCTS INDIA | C216: NOS | D216: 101 | E216: 111.136 | F216: 2430128 | G216: 50-30-1.6-ERW 1-FC | H216: 215.837 | I216: TUB-R-AW-AUT-50.00X30.00X1.600X1.1000 | J216: TVS | K216: 50-30-1.6-ERW 1-FC-1.1
A217: 0000189287 | B217: BALAJI PRESS PRODUCTS INDIA | C217: NOS | D217: 1000 | E217: 1145.009 | F217: 4110464 | G217: 19.05-0-1.2-ERW 1-PE | H217: 604.844 | I217: TUB-O-N-AUT-AW-PE-19.05X1.200X1.1450 | J217: TVS
A218: 0000189287 | B218: BALAJI PRESS PRODUCTS INDIA | C218: NOS | D218: 1586 | E218: 1815.984 | F218: 4110464 | G218: 19.05-0-1.2-ERW 1-PE | H218: 959.283 | I218: TUB-O-N-AUT-AW-PE-19.05X1.200X1.1450 | J218: TVS
A219: 0000189287 | B219: BALAJI PRESS PRODUCTS INDIA | C219: NOS | D219: 414 | E219: 474.034 | F219: 4110464 | G219: 19.05-0-1.2-ERW 1-PE | H219: 250.406 | I219: TUB-O-N-AUT-AW-PE-19.05X1.200X1.1450 | J219: TVS
A220: 0000188595 | B220: Sri Balaji Gears | C220: NOS | D220: 1324 | E220: 1734.955 | F220: 1940801 | G220: 40-20-1.2-CRFH-PE | H220: 1910.532 | I220: TUB-R-AW-RHS-40.00X20.00X1.210X1.3100 | J220: TVS | K220: 40-20-1.2-CRFH-PE-1.31
A221: 0000188595 | B221: Sri Balaji Gears | C221: NOS | D221: 176 | E221: 230.628 | F221: 1940801 | G221: 40-20-1.2-CRFH-PE | H221: 253.968 | I221: TUB-R-AW-RHS-40.00X20.00X1.210X1.3100 | J221: TVS | K221: 40-20-1.2-CRFH-PE-1.31
A222: 0000189002 | B222: Marathwada Auto Compo Pvt. Ltd. | C222: NOS | D222: 1123 | E222: 1471.566 | F222: 1940801 | G222: 40-20-1.2-CRFH-PE | H222: 1620.489 | I222: TUB-R-AW-RHS-40.00X20.00X1.210X1.3100 | J222: TVS | K222: 40-20-1.2-CRFH-PE-1.31
A223: 0000189002 | B223: Marathwada Auto Compo Pvt. Ltd. | C223: NOS | D223: 188 | E223: 246.353 | F223: 1940801 | G223: 40-20-1.2-CRFH-PE | H223: 271.284 | I223: TUB-R-AW-RHS-40.00X20.00X1.210X1.3100 | J223: TVS | K223: 40-20-1.2-CRFH-PE-1.31
A224: 0000189002 | B224: Marathwada Auto Compo Pvt. Ltd. | C224: NOS | D224: 149 | E224: 195.248 | F224: 1940801 | G224: 40-20-1.2-CRFH-PE | H224: 215.007 | I224: TUB-R-AW-RHS-40.00X20.00X1.210X1.3100 | J224: TVS | K224: 40-20-1.2-CRFH-PE-1.31
A225: 0000189002 | B225: Marathwada Auto Compo Pvt. Ltd. | C225: NOS | D225: 40 | E225: 52.416 | F225: 1940801 | G225: 40-20-1.2-CRFH-PE | H225: 57.72 | I225: TUB-R-AW-RHS-40.00X20.00X1.210X1.3100 | J225: TVS | K225: 40-20-1.2-CRFH-PE-1.31
A226: 0000189002 | B226: Marathwada Auto Compo Pvt. Ltd. | C226: NOS | D226: 1500 | E226: 1965.583 | F226: 1940801 | G226: 40-20-1.2-CRFH-PE | H226: 2164.5 | I226: TUB-R-AW-RHS-40.00X20.00X1.210X1.3100 | J226: TVS | K226: 40-20-1.2-CRFH-PE-1.31
A227: 0000188595 | B227: Sri Balaji Gears | C227: NOS | D227: 1349 | E227: 1767.714 | F227: 1940801 | G227: 40-20-1.2-CRFH-PE | H227: 1946.607 | I227: TUB-R-AW-RHS-40.00X20.00X1.210X1.3100 | J227: TVS | K227: 40-20-1.2-CRFH-PE-1.31
A228: 0000188595 | B228: Sri Balaji Gears | C228: NOS | D228: 151 | E228: 197.869 | F228: 1940801 | G228: 40-20-1.2-CRFH-PE | H228: 217.893 | I228: TUB-R-AW-RHS-40.00X20.00X1.210X1.3100 | J228: TVS | K228: 40-20-1.2-CRFH-PE-1.31
A229: 0000189002 | B229: Marathwada Auto Compo Pvt. Ltd. | C229: NOS | D229: 799 | E229: 1047.001 | F229: 1940801 | G229: 40-20-1.2-CRFH-PE | H229: 1152.957 | I229: TUB-R-AW-RHS-40.00X20.00X1.210X1.3100 | J229: TVS | K229: 40-20-1.2-CRFH-PE-1.31
A230: 0000189002 | B230: Marathwada Auto Compo Pvt. Ltd. | C230: NOS | D230: 559 | E230: 732.507 | F230: 1940801 | G230: 40-20-1.2-CRFH-PE | H230: 806.637 | I230: TUB-R-AW-RHS-40.00X20.00X1.210X1.3100 | J230: TVS | K230: 40-20-1.2-CRFH-PE-1.31
A231: 0000189002 | B231: Marathwada Auto Compo Pvt. Ltd. | C231: NOS | D231: 84 | E231: 110.073 | F231: 1940801 | G231: 40-20-1.2-CRFH-PE | H231: 121.212 | I231: TUB-R-AW-RHS-40.00X20.00X1.210X1.3100 | J231: TVS | K231: 40-20-1.2-CRFH-PE-1.31
... A1827: 0000944141 | B1827: SRIKAM HITECH ENGINEERING PRIVATE L | C1827: NOS | D1827: 380.097 | E1827: 106.809 | F1827: 1940584 | G1827: 25.4-0-2-ERW 1-FC | H1827: 120.449 | I1827: TUB-O-O-AUT-AW-FC-25.40X2.000X0.2810 | J1827: TVS | K1827: 25.4-0-2-ERW 1-FC-0.281

Sheet pivot schedule copy check
A3: Row Labels
A4: Balaji press product
A5: ELKAYEM AUTO
A6: ELKAYEM AUTO MYSORE
A7: KAY JAY
A8: KNITVEL NEEDLES P LTD
A9: Marathwada
A10: Metalman
A11: Narasipur Auto Component(P)Ltd
A12: Rajsriya Automotive
A13: Rajsriya Mysore
A14: Rajsriya Unit 1
... A32: Grand Total

Sheet Schedule for Printing
A1: CUSTOMER NAME | B1: Sandhar
A3: CUSTOMER NAME | B3: ACTUAL OD | C3: OD | D3: ID | E3: TICKNESS | F3: LENGTH | G3: UoM | H3: SCHEDULE | I3: DISPATCH | J3: BAL IN NOS | K3: CTL stock in nos | L3: LL Stock | M3: WIP | N3: Model | O3: Application | Q3: Balaji press product | R3: Balaji Press
A4: {=_xlfn.CHOOSECOLS(scheduleapr[],_xlfn.XMATCH(A3:M3,scheduleapr[#Headers]))} | Q4: ELKAYEM AUTO | R4: Elkayem
Q5: ELKAYEM AUTO ANCILLARIES (PVT) | R5: Elkayem
Q6: ELKAYEM AUTO MYSORE | R6: Elkayem
Q7: KAY JAY | R7: Kay Jay
Q8: KNITVEL NEEDLES P LTD | R8: Knitvel
Q9: Marathwada | R9: Marathwada
Q10: Metalman | R10: Metalman
Q11: Narasipur Auto Component(P)Ltd | R11: Narsipur
Q12: NEEL METAL PRODUCTS LIMITED | R12: NMPL
Q13: NMPL (HUB) | R13: NMPL HUB
Q14: NMPL 1 | R14: NMPL 1
Q15: Rajsriya Automotive | R15: Rajsriya
Q16: Rajsriya Unit 2 | R16: Rajsriya
... Q29: TVS MOTOR COMPANY LIMITED | R29: Tvs
Q30: 0 | R30: 0

Sheet RM Tracker
A3: Sum of SCHEDULE IN MT | H3: CUSTOMER NAME
A4: ACTUAL OD | B4: OD | C4: ID | D4: TICKNESS | E4: Grade | F4: FC/NFC | G4: Bucket | H4: Balaji press product | I4: ELKAYEM AUTO | J4: ELKAYEM AUTO MYSORE | K4: KAY JAY | L4: KNITVEL NEEDLES P LTD | M4: Marathwada | N4: Metalman | O4: Narasipur Auto Component(P)Ltd | P4: Rajsriya Automotive | Q4: Rajsriya Mysore | R4: Rajsriya Unit 1 | S4: Rajsriya Unit 2 | T4: Rajsriya Unit 4 | U4: Rajsriya Unit 5 | V4: Rajsriya Unit 8 | W4: RUCHA | X4: Sandhar Automach | Y4: Sandhar Engg Mysore | Z4: SANDHAR ENGINEERING PVT LTD. | AA4: SRIKAM HITECH | AB4: TVS MOTOR COMPANY LIMITED | AC4: SRI BALAJI GEARS V4 | AD4: Laxmi | AE4: SRI BALAJI GEARS V7 | AF4: Marathwada v7 | AG4: Balaji Gears V3 | AH4: NMPL TVSM | AI4: NMPL HUB | AJ4: Grand Total
A5: 12.7 | B5: 12.7 | C5: 0 | D5: 1.2 | E5: ERW 1 | F5: PE | G5: 12.7-0-1.2-ERW 1-PE | I5: 4.0097613 | X5: 0 | AA5: 2.8369027 | AJ5: 6.846664
A6: 12.7 | B6: 12.7 | C6: 0 | D6: 1.6 | E6: ERW 1 | F6: PE | G6: 12.7-0-1.6-ERW 1-PE | H6: 2.8958237 | I6: 7.3490008 | P6: 0 | Q6: 4.771652 | S6: 0.86021066 | U6: 5.5815196 | AA6: 13.291459 | AH6: 0.95214157 | AJ6: 35.701807
A7: 12.7 | B7: 12.7 | C7: 0 | D7: 2 | E7: ERW 1 | F7: PE | G7: 12.7-0-2-ERW 1-PE | AI7: 0 | AJ7: 0
A8: 14 | B8: 14 | C8: 0 | D8: 1.6 | E8: CEW | F8: CEW | G8: 14-0-1.6-CEW-CEW | I8: 0 | AJ8: 0
A9: 14 | B9: 14 | C9: 0 | D9: 2.45 | E9: CEW | F9: CEW | G9: 14-0-2.45-CEW-CEW | Y9: 0 | AH9: 4.1850305 | AJ9: 4.1850305
A10: 14 | B10: 14 | C10: 0 | D10: 2.45 | E10: CEW | F10: (blank) | G10: 14-0-2.45-CEW- | Q10: 0 | AJ10: 0
A11: 14 | B11: 14 | C11: 9.1 | D11: 2.45 | E11: CEW | F11: (blank) | G11: 14-9.1-2.45-CEW- | N11: 0 | AJ11: 0
A12: 14 | B12: 14 | C12: 10.1 | D12: 1.95 | E12: CEW | F12: CEW | G12: 14-10.1-1.95-CEW-CEW | AA12: 0 | AJ12: 0
A13: 15.88 | B13: 15.88 | C13: 0 | D13: 1 | E13: ERW 1 | F13: PE | G13: 15.88-0-1-ERW 1-PE | M13: 20.582615 | AH13: 13.720765 | AI13: 0.30809278 | AJ13: 34.611473
A14: 15.88 | B14: 15.88 | C14: 0 | D14: 1 | E14: ERW 1 | F14: (blank) | G14: (blank) | H14: 6.668008 | AJ14: 6.668008
A15: 15.88 | B15: 15.88 | C15: 0 | D15: 1.2 | E15: ERW 1 | F15: PE | G15: 15.88-0-1.2-ERW 1-PE | H15: 5.5145532 | W15: 0 | AA15: 11.567535 | AC15: 0.065132518 | AE15: 0.78159021 | AG15: 0.065132518 | AJ15: 17.993944
A16: 15.88 | B16: 15.88 | C16: 0 | D16: 1.6 | E16: ERW 1 | F16: PE | G16: 15.88-0-1.6-ERW 1-PE | I16: 5.1362048 | J16: 2.3935165 | M16: 0 | P16: 0 | S16: 1.2446286 | U16: 1.4079509 | AA16: 4.8996691 | AJ16: 15.08197
A17: 15.88 | B17: 15.88 | C17: 0 | D17: 2 | E17: ERW 1 | F17: PE | G17: 15.88-0-2-ERW 1-PE | I17: 0 | J17: 2.4690702 | Q17: 3.9823713 | R17: 0 | V17: 0.99559283 | W17: 0 | AA17: 5.3885179 | AJ17: 12.835552
A18: 16.1 | B18: 16.1 | C18: 0 | D18: 2 | E18: CEW | F18: CEW | G18: 16.1-0-2-CEW-CEW | AI18: 0 | AJ18: 0
A19: 16.1 | B19: 16.1 | C19: 0 | D19: 2.8 | E19: CEW | F19: CEW | G19: 16.1-0-2.8-CEW-CEW | I19: 0 | P19: 0 | AJ19: 0
A20: 16.1 | B20: 16.1 | C20: 0 | D20: 2.8 | E20: CEW | F20: (blank) | G20: (blank) | J20: 6.8844657 | AJ20: 6.8844657
A21: 16.1 | B21: 16.1 | C21: 10.4 | D21: 2.7 | E21: CEW | F21: CEW | G21: 16.1-10.4-2.7-CEW-CEW | Q21: 2.6754025 | U21: 0 | AJ21: 2.6754025
A22: 16.1 | B22: 16.1 | C22: 10.7 | D22: 2.95 | E22: CEW | F22: CEW | G22: 16.1-10.7-2.95-CEW-CEW | I22: 0 | AJ22: 0
A23: 17.3 | B23: 17.3 | C23: 0 | D23: 1.2 | E23: CEW | F23: CEW | G23: 17.3-0-1.2-CEW-CEW | P23: 0 | AJ23: 0
A24: 17.3 | B24: 17.3 | C24: 0 | D24: 1.2 | E24: CEW | F24: (blank) | G24: 17.3-0-1.2-CEW- | AH24: 0 | AJ24: 0
A25: 17.3 | B25: 17.3 | C25: 0 | D25: 1.2 | E25: ERW 1 | F25: PE | G25: 17.3-0-1.2-ERW 1-PE | AH25: 0.35716401 | AI25: 1.0857786 | AJ25: 1.4429426
A26: 17.3 | B26: 17.3 | C26: 0 | D26: 1.2 | E26: ERW 1 | F26: (blank) | G26: 17.3-0-1.2-ERW 1- | Q26: 0 | AJ26: 0
A27: 17.3 | B27: 17.3 | C27: 0 | D27: 1.6 | E27: CEW | F27: (blank) | G27: 17.3-0-1.6-CEW- | I27: 0 | AJ27: 0
A28: 17.3 | B28: 17.3 | C28: 0 | D28: 1.6 | E28: ERW 1 | F28: PE | G28: 17.3-0-1.6-ERW 1-PE | I28: 9.3496615 | M28: 0 | Z28: 4.3961984 | AA28: 1.9813852 | AJ28: 15.727245
A29: 18 | B29: 26 | C29: 18 | D29: 4 | E29: CEW | F29: (blank) | G29: 26-18-4-CEW- | O29: 0 | AJ29: 0
A30: 18.2 | B30: 18.2 | C30: 0 | D30: 1 | E30: ERW 1 | F30: PE | G30: 18.2-0-1-ERW 1-PE | AH30: 0.54055257 | AI30: 3.3408269 | AJ30: 3.8813794
A31: 18.2 | B31: 18.2 | C31: 12.3 | D31: 2.95 | E31: CEW | F31: CEW | G31: 18.2-12.3-2.95-CEW-CEW | Q31: 0 | U31: 2.7722422 | AJ31: 2.7722422
A32: 19 | B32: 19 | C32: 12.5 | D32: 3.25 | E32: CEW | F32: CEW | G32: 19-12.5-3.25-CEW-CEW | N32: 1.3626583 | P32: 0 | R32: 0 | V32: 9.8414214 | AA32: 14.837835 | AJ32: 26.041915
A33: 19 | B33: 19 | C33: 12.5 | D33: 3.25 | E33: CEW | F33: (blank) | G33: 19-12.5-3.25-CEW- | AA33: 0 | AJ33: 0
A34: 19.05 | B34: 19 | C34: 12.5 | D34: 3.25 | E34: CEW | F34: CEW | G34: 19-12.5-3.25-CEW-CEW | P34: 0 | AJ34: 0
A35: 19.05 | B35: 19.05 | C35: 0 | D35: 1 | E35: ERW 1 | F35: PE | G35: 19.05-0-1-ERW 1-PE | H35: 8.5423574 | M35: 5.3389734 | AH35: 1.9487253 | AJ35: 15.830056
A36: 19.05 | B36: 19.05 | C36: 0 | D36: 1.2 | E36: CRFH | F36: PE | G36: 19.05-0-1.2-CRFH-PE | AC36: 0.89413681 | AE36: 8.743375 | AF36: 9.9355574 | AJ36: 19.573069
A37: 19.05 | B37: 19.05 | C37: 0 | D37: 1.2 | E37: ERW 1 | F37: PE | G37: 19.05-0-1.2-ERW 1-PE | H37: 24.30088 | M37: 0 | Z37: 8.5797007 | AG37: 0.9831017 | AH37: 6.9189346 | AJ37: 40.782617
A38: 19.05 | B38: 19.05 | C38: 0 | D38: 1.2 | E38: ERW 1 | F38: (blank) | G38: (blank) | H38: 4.1948137 | AJ38: 4.1948137
A39: 19.05 | B39: 19.05 | C39: 0 | D39: 1.6 | E39: ERW 1 | F39: PE | G39: 19.05-0-1.6-ERW 1-PE | N39: 0 | Z39: 3.2758324 | AA39: 0 | AH39: 0.8396041 | AJ39: 4.1154365
A40: 19.05 | B40: 19.05 | C40: 0 | D40: 1.6 | E40: ERW 1 | F40: (blank) | G40: 19.05-0-1.6-ERW 1- | P40: 0 | AH40: 0 | AJ40: 0
A41: 19.05 | B41: 19.05 | C41: 0 | D41: 1.6 | E41: ERW 2 MAHS | F41: PE | G41: 19.05-0-1.6-ERW 2 MAHS-PE | V41: 0 | AJ41: 0
A42: 19.05 | B42: 19.05 | C42: 0 | D42: 1.6 | E42: (blank) | F42: (blank) | G42: 19.05-0-1.6-- | I42: 0 | W42: 0 | AJ42: 0
A43: 19.05 | B43: 19.05 | C43: 0 | D43: 1.63 | E43: (blank) | F43: (blank) | G43: 19.05-0-1.63-- | I43: 0 | AJ43: 0
A44: 19.05 | B44: 19.05 | C44: 0 | D44: 2 | E44: ERW 1 | F44: PE | G44: 19.05-0-2-ERW 1-PE | I44: 1.3574574 | L44: 3.3621236 | Q44: 10.994144 | R44: 4.4548138 | S44: 4.787664 | U44: 10.994144 | V44: 3.2570572 | W44: 0 | AA44: 34.251634 | AJ44: 73.459039
A45: 19.05 | B45: 19.05 | C45: 0 | D45: 2 | E45: ERW 1 | F45: PE | G45: (blank) | AA45: 3.5092165 | AJ45: 3.5092165
A46: 19.05 | B46: 19.05 | C46: 0 | D46: 2 | E46: ERW 1 | F46: (blank) | G46: 19.05-0-2-ERW 1- | P46: 0 | Q46: 0 | AJ46: 0
A47: 19.05 | B47: 19.05 | C47: 0 | D47: 2 | E47: ERW 1 | F47: (blank) | G47: (blank) | Q47: 6.5141145 | AJ47: 6.5141145
A48: 19.05 | B48: 19.05 | C48: 0 | D48: 2 | E48: (blank) | F48: (blank) | G48: 19.05-0-2-- | AA48: 0 | AJ48: 0
A49: 19.05 | B49: 19.05 | C49: 0 | D49: 2.3 | E49: ERW 1 | F49: PE | G49: 19.05-0-2.3-ERW 1-PE | I49: 6.5764737 | P49: 0 | R49: 3.4185698 | S49: 7.7535062 | U49: 6.5104763 | W49: 0 | Z49: 3.7984109 | AA49: 67.953571 | AH49: 3.7414347 | AJ49: 99.752443
A50: 19.05 | B50: 19.05 | C50: 0 | D50: 2.3 | E50: ERW 1 | F50: (blank) | G50: 19.05-0-2.3-ERW 1- | P50: 0 | W50: 0 | Z50: 0 | AJ50: 0
A51: 19.05 | B51: 19.05 | C51: 0 | D51: 2.34 | E51: ERW 1 | F51: (blank) | G51: 19.05-0-2.34-ERW 1- | P51: 0 | AA51: 0 | AJ51: 0
A52: 19.05 | B52: 19.05 | C52: 0 | D52: 2.5 | E52: ERW 2 | F52: (blank) | G52: 19.05-0-2.5-ERW 2- | P52: 0 | AJ52: 0
A53: 20 | B53: 20 | C53: 12.4 | D53: 3.8 | E53: CEW | F53: CEW | G53: 20-12.4-3.8-CEW-CEW | Y53: 0 | AJ53: 0
A54: 20 | B54: 20 | C54: 12.4 | D54: 4.5 | E54: CEW | F54: CEW | G54: 20-12.4-4.5-CEW-CEW | Y54: 0 | AI54: 3.4385355 | AJ54: 3.4385355
A55: 20 | B55: 20 | C55: 17.16 | D55: 1.42 | E55: CEW | F55: CEW | G55: 20-17.16-1.42-CEW-CEW | AD55: 2.4855588 | AH55: 3.5507983 | AJ55: 6.0363571
A56: 21.7 | B56: 21.7 | C56: 16.2 | D56: 2.75 | E56: CEW | F56: CEW | G56: 21.7-16.2-2.75-CEW-CEW | U56: 1.9267815 | AA56: 0 | AH56: 0 | AJ56: 1.9267815
A57: 21.75 | B57: 21.75 | C57: 0 | D57: 3.5 | E57: CEW | F57: CEW | G57: 21.75-0-3.5-CEW-CEW | Y57: 0 | AH57: 0 | AJ57: 0
A58: 21.75 | B58: 21.75 | C58: 0 | D58: 3.5 | E58: CEW | F58: (blank) | G58: 21.75-0-3.5-CEW- | N58: 0 | Q58: 0 | AJ58: 0
A59: 22.23 | B59: 22.2 | C59: 0 | D59: 1.2 | E59: (blank) | F59: (blank) | G59: 22.2-0-1.2-- | P59: 0 | AJ59: 0
A60: 22.23 | B60: 22.23 | C60: 0 | D60: 1.2 | E60: ERW 1 | F60: PE | G60: 22.23-0-1.2-ERW 1-PE | I60: 6.505317 | S60: 0 | T60: 3.5960258 | X60: 2.478216 | Z60: 0 | AA60: 8.1363115 | AI60: 0.52251542 | AJ60: 21.238386
A61: 22.23 | B61: 22.23 | C61: 0 | D61: 1.2 | E61: ERW 1 | F61: (blank) | G61: 22.23-0-1.2-ERW 1- | AA61: 0 | AJ61: 0
A62: 22.23 | B62: 22.23 | C62: 0 | D62: 1.2 | E62: (blank) | F62: (blank) | G62: 22.23-0-1.2-- | AA62: 0 | AJ62: 0
A63: 22.23 | B63: 22.23 | C63: 0 | D63: 1.6 | E63: ERW 1 | F63: PE | G63: 22.23-0-1.6-ERW 1-PE | I63: 0 | L63: 10.495623 | M63: 0 | N63: 3.954165 | S63: 14.112952 | U63: 14.33995 | Y63: 22.455752 | Z63: 2.2293029 | AA63: 22.858491 | AH63: 9.2174352 | AI63: 34.198483 | AJ63: 133.86215
A64: 22.23 | B64: 22.23 | C64: 0 | D64: 1.6 | E64: ERW 1 | F64: (blank) | G64: 22.23-0-1.6-ERW 1- | P64: 0 | Q64: 0 | AJ64: 0
A65: 22.23 | B65: 22.23 | C65: 0 | D65: 1.6 | E65: ERW 2 MAHS | F65: PE | G65: 22.23-0-1.6-ERW 2 MAHS-PE | X65: 22.821878 | AJ65: 22.821878
A66: 22.23 | B66: 22.23 | C66: 0 | D66: 2 | E66: ERW 1 | F66: FC | G66: 22.23-0-2-ERW 1-FC | I66: 0 | J66: 17.541484 | Y66: 64.274954 | AJ66: 81.816438
A67: 22.23 | B67: 22.23 | C67: 0 | D67: 2 | E67: ERW 1 | F67: PE | G67: 22.23-0-2-ERW 1-PE | J67: 13.66299 | S67: 6.1583185 | U67: 1.8828996 | X67: 0 | Z67: 28.07894 | AA67: 4.3881136 | AH67: 11.331306 | AI67: 8.0681452 | AJ67: 73.570713
A68: 22.23 | B68: 22.23 | C68: 0 | D68: 2 | E68: ERW 1 | F68: (blank) | G68: 22.23-0-2-ERW 1- | I68: 0 | P68: 0 | Q68: 0 | AA68: 0 | AJ68: 0
A69: 22.23 | B69: 22.23 | C69: 0 | D69: 2 | E69: ERW 2 | F69: FC | G69: 22.23-0-2-ERW 2-FC | Z69: 0 | AI69: 5.9726215 | AJ69: 5.9726215
A70: 22.23 | B70: 22.23 | C70: 0 | D70: 2 | E70: ERW 2 | F70: (blank) | G70: (blank) | U70: 8.6266324 | AJ70: 8.6266324
A71: 22.23 | B71: 22.23 | C71: 0 | D71: 2 | E71: ERW 2 MAHS | F71: FC | G71: 22.23-0-2-ERW 2 MAHS-FC | X71: 41.597322 | AJ71: 41.597322
A72: 22.23 | B72: 22.23 | C72: 0 | D72: 2 | E72: ERW 2 MAHS | F72: PE | G72: 22.23-0-2-ERW 2 MAHS-PE | L72: 0.80980641 | X72: 63.178863 | AA72: 0 | AJ72: 63.988669
A73: 22.23 | B73: 22.23 | C73: 0 | D73: 2 | E73: ERW 2 MAHS | F73: (blank) | G73: (blank) | X73: 13.912315 | AJ73: 13.912315
A74: 22.23 | B74: 22.23 | C74: 0 | D74: 2 | E74: (blank) | F74: (blank) | G74: 22.23-0-2-- | L74: 0 | AJ74: 0
A75: 22.23 | B75: 22.23 | C75: 0 | D75: 2.3 | E75: ERW 1 | F75: PE | G75: 22.23-0-2.3-ERW 1-PE | I75: 0 | M75: 0 | P75: 0 | Q75: 10.451441 | S75: 0 | U75: 6.7793131 | AA75: 24.637154 | AH75: 0 | AJ75: 41.867908
A76: 22.23 | B76: 22.23 | C76: 0 | D76: 2.3 | E76: ERW 1 | F76: PE | G76: (blank) | AA76: 0 | AJ76: 0
A77: 22.23 | B77: 22.23 | C77: 0 | D77: 2.3 | E77: (blank) | F77: PE | G77: 22.23-0-2.3--PE | AA77: 0 | AJ77: 0
A78: 23.42 | B78: 19 | C78: 19 | D78: 1 | E78: CRFH | F78: PE | G78: 19-19-1-CRFH-PE | M78: 0 | AC78: 3.9869533 | AE78: 61.656994 | AF78: 58.20029 | AG78: 4.2140845 | AJ78: 128.05832
A79: 25.4 | B79: 25.4 | C79: 0 | D79: 1.2 | E79: ERW 1 | F79: PE | G79: 25.4-0-1.2-ERW 1-PE | M79: 9.1766452 | AH79: 2.4194275 | AI79: 0 | AJ79: 11.596073
A80: 25.4 | B80: 25.4 | C80: 0 | D80: 1.6 | E80: ERW 1 | F80: FC | G80: 25.4-0-1.6-ERW 1-FC | N80: 0 | Q80: 0 | W80: 0 | AJ80: 0
A81: 25.4 | B81: 25.4 | C81: 0 | D81: 1.6 | E81: ERW 1 | F81: PE | G81: 25.4-0-1.6-ERW 1-PE | H81: 19.448495 | M81: 4.843351 | P81: 0 | AH81: 0 | AJ81: 24.291846
A82: 25.4 | B82: 25.4 | C82: 0 | D82: 2 | E82: ERW 1 | F82: FC | G82: 25.4-0-2-ERW 1-FC | I82: 0 | J82: 4.1990064 | M82: 6.6907246 | P82: 0 | V82: 7.8212263 | Y82: 10.207074 | Z82: 0 | AA82: 6.4830814 | AJ82: 35.401113
A83: 25.4 | B83: 25.4 | C83: 0 | D83: 2 | E83: ERW 1 | F83: FC | G83: (blank) | V83: 1.8099564 | AJ83: 1.8099564
A84: 25.4 | B84: 25.4 | C84: 0 | D84: 2 | E84: ERW 1 | F84: PE | G84: 25.4-0-2-ERW 1-PE | S84: 6.54076 | Y84: 0 | AI84: 10.455987 | AJ84: 16.996748
A85: 25.4 | B85: 25.4 | C85: 0 | D85: 2 | E85: ERW 1 | F85: (blank) | G85: 25.4-0-2-ERW 1- | W85: 0 | AJ85: 0
A86: 25.4 | B86: 25.4 | C86: 0 | D86: 2 | E86: (blank) | F86: (blank) | G86: 25.4-0-2-- | I86: 0 | L86: 0 | P86: 0 | AJ86: 0
A87: 25.4 | B87: 25.4 | C87: 0 | D87: 2.5 | E87: CEW | F87: CEW | G87: 25.4-0-2.5-CEW-CEW | M87: 9.1866207 | R87: 6.1244138 | AJ87: 15.311034
A88: 25.4 | B88: 25.4 | C88: 0 | D88: 2.5 | E88: ERW 1 | F88: FC | G88: 25.4-0-2.5-ERW 1-FC | Y88: 32.453033 | AJ88: 32.453033
A89: 25.4 | B89: 25.4 | C89: 0 | D89: 2.5 | E89: ERW 1 | F89: (blank) | G89: 25.4-0-2.5-ERW 1- | N89: 0 | AJ89: 0
A90: 25.4 | B90: 25.4 | C90: 0 | D90: 2.6 | E90: ERW 1 | F90: (blank) | G90: 25.4-0-2.6-ERW 1- | P90: 0 | Q90: 0 | AJ90: 0
A91: 25.4 | B91: 25.4 | C91: 18.4 | D91: 3.5 | E91: CEW | F91: CEW | G91: 25.4-18.4-3.5-CEW-CEW | O91: 35.319431 | AJ91: 35.319431
A92: 25.4 | B92: 25.4 | C92: 18.4 | D92: 3.5 | E92: CEW | F92: (blank) | G92: 25.4-18.4-3.5-CEW- | O92: 0 | AJ92: 0
A93: 25.4 | B93: 25.4 | C93: 19 | D93: 3.2 | E93: CEW | F93: CEW | G93: 25.4-19-3.2-CEW-CEW | Y93: 0 | AH93: 0 | AI93: 3.5021299 | AJ93: 3.5021299
A94: 25.4 | B94: 25.4 | C94: 19 | D94: 3.2 | E94: CEW | F94: (blank) | G94: 25.4-19-3.2-CEW- | Q94: 0 | AJ94: 0
A95: 25.4 | B95: 25.4 | C95: 20.4 | D95: 2.5 | E95: CEW | F95: CEW | G95: 25.4-20.4-2.5-CEW-CEW | P95: 0 | AJ95: 0
A96: 25.4 | B96: 25.4 | C96: 20.4 | D96: 2.5 | E96: CEW | F96: (blank) | G96: 25.4-20.4-2.5-CEW- | M96: 0 | AJ96: 0
A97: 25.5 | B97: 30.15 | C97: 25.5 | D97: 2.32 | E97: CEW | F97: CEW | G97: 30.15-25.5-2.32-CEW-CEW | P97: 0 | AJ97: 0
A98: 25.6 | B98: 25.6 | C98: 16.6 | D98: 4.5 | E98: CEW | F98: (blank) | G98: 25.6-16.6-4.5-CEW- | O98: 0 | AJ98: 0
A99: 28.58 | B99: 28.58 | C99: 0 | D99: 1.2 | E99: ERW 1 | F99: PE | G99: 28.58-0-1.2-ERW 1-PE | Z99: 3.8549695 | AH99: 0.9880384 | AJ99: 4.8430079
A100: 28.58 | B100: 28.58 | C100: 0 | D100: 1.6 | E100: ERW 1 | F100: FC | G100: 28.58-0-1.6-ERW 1-FC | I100: 5.5490105 | AJ100: 5.5490105
A101: 28.58 | B101: 28.58 | C101: 0 | D101: 1.6 | E101: ERW 1 | F101: PE | G101: 28.58-0-1.6-ERW 1-PE | AA101: 0 | AJ101: 0
A102: 28.58 | B102: 28.58 | C102: 0 | D102: 1.6 | E102: ERW 1 | F102: (blank) | G102: 28.58-0-1.6-ERW 1- | N102: 0 | AJ102: 0
...

Sheet dec indent
B1: Customer | C1: Metallurgy condition | D1: Material Type | E1: GRADE | F1: OD | G1: ID | H1: THK | I1: LENGTH | J1: Length in Mtrs | K1: Key | L1: plant | M1: TSL Material Code | N1: SCH DEC- 25 | O1: BALANCE TO BE SUPPLY | P1: Stock 24-11-25 | Q1: intransist | R1: OPENIG STOCK FOR DEC-2025 | S1: order logg | T1: Opening stock including order logger | U1: INDENT FOR DEC-25 as per VSM | V1: INDENT FOR DEC-25 recommended | W1: Before 20th | X1: ofter 20th
A2: TVS | B2: RUCHA | C2: CEW AN | D2: NON FIN | E2: CEW | F2: 11 | H2: 1.5 | I2: 6000 | J2: 6 | K2: 111.56CEW | L2: 789 | M2: 2442390 | N2: 0 | O2: 0 | P2: 0 | Q2: 0 | R2: =P2-O2 | S2: 0 | T2: =R2+S2 | U2: =N2-T2 | V2: =IF(U2>0,U2,0)*150%
A3: TVS | B3: RUCHA | C3: ERW1 | D3: NON FIN | E3: ERW | F3: 12.7 | H3: 1.2 | I3: 6000 | J3: 6 | K3: 12.71.26ERW | L3: 0789 | M3: 1939985 | N3: 10 | O3: 3 | P3: 7 | Q3: 0 | R3: =P3-O3 | S3: 0 | T3: =R3+S3 | U3: =N3-T3 | V3: =IF(U3>0,U3,0)*150%
A4: HMSI | B4: BADVE | C4: ERW1 | D4: NON FIN | E4: ERW | F4: 12.7 | H4: 1.4 | I4: 6000 | J4: 6 | K4: 12.71.46ERW | L4: 0789 | M4: 1931117 | N4: 0 | O4: 0 | P4: 4.5 | Q4: 0 | R4: =P4-O4 | S4: 0 | T4: =R4+S4 | U4: =N4-T4 | V4: =IF(U4>0,U4,0)*150%
A5: HMSI | B5: BADVE | C5: ERW1 | D5: NON FIN | E5: ERW | F5: 12.7 | H5: 1.6 | I5: 6000 | J5: 6 | K5: 12.71.66ERW | L5: 0789 | M5: 1931154 | N5: 0 | O5: 0 | P5: 3 | Q5: 0 | R5: =P5-O5 | S5: 0 | T5: =R5+S5 | U5: =N5-T5 | V5: =IF(U5>0,U5,0)*150%
A6: TVS | B6: RUCHA | C6: ERW1 | D6: NON FIN | E6: ERW | F6: 12 | H6: 2 | I6: 6000 | J6: 6 | K6: 12.726ERW | L6: 0789 | M6: 236166 | N6: 0 | O6: 0 | P6: 0 | Q6: 0 | R6: =P6-O6 | S6: 0 | T6: =R6+S6 | U6: =N6-T6 | V6: =IF(U6>0,U6,0)*150%
A7: HMSI | B7: BADVE | C7: ERW1 | D7: NON FIN | E7: ERW | F7: 15.88 | H7: 1 | I7: 6000 | J7: 6 | K7: 15.8816ERW | L7: 0789 | M7: 1940054 | N7: 0 | O7: 0 | P7: 1.4 | Q7: 0 | R7: =P7-O7 | S7: 0 | T7: =R7+S7 | U7: =N7-T7 | V7: =IF(U7>0,U7,0)*150%
A8: TVS | B8: RUCHA | C8: ERW1 | D8: NON FIN | E8: ERW | F8: 15.88 | H8: 1.2 | I8: 6000 | J8: 6 | K8: 15.881.26ERW | L8: 0789 | M8: 1940054 | N8: 8 | O8: 3 | P8: 19.8 | Q8: 0 | R8: =P8-O8 | S8: 0 | T8: =R8+S8 | U8: =N8-T8 | V8: =IF(U8>0,U8,0)*150%
A9: HMSI | B9: BADVE | C9: ERW1 | D9: NON FIN | E9: ERW | F9: 15.88 | H9: 1.6 | I9: 6000 | J9: 6 | K9: 15.881.66ERW | L9: 0789 | M9: 1900224 | N9: 0 | O9: 1 | P9: 3.1 | Q9: 0 | R9: =P9-O9 | S9: 0 | T9: =R9+S9 | U9: =N9-T9 | V9: =IF(U9>0,U9,0)*150%
A10: HMSI | B10: BADVE | C10: ERW1 | D10: NON FIN | E10: ERW | F10: 15.88 | H10: 2 | I10: 6000 | J10: 6 | K10: 15.8826ERW | L10: 0789 | M10: 1940120 | N10: 0 | O10: 0 | P10: 9 | Q10: 0 | R10: =P10-O10 | S10: 0 | T10: =R10+S10 | U10: =N10-T10 | V10: =IF(U10>0,U10,0)*150%
A11: TVS | B11: Rucha | C11: ERW1 | D11: NON FIN | E11: ERW | F11: 18.3 | H11: 1 | I11: 6000 | J11: 6 | K11: 18.316ERW | L11: 0789 | M11: 2288945 | N11: 5 | O11: 2 | P11: 6.5 | Q11: 0 | R11: =P11-O11 | S11: 0 | T11: =R11+S11 | U11: =N11-T11 | V11: =IF(U11>0,U11,0)*150%
A12: HMSI | B12: BADVE | C12: ERW1 | D12: NON FIN | E12: ERW | F12: 19.05 | H12: 1.6 | I12: 6000 | J12: 6 | K12: 19.051.66ERW | L12: 56 | M12: 3498997 | N12: 5 | O12: 3 | P12: 12.5 | Q12: 0 | R12: =P12-O12 | S12: 0 | T12: =R12+S12 | U12: =N12-T12 | V12: =IF(U12>0,U12,0)*150%
A13: HMSI | B13: BADVE | C13: ERW2 | D13: NON FIN | E13: ERW2 | F13: 19.05 | H13: 1.4 | I13: 6000 | J13: 6 | K13: 19.051.46ERW2 | L13: 056 | M13: 3891285 | N13: 5 | O13: 0 | P13: 0 | Q13: 0 | R13: =P13-O13 | S13: 25 | T13: =R13+S13 | U13: =N13-T13 | V13: =IF(U13>0,U13,0)*150%
A14: TVS | B14: RUCHA | C14: ERW1 | D14: NON FIN | E14: ERW | F14: 19.05 | H14: 2 | I14: 5800 | N14: 35 | O14: 0 | P14: 0 | Q14: 0 | R14: 0 | S14: 0 | T14: =R14+S14 | U14: =N14-T14 | V14: =IF(U14>0,U14,0)*150%
A15: TVS | B15: RUCHA,METALMAN | C15: ERW1 | D15: NON FIN | E15: ERW | F15: 19.05 | H15: 2.3 | I15: 7000 | J15: 7 | K15: 19.052.37ERW | L15: 056 | M15: 3500582 | N15: 20 | O15: 6 | P15: 8 | Q15: 0 | R15: =P15-O15 | S15: 0 | T15: =R15+S15 | U15: =N15-T15 | V15: =IF(U15>0,U15,0)*150%
A16: TVS | B16: RUCHA | C16: ERW1 | D16: NON FIN | E16: ERW | F16: 21.4 | H16: 1.6 | I16: 6000 | J16: 6 | K16: 21.41.66ERW | M16: 3219710 | N16: 10 | O16: 2 | P16: 12.9 | Q16: 0 | R16: =P16-O16 | S16: 0 | T16: =R16+S16 | U16: =N16-T16 | V16: =IF(U16>0,U16,0)*150%
A17: TVS | B17: RUCHA | C17: ERW1 | D17: NON FIN | E17: ERW | F17: 22.2 | H17: 1.2 | I17: 5870 | J17: 5.87 | K17: 22.21.25.87ERW | L17: 056 | M17: 3882110 | N17: 30 | O17: 10 | P17: 11 | Q17: 0 | R17: =P17-O17 | S17: 45 | T17: =R17+S17 | U17: =N17-T17 | V17: =IF(U17>0,U17,0)*150%
A18: HMSI | B18: BADVE | C18: ERW2 | D18: NON FIN | E18: ERW-2 | F18: 22.2 | H18: 1.4 | I18: 6000 | J18: 6 | K18: 22.21.46ERW-2 | L18: 056 | M18: 3829175 | N18: 10 | O18: 2 | P18: 19.7 | Q18: 0 | R18: =P18-O18 | S18: 0 | T18: =R18+S18 | U18: =N18-T18 | V18: =IF(U18>0,U18,0)*150%
A19: TVS | B19: RUCHA | C19: ERW1 | D19: NON FIN | E19: ERW | F19: 22.2 | H19: 1.6 | I19: 5270 | N19: 35 | O19: 10 | P19: 20 | Q19: 0 | R19: =P19-O19 | S19: 0 | T19: =R19+S19 | U19: =N19-T19 | V19: =IF(U19>0,U19,0)*150%
A20: TVS | B20: RUCHA | C20: ERW1 | D20: NON FIN | E20: ERW | F20: 22.2 | H20: 1.6 | I20: 5670 | N20: 30 | O20: 10 | P20: 0 | Q20: 0 | R20: =P20-O20 | S20: 0 | T20: =R20+S20 | U20: =N20-T20 | V20: =IF(U20>0,U20,0)*150%
A21: TVS | B21: RUCHA | C21: ;;;;;o;;l;ll;;;;l;l;;;l;;;l;;;;l;l;;l;;;;l;;;;;;l;l;;;;;;l;;;;;;;l;;;;;lll;;;;;l;l;o;;;;;;;;;l;;;;;;;;;l;;;;l;;;l;l;;;;;l;;ll;l;;;l;;;ll;;o;l;;;lll;;lll;l;;l;;;;;lllllllllllllllllllllllllllllllllllllllll;o;ooooooooooooooooooooooooooooooooooooooooooooooooooooooooooooooooooo;o | D21: NON FIN | E21: ERW | F21: 22.2 | H21: 2 | I21: 5950 | J21: 5.95 | L21: 056 | M21: 3905466 | N21: 90 | O21: 30 | P21: 20 | Q21: 0 | R21: =P21-O21 | S21: 90 | T21: =R21+S21 | U21: =N21-T21 | V21: =IF(U21>0,U21,0)*150%
A22: TVS | B22: RUCHA | C22: ERW1 | D22: NON FIN | E22: ERW | F22: 22.2 | H22: 2 | I22: 5100 | J22: 5.95 | L22: 056 | M22: 3500554 | N22: 20 | O22: 5 | P22: 5 | Q22: 0 | R22: =P22-O22 | S22: 4.1 | T22: =R22+S22 | U22: =N22-T22 | V22: =IF(U22>0,U22,0)*150%
A23: TVS | B23: RUCHA | C23: ERW2 | D23: FIN CUT | E23: HST | F23: 22.2 | H23: 2 | I23: 6000 | J23: 6000 | K23: 22.226.15HST | L23: 056 | N23: 40 | O23: 5 | P23: 14.6 | Q23: 0 | R23: =P23-O23 | S23: 2.6 | T23: =R23+S23 | U23: =N23-T23 | V23: =IF(U23>0,U23,0)*150%
A24: HMSI | B24: BADVE | C24: CR ERW 1 | D24: FIN CUT | E24: CR ERW | F24: 22.2 | H24: 2 | I24: 5400 | J24: 5.39 | K24: 22.225.39CR ERW | L24: 056 | M24: 3568328 | N24: 10 | O24: 2 | P24: 23.5 | Q24: 0 | R24: =P24-O24 | S24: 0 | T24: =R24+S24 | U24: =N24-T24 | V24: =IF(U24>0,U24,0)*150%
A25: HMSI | B25: BADVE | C25: ERW2 | D25: FIN CUT | E25: HST | F25: 25.4 | H25: 1.4 | I25: 5531 | J25: 5.531 | K25: 25.41.45.531HST | L25: 056 | M25: 3501900 | N25: 15 | O25: 0 | P25: 0 | Q25: 0 | R25: =P25-O25 | S25: 5.9 | T25: =R25+S25 | U25: =N25-T25 | V25: =IF(U25>0,U25,0)*150%
A26: HMSI | B26: BADVE | C26: ERW1 | D26: FIN CUT | E26: ERW | F26: 25.4 | H26: 1.4 | I26: 6060 | J26: 6.06 | K26: 25.41.46.06ERW | M26: 3557792 | N26: 15 | O26: 0 | P26: 0 | Q26: 0 | R26: =P26-O26 | S26: 0 | T26: =R26+S26 | U26: =N26-T26 | V26: =IF(U26>0,U26,0)*150%
A27: TVS | B27: RUCHA | C27: ERW1 | D27: NON FIN | E27: ERW | F27: 25.4 | H27: 1.6 | I27: 6000 | J27: 6 | K27: 25.41.66ERW | L27: 056 | M27: 3500097 | N27: 25 | O27: 5 | P27: 52.8 | Q27: 0 | R27: =P27-O27 | S27: 15 | T27: =R27+S27 | U27: =N27-T27 | V27: =IF(U27>0,U27,0)*150%
A28: RE | B28: BELRISE CHENNAI | C28: MICRO ALLOY | D28: NON FIN | E28: MICRO ALLOY | F28: 25.4 | H28: 1.6 | I28: 5840 | J28: 5.82 | N28: 25 | O28: 0 | P28: 22.7 | Q28: 0 | R28: =P28-O28 | S28: 0 | T28: =R28+S28 | U28: =N28-T28 | V28: =IF(U28>0,U28,0)*150%
A29: TVS | B29: RUCHA | C29: ERW1 | D29: NON FIN | E29: ERW | F29: 25.4 | H29: 2 | I29: 6050 | N29: 0 | O29: 0 | P29: 13.4 | Q29: 0 | R29: =P29-O29 | S29: 20 | T29: =R29+S29 | U29: =N29-T29 | V29: =IF(U29>0,U29,0)*150%
A30: TVS | B30: RUCHA | C30: ERW1 | D30: NON FIN | E30: ERW | F30: 25.4 | H30: 2.5 | I30: 5530 | J30: 5.53 | K30: 25.42.55.53ERW | L30: 056 | M30: 3502256 | N30: 0 | O30: 10 | P30: 43 | Q30: 0 | R30: =P30-O30 | S30: 2.8 | T30: =R30+S30 | U30: =N30-T30 | V30: =IF(U30>0,U30,0)*150%
A31: TVS | B31: RUCHA,METALMAN | C31: ERW1 | D31: FIN CUT | E31: ERW | F31: 28.6 | H31: 1.2 | I31: 6000 | J31: 6 | K31: 28.61.26ERW | M31: 3702101 | N31: 0 | O31: 0 | P31: 2.3 | Q31: 0 | R31: =P31-O31 | S31: 0 | T31: =R31+S31 | U31: =N31-T31 | V31: =IF(U31>0,U31,0)*150%
A32: TVS | B32: RUCHA | C32: CEW1 | D32: FIN CUT | E32: CEW | F32: 28.6 | H32: 2.65 | I32: 6000 | J32: 6 | K32: 28.62.656CEW | L32: 0788 | M32: 2410388 | N32: 10 | O32: 0 | P32: 9.8 | Q32: 0 | R32: =P32-O32 | S32: 0 | T32: =R32+S32 | U32: =N32-T32 | V32: =IF(U32>0,U32,0)*150%
A33: TVS | B33: RUCHA,METALMAN | C33: ERW1 | D33: FIN CUT | E33: ERW | F33: 31.75 | H33: 1.2 | I33: 6000 | J33: 6 | K33: 31.751.26ERW | L33: 056 | M33: 3884381 | N33: 0 | O33: 0 | P33: 29.1 | Q33: 2 | R33: =P33-O33 | S33: 1.2 | T33: =R33+S33 | U33: =N33-T33 | V33: =IF(U33>0,U33,0)*150%
A34: TVS | B34: RUCHA,METALMAN | C34: ERW1 | D34: FIN CUT | E34: ERW | F34: 31.75 | H34: 2 | I34: 6000 | J34: 6 | N34: 0 | O34: 1 | P34: 10.4 | Q34: 1.5 | R34: =P34-O34 | S34: 0 | T34: =R34+S34 | U34: =N34-T34 | V34: =IF(U34>0,U34,0)*150%
A35: RE | B35: BELRISE | C35: ERW1 | D35: FIN CUT | E35: ERW | F35: 31.75 | H35: 2.3 | I35: 5920 | N35: 15 | O35: 2 | P35: 7 | Q35: 0 | R35: =P35-O35 | S35: 0 | T35: =R35+S35 | U35: =N35-T35 | V35: =IF(U35>0,U35,0)*150%
A36: 0 | B36: RUCHA,METALMAN | C36: ERW1 | D36: FIN CUT | E36: ERW | F36: 34.93 | H36: 1.2 | I36: 6000 | J36: 6 | K36: 34.931.26ERW | M36: 1940701 | N36: 0 | O36: 3 | P36: 60 | Q36: 30 | R36: =P36-O36 | S36: 47 | T36: =R36+S36 | U36: =N36-T36 | V36: =IF(U36>0,U36,0)*150%
A37: RE | B37: BELRISE | C37: ERW1 | D37: FIN CUT | E37: ERW | F37: 34.93 | H37: 1.2 | I37: 780 | J37: 0.62 | L37: 0789 | M37: 2397073 | N37: 10 | O37: 0 | P37: 0 | Q37: 0 | R37: =P37-O37 | S37: 0 | T37: =R37+S37 | U37: =N37-T37 | V37: =IF(U37>0,U37,0)*150%
A38: RE | B38: RAJSRIYA | C38: ERW1 | D38: FIN CUT | E38: ERW | F38: 34.93 | H38: 1.2 | I38: 650 | J38: 0.7 | L38: 0789 | M38: 3649699 | N38: 10 | O38: 0 | P38: 0 | Q38: 0 | R38: =P38-O38 | S38: 0 | T38: =R38+S38 | U38: =N38-T38 | V38: =IF(U38>0,U38,0)*150%
A39: HMSI | B39: BADVE | C39: ERW2 | D39: FIN CUT | E39: ERW | F39: 34 | H39: 1.4 | I39: 5660 | J39: 5.66 | K39: 341.45.66ERW | L39: 0788 | M39: 3702855 | N39: 5 | O39: 0 | P39: 0 | Q39: 0 | R39: =P39-O39 | S39: 7.5 | T39: =R39+S39 | U39: =N39-T39 | V39: =IF(U39>0,U39,0)*150%
A40: TVS | B40: RUCHA,METALMAN | C40: ERW370 | D40: FIN CUT | E40: HST | F40: 38.1 | H40: 1.6 | I40: 6190 | J40: 6.19 | K40: 38.11.66.19HST | L40: 056 | M40: 3502254 | N40: 30 | O40: 10 | P40: 59 | Q40: 0 | R40: =P40-O40 | S40: 0 | T40: =R40+S40 | U40: =N40-T40 | V40: =IF(U40>0,U40,0)*150%
A41: TVS | B41: RUCHA,METALMAN | C41: ERW1 | D41: FIN CUT | E41: ERW | F41: 38.1 | H41: 2 | I41: 5650 | J41: 5.65 | K41: 38.125.65ERW | L41: 056 | M41: 3500959 | N41: 20 | O41: 5 | P41: 35 | Q41: 0 | R41: =P41-O41 | S41: 0 | T41: =R41+S41 | U41: =N41-T41 | V41: =IF(U41>0,U41,0)*150%
A42: TVS | B42: RUCHA,METALMAN | C42: ERW2 | D42: FIN CUT | E42: HST | F42: 38.1 | H42: 2.5 | I42: 6190 | J42: 6.19 | K42: 38.12.56.19HST | L42: 056 | M42: 3502007 | N42: 35 | O42: 10 | P42: 64 | Q42: 0 | R42: =P42-O42 | S42: 16 | T42: =R42+S42 | U42: =N42-T42 | V42: =IF(U42>0,U42,0)*150%
A43: RE | B43: BELRISE | C43: ERW2 | D43: FIN CUT | E43: ERW -2 | F43: 38.1 | H43: 3.2 | I43: 6000 | J43: 6 | N43: 10 | O43: 0 | P43: 1.9 | Q43: 0 | R43: =P43-O43 | S43: 15 | T43: =R43+S43 | U43: =N43-T43 | V43: =IF(U43>0,U43,0)*150% | W43: khopoli
A44: TVS | B44: RUCHA | C44: ERW1 | D44: FIN CUT | E44: ERW | F44: 41.28 | H44: 2.6 | I44: 6000 | J44: 6 | K44: 41.282.66.08ERW | L44: 0789 | M44: 3994149 | N44: 35 | O44: 0 | P44: 0 | Q44: 18 | R44: =P44-O44 | S44: 13 | T44: =R44+S44 | U44: =N44-T44 | V44: =IF(U44>0,U44,0)*150%
A45: TVS | B45: RUCHA | C45: ERW1 | D45: FIN CUT | E45: ERW | F45: 40x25 | H45: 1.6 | I45: 5900 | J45: 6.13 | L45: 0789 | N45: 0 | O45: 0 | P45: 7.8 | Q45: 0 | R45: =P45-O45 | S45: 0 | T45: =R45+S45 | U45: =N45-T45 | V45: =IF(U45>0,U45,0)*150%
A46: HMSI | B46: BADVE | C46: ERW1 | D46: FIN CUT | E46: ERW | F46: 41.28 | H46: 3.15 | I46: 5860 | J46: 5.86 | K46: 41.283.155.86ERW | M46: 3673889 | N46: 30 | O46: 8 | P46: 58 | Q46: 0 | R46: =P46-O46 | S46: 18.5 | T46: =R46+S46 | U46: =N46-T46 | V46: =IF(U46>0,U46,0)*150%
A47: TVS | B47: RUCHA,METALMAN | C47: ERW AN | D47: FIN CUT | E47: ERW | F47: 42.7 | H47: 3.5 | I47: 6000 | J47: 6 | K47: 42.73.56ERW | L47: 0788 | M47: 2396465 | N47: 0 | O47: 0 | P47: 17 | Q47: 0 | R47: =P47-O47 | S47: 0 | T47: =R47+S47 | U47: =N47-T47 | V47: =IF(U47>0,U47,0)*150%
A48: TVS | B48: RUCHA,METALMAN | C48: ERW AN | D48: FIN CUT | E48: ERW | F48: 42.7 | H48: 4 | I48: 6000 | J48: 6 | K48: 42.746ERW | M48: 3501985 | N48: 30 | O48: 0 | P48: 0 | Q48: 0 | R48: =P48-O48 | S48: 0 | T48: =R48+S48 | U48: =N48-T48 | V48: =IF(U48>0,U48,0)*150%
A49: TVS | B49: RUCHA,METALMAN | C49: ERW1 | D49: FIN CUT | E49: ERW | F49: 40x30 | H49: 1.6 | I49: 5900 | J49: 5.9 | L49: 0788 | M49: 3836440 | N49: 10 | O49: 2 | P49: 3 | Q49: 0 | R49: =P49-O49 | S49: 0 | T49: =R49+S49 | U49: =N49-T49 | V49: =IF(U49>0,U49,0)*150%
A50: HMSI | B50: BADVE | C50: ERW2 | D50: FIN CUT | E50: HST | F50: 45 | H50: 1.4 | I50: 6400 | J50: 6.42 | K50: 451.46.42HST | M50: 3502343 | N50: 0 | O50: 0 | P50: 46 | Q50: 0 | R50: =P50-O50 | S50: 0 | T50: =R50+S50 | U50: =N50-T50 | V50: =IF(U50>0,U50,0)*150%
A51: HMSI | B51: BADVE | C51: ERW1 | D51: FIN CUT | E51: ERW | F51: 45 | H51: 1.4 | I51: 5700 | J51: 5.7 | K51: 451.45.7ERW | L51: 056 | M51: 3545558 | N51: 0 | O51: 0 | P51: 8 | Q51: 0 | R51: =P51-O51 | S51: 0 | T51: =R51+S51 | U51: =N51-T51 | V51: =IF(U51>0,U51,0)*150%
A52: HMSI | B52: BADVE | C52: ERW2 | D52: FIN CUT | E52: HST | F52: 45 | H52: 1.6 | I52: 6400 | J52: 6.42 | K52: 451.66.42HST | M52: 3502388 | N52: 0 | O52: 0 | P52: 15 | Q52: 0 | R52: =P52-O52 | S52: 0 | T52: =R52+S52 | U52: =N52-T52 | V52: =IF(U52>0,U52,0)*150%
A53: HMSI | B53: BADVE | C53: CEW-1 | D53: FIN CUT | E53: CEW-1 | F53: 45 | H53: 3.5 | I53: 6100 | M53: 3500263 | N53: 10 | O53: 0 | P53: 6 | Q53: 0 | R53: =P53-O53 | S53: 18 | T53: =R53+S53 | U53: =N53-T53 | V53: =IF(U53>0,U53,0)*150%
A54: RE | B54: BELRISE | C54: CEW-1 | D54: FIN CUT | E54: CEW | F54: 47.63 | H54: 4 | I54: 6040 | J54: 6.04 | N54: 0 | O54: 0 | P54: 1.4 | Q54: 0 | R54: =P54-O54 | S54: 13.5 | T54: =R54+S54 | U54: =N54-T54 | V54: =IF(U54>0,U54,0)*150%
A55: RE | B55: BELRISE | C55: ERW1 | D55: FIN CUT | E55: ERW | F55: 48 | H55: 1.2 | I55: 780 | J55: 0.62 | L55: 0789 | M55: 2397072 | N55: 15 | O55: 0 | P55: 0 | Q55: 0 | R55: =P55-O55 | S55: 0 | T55: =R55+S55 | U55: =N55-T55 | V55: =IF(U55>0,U55,0)*150%
A56: RE | B56: RAJSRIYA | C56: ERW1 | D56: FIN CUT | E56: ERW | F56: 48 | H56: 1.2 | I56: 650 | J56: 0.7 | L56: 0789 | M56: 3649700 | N56: 14 | O56: 0 | P56: 0 | Q56: 0 | R56: =P56-O56 | S56: 0 | T56: =R56+S56 | U56: =N56-T56 | V56: =IF(U56>0,U56,0)*150%
A57: HMSI | B57: BADVE | C57: ERW2 | D57: FIN CUT | E57: HST | F57: 48.6 | H57: 2 | I57: 6270 | J57: 6.27 | K57: 48.626.27HST | M57: 3502301 | N57: 0 | O57: 0 | P57: 24 | Q57: 0 | R57: =P57-O57 | S57: 0 | T57: =R57+S57 | U57: =N57-T57 | V57: =IF(U57>0,U57,0)*150%
A58: HMSI | B58: BADVE | C58: ERW2 | D58: FIN CUT | E58: HST | F58: 48.6 | H58: 2.3 | I58: 6270 | J58: 6.27 | K58: 48.62.36.27HST | M58: 3549720 | N58: 0 | O58: 0 | P58: 23 | Q58: 0 | R58: =P58-O58 | S58: 0 | T58: =R58+S58 | U58: =N58-T58 | V58: =IF(U58>0,U58,0)*150%
A59: HMSI | B59: BADVE | C59: ERW1 | D59: FIN CUT | E59: ERW | F59: 48.6 | H59: 3.5 | I59: 6000 | J59: 6 | K59: 48.63.56ERW | M59: 3502422 | N59: 20 | O59: 0 | P59: 0 | Q59: 0 | R59: =P59-O59 | S59: 0 | T59: =R59+S59 | U59: =N59-T59 | V59: =IF(U59>0,U59,0)*150%
A60: TVS | B60: RUCHA | C60: ERW1 | D60: FIN CUT | E60: ERW | F60: 59x30 | H60: 1.6 | I60: 6000 | J60: 6 | L60: 0789 | N60: 5 | O60: 0 | P60: 0 | Q60: 0 | R60: =P60-O60 | S60: 0 | T60: =R60+S60 | U60: =N60-T60 | V60: =IF(U60>0,U60,0)*150%
A61: RE | B61: KUNAL | C61: ERW1 | D61: FIN CUT | E61: ERW | F61: 59x30 | H61: 1.6 | I61: 572.5 | J61: 0.5725 | K61: 59x301.60.5725ERW | L61: 0789 | M61: 2420716 | N61: 20 | O61: 0 | P61: 0 | Q61: 0 | R61: =P61-O61 | S61: 0 | T61: =R61+S61 | U61: =N61-T61 | V61: =IF(U61>0,U61,0)*150%
A62: RE | B62: BELRISE | C62: ERW1 | D62: FIN CUT | E62: ERW | F62: 50X50 | H62: 1.6 | I62: 6040 | J62: 6.04 | N62: 10 | O62: 2 | P62: 3 | Q62: 0 | R62: =P62-O62 | S62: 0 | T62: =R62+S62 | U62: =N62-T62 | V62: =IF(U62>0,U62,0)*150%
A63: RE | B63: BELRISE | C63: ERW1 | D63: FIN CUT | E63: ERW | F63: 50.8 | H63: 2.6 | I63: 6000 | J63: 6 | K63: 0 | L63: 0 | N63: 0 | O63: 0 | P63: 27 | Q63: 9 | R63: =P63-O63 | S63: 20 | T63: =R63+S63 | U63: 5 | V63: =IF(U63>0,U63,0)*150%
A64: RE | B64: BELRISE | C64: CEW-1 | D64: FIN CUT | E64: CEW | F64: 50.8 | G64: 45.6 | H64: 2.6 | I64: 6000 | J64: 6 | K64: 0 | N64: 0 | O64: 0 | P64: 1.2 | Q64: 0 | R64: =P64-O64 | S64: 32 | T64: =R64+S64 | U64: 5 | V64: =IF(U64>0,U64,0)*150%
A65: TVS | B65: METALMAN | C65: ERW1 | D65: FIN CUT | E65: ERW | F65: 54 | H65: 3 | I65: 59100 | N65: 15 | O65: 0 | P65: 0 | Q65: 0 | R65: =P65-O65 | S65: 15 | T65: =R65+S65 | U65: 10 | V65: =IF(U65>0,U65,0)*150%
A66: TVS | B66: RUCHA,METALMAN | C66: ERW1 | D66: FIN CUT | E66: ERW | F66: 57.15 | H66: 2.5 | I66: 5710 | J66: 5.71 | L66: 056 | M66: 3907863 | N66: 60 | O66: 10 | P66: 69.5 | Q66: 0 | R66: =P66-O66 | S66: 59 | T66: =R66+S66 | U66: =N66-T66 | V66: =IF(U66>0,U66,0)*150%
A67: TVS | B67: RUCHA,METALMAN | C67: ERW1 | D67: FIN CUT | E67: ERW | F67: 57.15 | H67: 2.5 | I67: 5750 | L67: 056 | N67: 15 | O67: 2 | P67: 60.8 | Q67: 0 | R67: =P67-O67 | S67: 0 | T67: =R67+S67 | U67: =N67-T67 | V67: =IF(U67>0,U67,0)*150%
A68: TVS | B68: RUCHA,METALMAN | C68: ERW1 | D68: FIN CUT | E68: ERW | F68: 57.15 | H68: 2.5 | I68: 6100 | J68: 6.75 | L68: 056 | M68: 3910001 | N68: 60 | O68: 10 | P68: 60 | Q68: 0 | R68: =P68-O68 | S68: 16.7 | T68: =R68+S68 | U68: =N68-T68 | V68: =IF(U68>0,U68,0)*150%
A69: HMSI | B69: BADVE | C69: ERW1 | D69: FIN CUT | E69: ERW | F69: 57.15 | H69: 3 | I69: 5650 | J69: 5.65 | K69: 57.1535.65ERW | L69: 056 | M69: 3501105 | N69: 10 | O69: 0 | P69: 15.5 | Q69: 0 | R69: =P69-O69 | S69: 1.7 | T69: =R69+S69 | U69: =N69-T69 | V69: =IF(U69>0,U69,0)*150%
A70: TVS | B70: METALMAN | C70: ERW1 | D70: FIN CUT | E70: ERW | F70: 60.3 | H70: 2 | I70: 5900 | J70: 5.9 | L70: 0788 | N70: 20 | O70: 5 | P70: 22 | Q70: 0 | R70: =P70-O70 | S70: 0 | T70: =R70+S70 | U70: =N70-T70 | V70: =IF(U70>0,U70,0)*150%
I71: TOTAL | N71: =SUM(N2:N70) | O71: =SUM(O2:O70) | P71: =SUM(P2:P70) | Q71: =SUM(Q2:Q70) | R71: =SUM(R2:R70) | S71: =SUM(S2:S70) | T71: =SUM(T2:T70) | U71: =SUM(U2:U70) | ... X71: =SUM(X2:X70)

Sheet Chamferring and Angle cut
A1: Outer Diameter of Material | B1: Thickness for TATA Tubes Material | C1: Length for TATA Tubes Material | D1: MATERAIL NUMBER | E1: Material Description | F1: Cham/Angle Cut
A2: 12.7 | B2: 1.2 | C2: 0.278 | D2: 000000000001939963 | E2: TUB-O-O-AUT-AW-PE-12.70X1.200X0.2780 | F2: De-burring
A3: 12.7 | B3: 1.2 | C3: 0.408 | D3: 000000000001939966 | E3: TUB-O-O-AUT-AW-PE-12.70X1.200X0.4080 | F3: De-burring
A4: 12.7 | B4: 1.2 | C4: 0.772 | D4: 000000000001939974 | E4: TUB-O-O-AUT-AW-PE-12.70X1.200X0.7720 | F4: De-burring
A5: 12.7 | B5: 1.2 | C5: 6 | D5: 000000000001939986 | E5: TUB-O-O-GEN-AW-PE-12.70X1.200X6.0000 | F5: De-burring
A6: 12.7 | B6: 1.2 | C6: 6 | D6: 000000000001939985 | E6: TUB-O-O-AUT-AW-PE-12.70X1.200X6.0000 | F6: De-burring
A7: 12.7 | B7: 1.5 | C7: 0.164 | D7: 000000000003181176 | E7: TUB-O-N-AUT-AW-PE-12.70X1.500X0.1640 | F7: De-burring
A8: 12.7 | B8: 1.5 | C8: 0.17 | D8: 000000000003204542 | E8: TUB-O-N-AUT-AW-PE-12.70X1.500X0.1703 | F8: De-burring
A9: 12.7 | B9: 1.5 | C9: 0.174 | D9: 000000000003181177 | E9: TUB-O-N-AUT-AW-PE-12.70X1.500X0.1740 | F9: De-burring
A10: 12.7 | B10: 1.5 | C10: 0.184 | D10: 000000000003204544 | E10: TUB-O-N-AUT-AW-PE-12.70X1.500X0.1840 | F10: De-burring
A11: 12.7 | B11: 1.6 | C11: 0.145 | D11: 000000000001939991 | E11: TUB-O-O-AUT-AW-PE-12.70X1.600X0.1450 | F11: De-burring
A12: 12.7 | B12: 1.6 | C12: 0.189 | D12: 000000000003432081 | E12: TUB-O-N-AUT-AW-PE-12.70X1.600X0.1890 | F12: De-burring
A13: 12.7 | B13: 1.6 | C13: 0.255 | D13: 000000000003223304 | E13: TUB-O-N-AUT-AW-PE-12.70X1.600X0.2550 | F13: De-burring
... A219: 22.23 | B219: 1.6 | C219: 0.394 | D219: 000000000001938251 | E219: TUB-O-N-AUT-AW-PE-22.23X1.600X0.3940 | F219: De-burring
A220: 22.23 | B220: 1.6 | C220: 0.675 | D220: 2427939 | E220: TUB-O-N-AUT-AW-PE-22.23X1.600X0.6750 | F220: Taper Cutting
A221: 22.23 | B221: 1.6 | C221: 0.69 | D221: 3714733 | E221: TUB-O-N-AUT-AW-PE-22.23X1.600X0.690 | F221: De-burring
A222: 22.23 | B222: 1.6 | C222: 0.7 | D222: 2270133 | E222: TUB-O-N-AUT-HR-PE-22.23X1.600X0.7000 | F222: De-burring
A223: 22.23 | B223: 1.6 | C223: 0.74 | D223: 1940407 | E223: TUB-O-O-AUT-AW-PE-22.23X1.600X0.7400 | F223: De-burring
A224: 22.23 | B224: 1.6 | C224: 0.88 | D224: 2418687 | E224: TUB-O-N-AUT-AW-PE-22.23X1.600X0.8800 | F224: De-burring
A225: 22.23 | B225: 1.6 | C225: 0.935 | D225: 1940416 | E225: TUB-O-O-AUT-AW-PE-22.23X1.60X0.935-MAHS | F225: Chamferring
A226: 22.23 | B226: 1.6 | C226: 0.945 | D226: 3599863 | E226: TUB-O-N-AUT-AW-PE-22.23X1.600X0.9450 | F226: De-burring
A227: 22.23 | B227: 1.6 | C227: 0.949 | D227: 3673012 | E227: TUB-O-N-AUT-AW-PE-22.23X1.600X0.9490 | F227: De-burring
A228: 22.23 | B228: 1.6 | C228: 1.175 | D228: 1940420 | E228: TUB-O-O-AUT-AW-PE-22.23X1.600X1.1750 | F228: De-burring
A229: 22.23 | B229: 1.6 | C229: 1.304 | D229: 3673011 | E229: TUB-O-N-AUT-AW-PE-22.23X1.600X1.3040 | F229: De-burring
A230: 22.23 | B230: 2 | C230: 0.124 | D230: 3181172 | E230: TUB-O-N-AUT-AW-PE-22.23X2.000X0.1240 | F230: De-burring
A231: 22.23 | B231: 2 | C231: 0.178 | D231: 3181173 | E231: TUB-O-N-AUT-AW-PE-22.23X2.000X0.1780 | F231: De-burring
... A529: 54 | B529: 3 | C529: 1.14 | D529: 2396464 | E529: TUB-O-N-AUT-AN-FC-54.00X3.000X1.1400 | F529: De-burring
A530: 57.15 | B530: 2 | C530: 0.713 | D530: 460176|1940908 | E530: PT4-O-N-AUT-NR-AG-57.15X2.000X0.713 | F530: Angle Cut
A531: 57.15 | B531: 2.3 | C531: 1.365 | D531: 3182342 | E531: TUB-O-N-AUT-AW-FC-57.15X2.300X1.3650 | F531: Angle Cut
A532: 57.15 | B532: 2.5 | C532: 0.326 | D532: 3732177 | E532: TUB-O-N-AUT-AW-AG-57.15X2.500X0.3260 | F532: Angle Cut
A533: 57.15 | B533: 2.5 | C533: 0.375 | D533: 2440972 | E533: TUB-O-N-AUT-AW-FC-57.15X2.500X0.3750 | F533: De-burring
A534: 57.15 | B534: 2.5 | C534: 0.526 | D534: 3731697 | E534: CUT-O-N-AUT-AW-AG-57.15X2.500X0.5260 | F534: Angle Cut
A535: 57.15 | B535: 2.5 | C535: 5.711 | D535: 3907863 | E535: TUB-O-N-AUT-AW-FC-57.15X2.500X5.7110 | F535: De-burring
A536: 57.15 | B536: 2.5 | C536: 6 | D536: 3515489 | E536: TUB-O-N-AUT-AP-FC-57.15X2.500X6.0000 | F536: De-burring
A537: 57.15 | B537: 2.5 | C537: 6.02 | D537: 3520439 | E537: TUB-O-N-AUT-HR-FC-57.15X2.500X6.0200 | F537: De-burring
A538: 57.15 | B538: 2.5 | C538: 6.1 | D538: 3910001 | E538: TUB-O-N-AUT-AW-FC-57.15X2.500X6.1000 | F538: De-burring
A539: 57.15 | B539: 3 | C539: 0.46 | D539: 3136139 | E539: TUB-O-N-AUT-AW-FC-57.15X3.000X0.4600 | F539: De-burring
A540: 57.15 | B540: 3 | C540: 5.65 | D540: 3501105 | E540: TUB-O-N-AUT-AW-FC-57.15X3.000X5.65-ERW 1 | F540: De-burring
A541: 59 | B541: 1.6 | C541: 0.571 | D541: 3781648 | E541: TUB-E-AW-AUT-59.00X30.00X1.600X0.5710 | F541: De-burring
A542: 59 | B542: 1.6 | C542: 0.573 | D542: 2420716 | E542: TUB-E-AW-AUT-59.00X30.00X1.600X0.5725 | F542: De-burring
... A556: 70 | B556: 3.2 | C556: 0.49 | D556: 424601 | E556: TUB-O-N-AUT-AN-AG-70.00X3.200X0.490 HST | F556: Angle Cut
A557: 70 | B557: 3.2 | C557: 0.512 | D557: 3801263|3768903 | E557: CUT-N-AUT-AN-FC-70.00X3.200X0.5120 | F557: Angle Cut
A558: 88.9 | B558: 3.2 | C558: 6 | D558: 000000000003702274 | E558: TUB-O-N-GEN-AW-FC-88.90X3.200X6.0000 | F558: De-burring
A559: 88.9 | B559: 4.5 | C559: 6 | D559: 000000000003702251 | E559: TUB-O-N-GEN-AW-FC-88.90X4.500X6.0000 | F559: De-burring
A560: 96 | B560: 3.6 | C560: 6 | D560: 000000000003504753 | E560: TUB-R-BU-RHS-96.00X48.00X3.600X6.00-210 | F560: De-burring
A561: 96 | B561: 3.6 | C561: 6 | D561: 000000000003503970 | E561: TUB-R-BU-RHS-96.00X48.00X3.60X6.000-310 | F561: De-burring
A562: 100 | B562: 2.5 | C562: 6 | D562: 000000000003505208 | E562: TUB-S-BL-SHS-100.00X100.00X2.50X6.00 310 | F562: De-burring
A563: 101.6 | B563: 3.2 | C563: 6 | D563: 000000000003702252 | E563: TUB-O-N-GEN-AW-FC-101.60X3.200X6.0000 | F563: De-burring
A564: 113.5 | B564: 4.5 | C564: 6 | D564: 000000000003504024 | E564: TUB-S-BU-SHS-113.50X113.50X4.50X6.00-310 | F564: De-burring
A565: 114.3 | B565: 3.2 | C565: 6 | D565: 000000000003702253 | E565: TUB-O-N-GEN-AW-FC-114.30X3.200X6.0000 | F565: De-burring
A566: 122 | B566: 3.6 | C566: 6 | D566: 000000000003693901 | E566: TUB-R-BU-RHS-122.00X61.00X3.60X6.000-240 | F566: De-burring
A567: 132 | B567: 3.6 | C567: 6 | D567: 000000000003503188 | E567: TUB-S-BU-SHS-132.00X132.00X3.60X6.00-210 | F567: De-burring
A568: 145 | B568: 2.9 | C568: 6 | D568: 000000000003504369 | E568: TUB-R-BU-RHS-145.00X82.00X2.900X6.00-310 | F568: De-burring
... A570: 150 | B570: 6 | C570: 6 | D570: 000000000003509371 | E570: TUB-S-BU-SHS-150.00X150.00X6.000X6.0-210 | F570: De-burring
A571: 50.8 | B571: 1.6 | C571: 0.385 | D571: 2353927 | F571: Angle Cut
A572: 57.15 | B572: 2.5 | C572: 0.772 | D572: 1940911 | 114860 | F572: Angle Cut
A573: 60.3 | B573: 2 | C573: 0.493 | D573: 3662752 | F573: Angle Cut
A574: 60.3 | B574: 2 | C574: 0.525 | D574: 3768903 | F574: Angle Cut
A575: 19.05 | B575: 1.6 | C575: 394 | D575: 3122347 | E575: TUB-O-N-AUT-AW-PE-19.05X1.600X0.3940(HSST) | F575: Angle Cut
A576: 19.05 | B576: 1.6 | C576: 775 | D576: 2425969 | E576: TUB-O-N-AUT-AW-FC-19.05X1.600X0.7750 | F576: Angle Cut

Sheet RM Tracker Pasted
A1: Buckets not in paster rm tracker but are in RM tracker | C1: Buckets not in RM tracker but are in paster rm tracker | J1: ACTUAL OD | K1: OD | L1: ID | M1: TICKNESS | N1: GRADE | O1: FC/NFC | P1: Bucket | Q1: Plant | R1: Requirement | S1: Sales | T1: Stock CTL | U1: Stock LL | V1: WIP | W1: Total Stock | X1: GAP | Y1: Remark | Z1: ACTUAL OD2 | AA1: OD3 | AB1: ID4 | AC1: TICKNESS5 | AD1: GRADE6 | AE1: FC/NFC7 | AF1: Bucket8 | AG1: Bucket9 | AH1: Balaji press product | AI1: ELKAYEM AUTO | AJ1: ELKAYEM AUTO MYSORE | AK1: KAY JAY | AL1: Marathwada | AM1: Metalman | AN1: Narasipur Auto Component(P)Ltd | AO1: NMPL (HUB) | AP1: NMPL 1 | AQ1: Rajsriya Mysore | AR1: Rajsriya Unit 1 | AS1: Rajsriya Unit 2 | AT1: Rajsriya Unit 4 | AU1: Rajsriya Unit 5 | AV1: Rajsriya Unit 8 | AW1: Sandhar Automach | AX1: Sandhar Engg Mysore | AY1: SANDHAR ENGINEERING PVT LTD. | AZ1: SRIKAM HITECH | BA1: TVS MOTOR COMPANY LIMITED | BB1: SRI BALAJI GEARS V4 | BC1: SRI BALAJI GEARS V3 | BD1: Laxmi | BE1: Grand Total
A2: {=_xlfn._xlws.FILTER('RM Tracker'!$G$5:$G$106,ISNA(_xlfn.XMATCH('RM Tracker'!$G$5:$G$106,Table11[Bucket])))} | C2: {=_xlfn._xlws.FILTER(Table11[Bucket],ISNA(_xlfn.XMATCH(Table11[Bucket],'RM Tracker'!G5:G104)))} | J2: 12.7 | K2: 12.7 | L2: 0 | M2: 1.2 | N2: ERW 1 | O2: PE | P2: 12.7-0-1.2-ERW 1-PE | Q2: Hosur | R2: =Table11[[#This Row],[Grand Total]] | S2: =VLOOKUP(Table11[[#This Row],[Bucket]],salesforecast[[#All],[Bucket2]:[WIP]],3,0) | T2: =VLOOKUP(Table11[[#This Row],[Bucket]],salesforecast[[#All],[Bucket2]:[WIP]],4,0) | U2: =VLOOKUP(Table11[[#This Row],[Bucket]],salesforecast[[#All],[Bucket2]:[WIP]],5,0) | V2: =VLOOKUP(Table11[[#This Row],[Bucket]],salesforecast[[#All],[Bucket2]:[WIP]],7,0) | W2: =Table11[[#This Row],[Stock LL]]+Table11[[#This Row],[WIP]]+Table11[[#This Row],[Stock CTL]] | X2: =IF((Table11[[#This Row],[Requirement]]-Table11[[#This Row],[Sales]]-Table11[[#This Row],[Total Stock]])<0,0,Table11[[#This Row],[Requirement]]-Table11[[#This Row],[Sales]]-Table11[[#This Row],[Total Stock]]) | Z2: 12.7 | AA2: 12.7 | AB2: 0 | AC2: 1.2 | AD2: ERW 1 | AE2: PE | AF2: 12.7-0-1.2-ERW 1-PE | AG2: =EXACT(Table11[[#This Row],[Bucket8]],Table11[[#This Row],[Bucket]]) | AI2: 4.2914106 | AZ2: 1.8912685 | BE2: 6.1826791
A3: 14-0-2.45-CEW- | C3: 29.4-20.4-4.5-CEW-CEW | J3: 12.7 | K3: 12.7 | L3: 0 | M3: 1.6 | N3: ERW 1 | O3: PE | P3: 12.7-0-1.6-ERW 1-PE | Q3: Hosur | R3: =Table11[[#This Row],[Grand Total]] | S3: =VLOOKUP(Table11[[#This Row],[Bucket]],salesforecast[[#All],[Bucket2]:[WIP]],3,0) | T3: =VLOOKUP(Table11[[#This Row],[Bucket]],salesforecast[[#All],[Bucket2]:[WIP]],4,0) | U3: =VLOOKUP(Table11[[#This Row],[Bucket]],salesforecast[[#All],[Bucket2]:[WIP]],5,0) | V3: =VLOOKUP(Table11[[#This Row],[Bucket]],salesforecast[[#All],[Bucket2]:[WIP]],7,0) | W3: =Table11[[#This Row],[Stock LL]]+Table11[[#This Row],[WIP]]+Table11[[#This Row],[Stock CTL]] | X3: =IF((Table11[[#This Row],[Requirement]]-Table11[[#This Row],[Sales]]-Table11[[#This Row],[Total Stock]])<0,0,Table11[[#This Row],[Requirement]]-Table11[[#This Row],[Sales]]-Table11[[#This Row],[Total Stock]]) | Y3: =ROUND(Table11[[#This Row],[Total Stock]]/Table11[[#This Row],[Requirement]]*100,0) & "% coverage. Further rolling by week 2" | Z3: 12.7 | AA3: 12.7 | AB3: 0 | AC3: 1.6 | AD3: ERW 1 | AE3: PE | AF3: 12.7-0-1.6-ERW 1-PE | AG3: =EXACT(Table11[[#This Row],[Bucket8]],Table11[[#This Row],[Bucket]]) | AH3: 1.6547564 | AI3: 5.6865835 | AP3: 0.63476105 | AQ3: 4.771652 | AS3: 0.50780884 | AU3: 5.5815196 | AZ3: 6.9167066 | BE3: 25.753788
A4: 14-9.1-2.45-CEW- | C4: 29.4-20.4-4.5-CEW STKM 13C-CEW | J4: 14 | K4: 14 | L4: 0 | M4: 1.6 | N4: CEW | O4: CEW | P4: 14-0-1.6-CEW-CEW | Q4: Khopoli | R4: =Table11[[#This Row],[Grand Total]] | S4: =VLOOKUP(Table11[[#This Row],[Bucket]],salesforecast[[#All],[Bucket2]:[WIP]],3,0) | T4: =VLOOKUP(Table11[[#This Row],[Bucket]],salesforecast[[#All],[Bucket2]:[WIP]],4,0) | U4: =VLOOKUP(Table11[[#This Row],[Bucket]],salesforecast[[#All],[Bucket2]:[WIP]],5,0) | V4: =VLOOKUP(Table11[[#This Row],[Bucket]],salesforecast[[#All],[Bucket2]:[WIP]],7,0) | W4: =Table11[[#This Row],[Stock LL]]+Table11[[#This Row],[WIP]]+Table11[[#This Row],[Stock CTL]] | X4: =IF((Table11[[#This Row],[Requirement]]-Table11[[#This Row],[Sales]]-Table11[[#This Row],[Total Stock]])<0,0,Table11[[#This Row],[Requirement]]-Table11[[#This Row],[Sales]]-Table11[[#This Row],[Total Stock]]) | Y4: no order | Z4: 14 | AA4: 14 | AB4: 0 | AC4: 1.6 | AD4: CEW | AE4: CEW | AF4: 14-0-1.6-CEW-CEW | AG4: =EXACT(Table11[[#This Row],[Bucket8]],Table11[[#This Row],[Bucket]]) | AI4: 1.2225904 | BE4: 1.2225904
A5: (blank) | C5: 30-25.5-2.25-CEW-CEW | J5: 14 | K5: 14 | L5: 0 | M5: 2.45 | N5: CEW | O5: CEW | P5: 14-0-2.45-CEW-CEW | Q5: Khopoli | R5: =Table11[[#This Row],[Grand Total]] | S5: =VLOOKUP(Table11[[#This Row],[Bucket]],salesforecast[[#All],[Bucket2]:[WIP]],3,0) | T5: =VLOOKUP(Table11[[#This Row],[Bucket]],salesforecast[[#All],[Bucket2]:[WIP]],4,0) | U5: =VLOOKUP(Table11[[#This Row],[Bucket]],salesforecast[[#All],[Bucket2]:[WIP]],5,0) | V5: =VLOOKUP(Table11[[#This Row],[Bucket]],salesforecast[[#All],[Bucket2]:[WIP]],7,0) | W5: =Table11[[#This Row],[Stock LL]]+Table11[[#This Row],[WIP]]+Table11[[#This Row],[Stock CTL]] | X5: =IF((Table11[[#This Row],[Requirement]]-Table11[[#This Row],[Sales]]-Table11[[#This Row],[Total Stock]])<0,0,Table11[[#This Row],[Requirement]]-Table11[[#This Row],[Sales]]-Table11[[#This Row],[Total Stock]]) | Y5: no order | Z5: 14 | AA5: 14 | AB5: 0 | AC5: 2.45 | AD5: CEW | AE5: CEW | AF5: 14-0-2.45-CEW-CEW | AG5: =EXACT(Table11[[#This Row],[Bucket8]],Table11[[#This Row],[Bucket]]) | AP5: 2.7900203 | AX5: 0.33549994 | BE5: 3.1255203
A6: 16.1-0-2-CEW-CEW | C6: 25-25-1.2-CRFH-PE | J6: 14 | K6: 14 | L6: 10.1 | M6: 1.95 | N6: CEW | O6: CEW | P6: 14-10.1-1.95-CEW-CEW | Q6: Khopoli | R6: =Table11[[#This Row],[Grand Total]] | S6: =VLOOKUP(Table11[[#This Row],[Bucket]],salesforecast[[#All],[Bucket2]:[WIP]],3,0) | T6: =VLOOKUP(Table11[[#This Row],[Bucket]],salesforecast[[#All],[Bucket2]:[WIP]],4,0) | U6: =VLOOKUP(Table11[[#This Row],[Bucket]],salesforecast[[#All],[Bucket2]:[WIP]],5,0) | V6: =VLOOKUP(Table11[[#This Row],[Bucket]],salesforecast[[#All],[Bucket2]:[WIP]],7,0) | W6: =Table11[[#This Row],[Stock LL]]+Table11[[#This Row],[WIP]]+Table11[[#This Row],[Stock CTL]] | X6: =IF((Table11[[#This Row],[Requirement]]-Table11[[#This Row],[Sales]]-Table11[[#This Row],[Total Stock]])<0,0,Table11[[#This Row],[Requirement]]-Table11[[#This Row],[Sales]]-Table11[[#This Row],[Total Stock]]) | Y6: No Commitment | Z6: 14 | AA6: 14 | AB6: 10.1 | AC6: 1.95 | AD6: CEW | AE6: CEW | AF6: 14-10.1-1.95-CEW-CEW | AG6: =EXACT(Table11[[#This Row],[Bucket8]],Table11[[#This Row],[Bucket]]) | AZ6: 1.7375696 | BE6: 1.7375696
A7: (blank) | C7: 31.75-0-1.2-ERW 1-FC | J7: 15.88 | K7: 15.88 | L7: 0 | M7: 1 | N7: ERW 1 | O7: PE | P7: 15.88-0-1-ERW 1-PE | Q7: Hosur | R7: =Table11[[#This Row],[Grand Total]] | S7: =VLOOKUP(Table11[[#This Row],[Bucket]],salesforecast[[#All],[Bucket2]:[WIP]],3,0) | T7: =VLOOKUP(Table11[[#This Row],[Bucket]],salesforecast[[#All],[Bucket2]:[WIP]],4,0) | U7: =VLOOKUP(Table11[[#This Row],[Bucket]],salesforecast[[#All],[Bucket2]:[WIP]],5,0) | V7: =VLOOKUP(Table11[[#This Row],[Bucket]],salesforecast[[#All],[Bucket2]:[WIP]],7,0) | W7: =Table11[[#This Row],[Stock LL]]+Table11[[#This Row],[WIP]]+Table11[[#This Row],[Stock CTL]] | X7: =IF((Table11[[#This Row],[Requirement]]-Table11[[#This Row],[Sales]]-Table11[[#This Row],[Total Stock]])<0,0,Table11[[#This Row],[Requirement]]-Table11[[#This Row],[Sales]]-Table11[[#This Row],[Total Stock]]) | Z7: 15.88 | AA7: 15.88 | AB7: 0 | AC7: 1 | AD7: ERW 1 | AE7: PE | AF7: 15.88-0-1-ERW 1-PE | AG7: =EXACT(Table11[[#This Row],[Bucket8]],Table11[[#This Row],[Bucket]]) | AO7: 0.10269759 | AP7: 6.6716758 | BE7: 6.7743734
A8: 16.1-10.7-2.95-CEW-CEW | C8: 31.75-0-1.2-ERW 1-PE | J8: 15.88 | K8: 15.88 | L8: 0 | M8: 1.2 | N8: ERW 1 | O8: PE | P8: 15.88-0-1.2-ERW 1-PE | Q8: Hosur | R8: =Table11[[#This Row],[Grand Total]] | S8: =VLOOKUP(Table11[[#This Row],[Bucket]],salesforecast[[#All],[Bucket2]:[WIP]],3,0) | T8: =VLOOKUP(Table11[[#This Row],[Bucket]],salesforecast[[#All],[Bucket2]:[WIP]],4,0) | U8: =VLOOKUP(Table11[[#This Row],[Bucket]],salesforecast[[#All],[Bucket2]:[WIP]],5,0) | V8: =VLOOKUP(Table11[[#This Row],[Bucket]],salesforecast[[#All],[Bucket2]:[WIP]],7,0) | W8: =Table11[[#This Row],[Stock LL]]+Table11[[#This Row],[WIP]]+Table11[[#This Row],[Stock CTL]] | X8: =IF((Table11[[#This Row],[Requirement]]-Table11[[#This Row],[Sales]]-Table11[[#This Row],[Total Stock]])<0,0,Table11[[#This Row],[Requirement]]-Table11[[#This Row],[Sales]]-Table11[[#This Row],[Total Stock]]) | Y8: =_xlfn.CONCAT(ROUND(Table11[[#This Row],[Total Stock]]/Table11[[#This Row],[Requirement]]*100,0),"% Coverage. Rest by Week 3") | Z8: 15.88 | AA8: 15.88 | AB8: 0 | AC8: 1.2 | AD8: ERW 1 | AE8: PE | AF8: 15.88-0-1.2-ERW 1-PE | AG8: =EXACT(Table11[[#This Row],[Bucket8]],Table11[[#This Row],[Bucket]]) | AH8: 3.9817679 | AZ8: 9.6396126 | BB8: 0.56448182 | BC8: 0.56448182 | BE8: 14.750344
A9: 17.3-0-1.2-CEW-CEW | C9: 31.75-0-1.6-ERW 1-FC | J9: 15.88 | K9: 15.88 | L9: 0 | M9: 1.6 | N9: ERW 1 | O9: PE | P9: 15.88-0-1.6-ERW 1-PE | Q9: Hosur | R9: =Table11[[#This Row],[Grand Total]] | S9: =VLOOKUP(Table11[[#This Row],[Bucket]],salesforecast[[#All],[Bucket2]:[WIP]],3,0) | T9: =VLOOKUP(Table11[[#This Row],[Bucket]],salesforecast[[#All],[Bucket2]:[WIP]],4,0) | U9: =VLOOKUP(Table11[[#This Row],[Bucket]],salesforecast[[#All],[Bucket2]:[WIP]],5,0) | V9: =VLOOKUP(Table11[[#This Row],[Bucket]],salesforecast[[#All],[Bucket2]:[WIP]],7,0) | W9: =Table11[[#This Row],[Stock LL]]+Table11[[#This Row],[WIP]]+Table11[[#This Row],[Stock CTL]] | X9: =IF((Table11[[#This Row],[Requirement]]-Table11[[#This Row],[Sales]]-Table11[[#This Row],[Total Stock]])<0,0,Table11[[#This Row],[Requirement]]-Table11[[#This Row],[Sales]]-Table11[[#This Row],[Total Stock]]) | Z9: 15.88 | AA9: 15.88 | AB9: 0 | AC9: 1.6 | AD9: ERW 1 | AE9: PE | AF9: 15.88-0-1.6-ERW 1-PE | AG9: =EXACT(Table11[[#This Row],[Bucket8]],Table11[[#This Row],[Bucket]]) | AI9: 6.1977998 | AL9: 1.1263607 | AS9: 0.49785143 | AZ9: 6.3188835 | BE9: 14.140895
A10: 17.3-0-1.2-CEW- | C10: 31.75-0-2.3-ERW 1-FC | J10: 15.88 | K10: 15.88 | L10: 0 | M10: 2 | N10: ERW 1 | O10: PE | P10: 15.88-0-2-ERW 1-PE | Q10: Hosur | R10: =Table11[[#This Row],[Grand Total]] | S10: =VLOOKUP(Table11[[#This Row],[Bucket]],salesforecast[[#All],[Bucket2]:[WIP]],3,0) | T10: =VLOOKUP(Table11[[#This Row],[Bucket]],salesforecast[[#All],[Bucket2]:[WIP]],4,0) | U10: =VLOOKUP(Table11[[#This Row],[Bucket]],salesforecast[[#All],[Bucket2]:[WIP]],5,0) | V10: =VLOOKUP(Table11[[#This Row],[Bucket]],salesforecast[[#All],[Bucket2]:[WIP]],7,0) | W10: =Table11[[#This Row],[Stock LL]]+Table11[[#This Row],[WIP]]+Table11[[#This Row],[Stock CTL]] | X10: =IF((Table11[[#This Row],[Requirement]]-Table11[[#This Row],[Sales]]-Table11[[#This Row],[Total Stock]])<0,0,Table11[[#This Row],[Requirement]]-Table11[[#This Row],[Sales]]-Table11[[#This Row],[Total Stock]]) | Y10: =_xlfn.CONCAT(ROUND(Table11[[#This Row],[Total Stock]]/Table11[[#This Row],[Requirement]]*100,0),"% Coverage. Rest by Week 3") | Z10: 15.88 | AA10: 15.88 | AB10: 0 | AC10: 2 | AD10: ERW 1 | AE10: PE | AF10: 15.88-0-2-ERW 1-PE | AG10: =EXACT(Table11[[#This Row],[Bucket8]],Table11[[#This Row],[Bucket]]) | AJ10: 1.7124197 | AQ10: 0.99559283 | AV10: 0.99559283 | AZ10: 5.3885179 | BE10: 9.0921232
A11: 17.3-0-1.2-ERW 1- | C11: 31.75-0-2.5-ERW 1-FC | J11: 16.1 | K11: 16.1 | L11: 0 | M11: 2.8 | N11: CEW | O11: CEW | P11: 16.1-0-2.8-CEW-CEW | Q11: Khopoli | R11: =Table11[[#This Row],[Grand Total]] | S11: =VLOOKUP(Table11[[#This Row],[Bucket]],salesforecast[[#All],[Bucket2]:[WIP]],3,0) | T11: =VLOOKUP(Table11[[#This Row],[Bucket]],salesforecast[[#All],[Bucket2]:[WIP]],4,0) | U11: =VLOOKUP(Table11[[#This Row],[Bucket]],salesforecast[[#All],[Bucket2]:[WIP]],5,0) | V11: =VLOOKUP(Table11[[#This Row],[Bucket]],salesforecast[[#All],[Bucket2]:[WIP]],7,0) | W11: =Table11[[#This Row],[Stock LL]]+Table11[[#This Row],[WIP]]+Table11[[#This Row],[Stock CTL]] | X11: =IF((Table11[[#This Row],[Requirement]]-Table11[[#This Row],[Sales]]-Table11[[#This Row],[Total Stock]])<0,0,Table11[[#This Row],[Requirement]]-Table11[[#This Row],[Sales]]-Table11[[#This Row],[Total Stock]]) | Y11: no order | Z11: 16.1 | AA11: 16.1 | AB11: 0 | AC11: 2.8 | AD11: CEW | AE11: CEW | AF11: 16.1-0-2.8-CEW-CEW | AG11: =EXACT(Table11[[#This Row],[Bucket8]],Table11[[#This Row],[Bucket]]) | AI11: 2.7537863 | BE11: 2.7537863
A12: 17.3-0-1.6-CEW- | C12: 31.75-25-3.37-CEW-CEW | J12: 16.1 | K12: 16.1 | L12: 10.4 | M12: 2.7 | N12: CEW | O12: CEW | P12: 16.1-10.4-2.7-CEW-CEW | Q12: Khopoli | R12: =Table11[[#This Row],[Grand Total]] | S12: =VLOOKUP(Table11[[#This Row],[Bucket]],salesforecast[[#All],[Bucket2]:[WIP]],3,0) | T12: =VLOOKUP(Table11[[#This Row],[Bucket]],salesforecast[[#All],[Bucket2]:[WIP]],4,0) | U12: =VLOOKUP(Table11[[#This Row],[Bucket]],salesforecast[[#All],[Bucket2]:[WIP]],5,0) | V12: =VLOOKUP(Table11[[#This Row],[Bucket]],salesforecast[[#All],[Bucket2]:[WIP]],7,0) | W12: =Table11[[#This Row],[Stock LL]]+Table11[[#This Row],[WIP]]+Table11[[#This Row],[Stock CTL]] | X12: =IF((Table11[[#This Row],[Requirement]]-Table11[[#This Row],[Sales]]-Table11[[#This Row],[Total Stock]])<0,0,Table11[[#This Row],[Requirement]]-Table11[[#This Row],[Sales]]-Table11[[#This Row],[Total Stock]]) | Y12: 16 MT supplied in Apr against schedule of 6 MT. Next Lot expected in last week of May'25 | Z12: 16.1 | AA12: 16.1 | AB12: 10.4 | AC12: 2.7 | AD12: CEW | AE12: CEW | AF12: 16.1-10.4-2.7-CEW-CEW | AG12: =EXACT(Table11[[#This Row],[Bucket8]],Table11[[#This Row],[Bucket]]) | AQ12: 2.6754025 | BE12: 2.6754025
A13: 26-18-4-CEW- | C13: 33.3-29.3-2-CEW-CEW | J13: 17.3 | K13: 17.3 | L13: 0 | M13: 1.2 | N13: ERW 1 | O13: PE | P13: 17.3-0-1.2-ERW 1-PE | Q13: Hosur | R13: =Table11[[#This Row],[Grand Total]] | S13: =VLOOKUP(Table11[[#This Row],[Bucket]],salesforecast[[#All],[Bucket2]:[WIP]],3,0) | T13: =VLOOKUP(Table11[[#This Row],[Bucket]],salesforecast[[#All],[Bucket2]:[WIP]],4,0) | U13: =VLOOKUP(Table11[[#This Row],[Bucket]],salesforecast[[#All],[Bucket2]:[WIP]],5,0) | V13: =VLOOKUP(Table11[[#This Row],[Bucket]],salesforecast[[#All],[Bucket2]:[WIP]],7,0) | W13: =Table11[[#This Row],[Stock LL]]+Table11[[#This Row],[WIP]]+Table11[[#This Row],[Stock CTL]] | X13: =IF((Table11[[#This Row],[Requirement]]-Table11[[#This Row],[Sales]]-Table11[[#This Row],[Total Stock]])<0,0,Table11[[#This Row],[Requirement]]-Table11[[#This Row],[Sales]]-Table11[[#This Row],[Total Stock]]) | Y13: No Commitment | Z13: 17.3 | AA13: 17.3 | AB13: 0 | AC13: 1.2 | AD13: ERW 1 | AE13: PE | AF13: 17.3-0-1.2-ERW 1-PE | AG13: =EXACT(Table11[[#This Row],[Bucket8]],Table11[[#This Row],[Bucket]]) | AO13: 1.071492 | BE13: 1.071492
A14: 19-12.5-3.25-CEW- | C14: 34.93-0-1.2-ERW 1-FC | J14: 17.3 | K14: 17.3 | L14: 0 | M14: 1.6 | N14: ERW 1 | O14: PE | P14: 17.3-0-1.6-ERW 1-PE | Q14: Hosur | R14: =Table11[[#This Row],[Grand Total]] | S14: =VLOOKUP(Table11[[#This Row],[Bucket]],salesforecast[[#All],[Bucket2]:[WIP]],3,0) | T14: =VLOOKUP(Table11[[#This Row],[Bucket]],salesforecast[[#All],[Bucket2]:[WIP]],4,0) | U14: =VLOOKUP(Table11[[#This Row],[Bucket]],salesforecast[[#All],[Bucket2]:[WIP]],5,0) | V14: =VLOOKUP(Table11[[#This Row],[Bucket]],salesforecast[[#All],[Bucket2]:[WIP]],7,0) | W14: =Table11[[#This Row],[Stock LL]]+Table11[[#This Row],[WIP]]+Table11[[#This Row],[Stock CTL]] | X14: =IF((Table11[[#This Row],[Requirement]]-Table11[[#This Row],[Sales]]-Table11[[#This Row],[Total Stock]])<0,0,Table11[[#This Row],[Requirement]]-Table11[[#This Row],[Sales]]-Table11[[#This Row],[Total Stock]]) | Z14: 17.3 | AA14: 17.3 | AB14: 0 | AC14: 1.6 | AD14: ERW 1 | AE14: PE | AF14: 17.3-0-1.6-ERW 1-PE | AG14: =EXACT(Table11[[#This Row],[Bucket8]],Table11[[#This Row],[Bucket]]) | AI14: 12.498206 | AY14: 5.5262072 | AZ14: 1.9813852 | BE14: 20.005799
A15: (blank) | C15: 34.93-0-1.6-ERW 1-FC | J15: 18.2 | K15: 18.2 | L15: 0 | M15: 1 | N15: ERW 1 | O15: PE | P15: 18.2-0-1-ERW 1-PE | Q15: Hosur | R15: =Table11[[#This Row],[Grand Total]] | S15: =VLOOKUP(Table11[[#This Row],[Bucket]],salesforecast[[#All],[Bucket2]:[WIP]],3,0) | T15: =VLOOKUP(Table11[[#This Row],[Bucket]],salesforecast[[#All],[Bucket2]:[WIP]],4,0) | U15: =VLOOKUP(Table11[[#This Row],[Bucket]],salesforecast[[#All],[Bucket2]:[WIP]],5,0) | V15: =VLOOKUP(Table11[[#This Row],[Bucket]],salesforecast[[#All],[Bucket2]:[WIP]],7,0) | W15: =Table11[[#This Row],[Stock LL]]+Table11[[#This Row],[WIP]]+Table11[[#This Row],[Stock CTL]] | X15: =IF((Table11[[#This Row],[Requirement]]-Table11[[#This Row],[Sales]]-Table11[[#This Row],[Total Stock]])<0,0,Table11[[#This Row],[Requirement]]-Table11[[#This Row],[Sales]]-Table11[[#This Row],[Total Stock]]) | Z15: 18.2 | AA15: 18.2 | AB15: 0 | AC15: 1 | AD15: ERW 1 | AE15: PE | AF15: 18.2-0-1-ERW 1-PE | AG15: =EXACT(Table11[[#This Row],[Bucket8]],Table11[[#This Row],[Bucket]]) | AO15: 2.3953898 | AP15: 0.27981545 | BE15: 2.6752053
A16: 19.05-0-1.6-ERW 1- | C16: 34.93-0-2.6-ERW 1-FC | J16: 18.2 | K16: 18.2 | L16: 12.3 | M16: 2.95 | N16: ERW 1 | O16: PE | P16: 18.2-12.3-2.95-CEW-CEW | Q16: Khopoli | R16: =Table11[[#This Row],[Grand Total]] | S16: =VLOOKUP(Table11[[#This Row],[Bucket]],salesforecast[[#All],[Bucket2]:[WIP]],3,0) | T16: =VLOOKUP(Table11[[#This Row],[Bucket]],salesforecast[[#All],[Bucket2]:[WIP]],4,0) | U16: =VLOOKUP(Table11[[#This Row],[Bucket]],salesforecast[[#All],[Bucket2]:[WIP]],5,0) | V16: =VLOOKUP(Table11[[#This Row],[Bucket]],salesforecast[[#All],[Bucket2]:[WIP]],7,0) | W16: =Table11[[#This Row],[Stock LL]]+Table11[[#This Row],[WIP]]+Table11[[#This Row],[Stock CTL]] | X16: =IF((Table11[[#This Row],[Requirement]]-Table11[[#This Row],[Sales]]-Table11[[#This Row],[Total Stock]])<0,0,Table11[[#This Row],[Requirement]]-Table11[[#This Row],[Sales]]-Table11[[#This Row],[Total Stock]]) | Z16: 18.2 | AA16: 18.2 | AB16: 12.3 | AC16: 2.95 | AD16: CEW | AE16: CEW | AF16: 18.2-12.3-2.95-CEW-CEW | AG16: =EXACT(Table11[[#This Row],[Bucket8]],Table11[[#This Row],[Bucket]]) | AU16: 2.2177938 | BE16: 2.2177938
A17: 19.05-0-1.6-- | C17: 37.6-31.2-3.2-CEW-CEW | J17: 19 | K17: 19 | L17: 12.5 | M17: 3.25 | N17: CEW | O17: CEW | P17: 19-12.5-3.25-CEW-CEW | Q17: Khopoli | R17: =Table11[[#This Row],[Grand Total]] | S17: =VLOOKUP(Table11[[#This Row],[Bucket]],salesforecast[[#All],[Bucket2]:[WIP]],3,0) | T17: =VLOOKUP(Table11[[#This Row],[Bucket]],salesforecast[[#All],[Bucket2]:[WIP]],4,0) | U17: =VLOOKUP(Table11[[#This Row],[Bucket]],salesforecast[[#All],[Bucket2]:[WIP]],5,0) | V17: =VLOOKUP(Table11[[#This Row],[Bucket]],salesforecast[[#All],[Bucket2]:[WIP]],7,0) | W17: =Table11[[#This Row],[Stock LL]]+Table11[[#This Row],[WIP]]+Table11[[#This Row],[Stock CTL]] | X17: =IF((Table11[[#This Row],[Requirement]]-Table11[[#This Row],[Sales]]-Table11[[#This Row],[Total Stock]])<0,0,Table11[[#This Row],[Requirement]]-Table11[[#This Row],[Sales]]-Table11[[#This Row],[Total Stock]]) | Z17: 19 | AA17: 19 | AB17: 12.5 | AC17: 3.25 | AD17: CEW | AE17: CEW | AF17: 19-12.5-3.25-CEW-CEW | AG17: =EXACT(Table11[[#This Row],[Bucket8]],Table11[[#This Row],[Bucket]]) | AR17: 3.7094588 | AV17: 1.9682843 | AZ17: 11.128376 | BE17: 16.80612
A18: 19.05-0-1.63-- | C18: 37.95-32-2.95-CEW-CEW | J18: 19.05 | K18: 19.05 | L18: 0 | M18: 1 | N18: ERW 1 | O18: PE | P18: 19.05-0-1-ERW 1-PE | Q18: Hosur | R18: =Table11[[#This Row],[Grand Total]] | S18: =VLOOKUP(Table11[[#This Row],[Bucket]],salesforecast[[#All],[Bucket2]:[WIP]],3,0) | T18: =VLOOKUP(Table11[[#This Row],[Bucket]],salesforecast[[#All],[Bucket2]:[WIP]],4,0) | U18: =VLOOKUP(Table11[[#This Row],[Bucket]],salesforecast[[#All],[Bucket2]:[WIP]],5,0) | V18: =VLOOKUP(Table11[[#This Row],[Bucket]],salesforecast[[#All],[Bucket2]:[WIP]],7,0) | W18: =Table11[[#This Row],[Stock LL]]+Table11[[#This Row],[WIP]]+Table11[[#This Row],[Stock CTL]] | X18: =IF((Table11[[#This Row],[Requirement]]-Table11[[#This Row],[Sales]]-Table11[[#This Row],[Total Stock]])<0,0,Table11[[#This Row],[Requirement]]-Table11[[#This Row],[Sales]]-Table11[[#This Row],[Total Stock]]) | Y18: Available from week 2 | Z18: 19.05 | AA18: 19.05 | AB18: 0 | AC18: 1 | AD18: ERW 1 | AE18: PE | AF18: 19.05-0-1-ERW 1-PE | AG18: =EXACT(Table11[[#This Row],[Bucket8]],Table11[[#This Row],[Bucket]]) | AH18: 4.2711787 | AP18: 4.8718132 | BE18: 9.1429919
A19: (blank) | C19: 30-30-1.2-CRFH-PE | J19: 19.05 | K19: 19.05 | L19: 0 | M19: 1.2 | N19: CRFH | O19: PE | P19: 19.05-0-1.2-CRFH-PE | Q19: Hosur | R19: =Table11[[#This Row],[Grand Total]] | S19: =VLOOKUP(Table11[[#This Row],[Bucket]],salesforecast[[#All],[Bucket2]:[WIP]],3,0) | T19: =VLOOKUP(Table11[[#This Row],[Bucket]],salesforecast[[#All],[Bucket2]:[WIP]],4,0) | U19: =VLOOKUP(Table11[[#This Row],[Bucket]],salesforecast[[#All],[Bucket2]:[WIP]],5,0) | V19: =VLOOKUP(Table11[[#This Row],[Bucket]],salesforecast[[#All],[Bucket2]:[WIP]],7,0) | W19: =Table11[[#This Row],[Stock LL]]+Table11[[#This Row],[WIP]]+Table11[[#This Row],[Stock CTL]] | X19: =IF((Table11[[#This Row],[Requirement]]-Table11[[#This Row],[Sales]]-Table11[[#This Row],[Total Stock]])<0,0,Table11[[#This Row],[Requirement]]-Table11[[#This Row],[Sales]]-Table11[[#This Row],[Total Stock]]) | Z19: 19.05 | AA19: 19.05 | AB19: 0 | AC19: 1.2 | AD19: CRFH | AE19: PE | AF19: 19.05-0-1.2-CRFH-PE | AG19: =EXACT(Table11[[#This Row],[Bucket8]],Table11[[#This Row],[Bucket]]) | BB19: 7.2087965 | BC19: 10.034818 | BE19: 17.243614
A20: 19.05-0-2-ERW 1- | C20: 38.1-0-1.6-ERW 1-FC | J20: 19.05 | K20: 19.05 | L20: 0 | M20: 1.2 | N20: ERW 1 | O20: PE | P20: 19.05-0-1.2-ERW 1-PE | Q20: Hosur | R20: =Table11[[#This Row],[Grand Total]] | S20: =VLOOKUP(Table11[[#This Row],[Bucket]],salesforecast[[#All],[Bucket2]:[WIP]],3,0) | T20: =VLOOKUP(Table11[[#This Row],[Bucket]],salesforecast[[#All],[Bucket2]:[WIP]],4,0) | U20: =VLOOKUP(Table11[[#This Row],[Bucket]],salesforecast[[#All],[Bucket2]:[WIP]],5,0) | V20: =VLOOKUP(Table11[[#This Row],[Bucket]],salesforecast[[#All],[Bucket2]:[WIP]],7,0) | W20: =Table11[[#This Row],[Stock LL]]+Table11[[#This Row],[WIP]]+Table11[[#This Row],[Stock CTL]] | X20: =IF((Table11[[#This Row],[Requirement]]-Table11[[#This Row],[Sales]]-Table11[[#This Row],[Total Stock]])<0,0,Table11[[#This Row],[Requirement]]-Table11[[#This Row],[Sales]]-Table11[[#This Row],[Total Stock]]) | Y20: =_xlfn.CONCAT(ROUND(Table11[[#This Row],[Total Stock]]/Table11[[#This Row],[Requirement]]*100,0),"% Coverage. Rest by Week 3") | Z20: 19.05 | AA20: 19.05 | AB20: 0 | AC20: 1.2 | AD20: ERW 1 | AE20: PE | AF20: 19.05-0-1.2-ERW 1-PE | AG20: =EXACT(Table11[[#This Row],[Bucket8]],Table11[[#This Row],[Bucket]]) | AH20: 7.9894173 | AP20: 5.4857286 | AY20: 1.7159401 | BE20: 15.191086
A21: (blank) | C21: 38.1-0-1.6-ERW 2 MAHS-FC | J21: 19.05 | K21: 19.05 | L21: 0 | M21: 1.6 | N21: ERW 1 | O21: PE | P21: 19.05-0-1.6-ERW 1-PE | Q21: Hosur | R21: =Table11[[#This Row],[Grand Total]] | S21: =VLOOKUP(Table11[[#This Row],[Bucket]],salesforecast[[#All],[Bucket2]:[WIP]],3,0) | T21: =VLOOKUP(Table11[[#This Row],[Bucket]],salesforecast[[#All],[Bucket2]:[WIP]],4,0) | U21: =VLOOKUP(Table11[[#This Row],[Bucket]],salesforecast[[#All],[Bucket2]:[WIP]],5,0) | V21: =VLOOKUP(Table11[[#This Row],[Bucket]],salesforecast[[#All],[Bucket2]:[WIP]],7,0) | W21: =Table11[[#This Row],[Stock LL]]+Table11[[#This Row],[WIP]]+Table11[[#This Row],[Stock CTL]] | X21: =IF((Table11[[#This Row],[Requirement]]-Table11[[#This Row],[Sales]]-Table11[[#This Row],[Total Stock]])<0,0,Table11[[#This Row],[Requirement]]-Table11[[#This Row],[Sales]]-Table11[[#This Row],[Total Stock]]) | Y21: =_xlfn.CONCAT(ROUND(Table11[[#This Row],[Total Stock]]/Table11[[#This Row],[Requirement]]*100,0),"% Coverage. Rest by Week 3") | Z21: 19.05 | AA21: 19.05 | AB21: 0 | AC21: 1.6 | AD21: ERW 1 | AE21: PE | AF21: 19.05-0-1.6-ERW 1-PE | AG21: =EXACT(Table11[[#This Row],[Bucket8]],Table11[[#This Row],[Bucket]]) | AP21: 1.2594061 | AY21: 2.0473952 | BE21: 3.3068014
A22: 19.05-0-2-- | C22: 38.1-0-2-ERW 1-FC | J22: 19.05 | K22: 19.05 | L22: 0 | M22: 1.6 | N22: ERW 2 MAHS | O22: PE | P22: 19.05-0-1.6-ERW 2 MAHS-PE | Q22: Hosur | R22: =Table11[[#This Row],[Grand Total]] | S22: =VLOOKUP(Table11[[#This Row],[Bucket]],salesforecast[[#All],[Bucket2]:[WIP]],3,0) | T22: =VLOOKUP(Table11[[#This Row],[Bucket]],salesforecast[[#All],[Bucket2]:[WIP]],4,0) | U22: =VLOOKUP(Table11[[#This Row],[Bucket]],salesforecast[[#All],[Bucket2]:[WIP]],5,0) | V22: =VLOOKUP(Table11[[#This Row],[Bucket]],salesforecast[[#All],[Bucket2]:[WIP]],7,0) | W22: =Table11[[#This Row],[Stock LL]]+Table11[[#This Row],[WIP]]+Table11[[#This Row],[Stock CTL]] | X22: =IF((Table11[[#This Row],[Requirement]]-Table11[[#This Row],[Sales]]-Table11[[#This Row],[Total Stock]])<0,0,Table11[[#This Row],[Requirement]]-Table11[[#This Row],[Sales]]-Table11[[#This Row],[Total Stock]]) | Z22: 19.05 | AA22: 19.05 | AB22: 0 | AC22: 1.6 | AD22: ERW 2 MAHS | AE22: PE | AF22: 19.05-0-1.6-ERW 2 MAHS-PE | AG22: =EXACT(Table11[[#This Row],[Bucket8]],Table11[[#This Row],[Bucket]]) | AQ22: 13.557542 | AV22: 5.3335506 | BE22: 18.891092
A23: 19.05-0-2.3-ERW 1- | C23: 38.1-0-2.5-ERW 2 MAHS-FC | J23: 19.05 | K23: 19.05 | L23: 0 | M23: 2 | N23: ERW 1 | O23: PE | P23: 19.05-0-2-ERW 1-PE | Q23: Hosur | R23: =Table11[[#This Row],[Grand Total]] | S23: =VLOOKUP(Table11[[#This Row],[Bucket]],salesforecast[[#All],[Bucket2]:[WIP]],3,0) | T23: =VLOOKUP(Table11[[#This Row],[Bucket]],salesforecast[[#All],[Bucket2]:[WIP]],4,0) | U23: =VLOOKUP(Table11[[#This Row],[Bucket]],salesforecast[[#All],[Bucket2]:[WIP]],5,0) | V23: =VLOOKUP(Table11[[#This Row],[Bucket]],salesforecast[[#All],[Bucket2]:[WIP]],7,0) | W23: =Table11[[#This Row],[Stock LL]]+Table11[[#This Row],[WIP]]+Table11[[#This Row],[Stock CTL]] | X23: =IF((Table11[[#This Row],[Requirement]]-Table11[[#This Row],[Sales]]-Table11[[#This Row],[Total Stock]])<0,0,Table11[[#This Row],[Requirement]]-Table11[[#This Row],[Sales]]-Table11[[#This Row],[Total Stock]]) | Y23: =_xlfn.CONCAT(ROUND(Table11[[#This Row],[Total Stock]]/Table11[[#This Row],[Requirement]]*100,0),"% Coverage. Rest by Week 3") | Z23: 19.05 | AA23: 19.05 | AB23: 0 | AC23: 2 | AD23: ERW 1 | AE23: PE | AF23: 19.05-0-2-ERW 1-PE | AG23: =EXACT(Table11[[#This Row],[Bucket8]],Table11[[#This Row],[Bucket]]) | AI23: 2.7149148 | AQ23: 1.9962609 | AS23: 5.98458 | AU23: 7.0016224 | AZ23: 21.059502 | BE23: 38.75688
A24: 19.05-0-2.34-ERW 1- | C24: 38.1-0-3.66-ERW 1-FC | J24: 19.05 | K24: 19.05 | L24: 0 | M24: 2.3 | N24: ERW 1 | O24: PE | P24: 19.05-0-2.3-ERW 1-PE | Q24: Hosur | R24: =Table11[[#This Row],[Grand Total]] | S24: =VLOOKUP(Table11[[#This Row],[Bucket]],salesforecast[[#All],[Bucket2]:[WIP]],3,0) | T24: =VLOOKUP(Table11[[#This Row],[Bucket]],salesforecast[[#All],[Bucket2]:[WIP]],4,0) | U24: =VLOOKUP(Table11[[#This Row],[Bucket]],salesforecast[[#All],[Bucket2]:[WIP]],5,0) | V24: =VLOOKUP(Table11[[#This Row],[Bucket]],salesforecast[[#All],[Bucket2]:[WIP]],7,0) | W24: =Table11[[#This Row],[Stock LL]]+Table11[[#This Row],[WIP]]+Table11[[#This Row],[Stock CTL]] | X24: =IF((Table11[[#This Row],[Requirement]]-Table11[[#This Row],[Sales]]-Table11[[#This Row],[Total Stock]])<0,0,Table11[[#This Row],[Requirement]]-Table11[[#This Row],[Sales]]-Table11[[#This Row],[Total Stock]]) | Z24: 19.05 | AA24: 19.05 | AB24: 0 | AC24: 2.3 | AD24: ERW 1 | AE24: PE | AF24: 19.05-0-2.3-ERW 1-PE | AG24: =EXACT(Table11[[#This Row],[Bucket8]],Table11[[#This Row],[Bucket]]) | AI24: 10.133211 | AL24: 2.6731317 | AP24: 3.7414347 | AS24: 4.6293133 | AZ24: 61.135423 | BE24: 82.312514
A25: 19.05-0-2.5-ERW 2- | C25: 40-20-1.2-CRFH-PE | J25: 20 | K25: 20 | L25: 12.4 | M25: 3.8 | N25: CEW | O25: CEW | P25: 20-12.4-3.8-CEW-CEW | Q25: Khopoli | R25: =Table11[[#This Row],[Grand Total]] | S25: =VLOOKUP(Table11[[#This Row],[Bucket]],salesforecast[[#All],[Bucket2]:[WIP]],3,0) | T25: =VLOOKUP(Table11[[#This Row],[Bucket]],salesforecast[[#All],[Bucket2]:[WIP]],4,0) | U25: =VLOOKUP(Table11[[#This Row],[Bucket]],salesforecast[[#All],[Bucket2]:[WIP]],5,0) | V25: =VLOOKUP(Table11[[#This Row],[Bucket]],salesforecast[[#All],[Bucket2]:[WIP]],7,0) | W25: =Table11[[#This Row],[Stock LL]]+Table11[[#This Row],[WIP]]+Table11[[#This Row],[Stock CTL]] | X25: =IF((Table11[[#This Row],[Requirement]]-Table11[[#This Row],[Sales]]-Table11[[#This Row],[Total Stock]])<0,0,Table11[[#This Row],[Requirement]]-Table11[[#This Row],[Sales]]-Table11[[#This Row],[Total Stock]]) | Y25: =_xlfn.CONCAT(ROUND(Table11[[#This Row],[Total Stock]]/Table11[[#This Row],[Requirement]]*100,0),"% Coverage. Rest by Week 3") | Z25: 20 | AA25: 20 | AB25: 12.4 | AC25: 3.8 | AD25: CEW | AE25: CEW | AF25: 20-12.4-3.8-CEW-CEW | AG25: =EXACT(Table11[[#This Row],[Bucket8]],Table11[[#This Row],[Bucket]]) | AP25: 12.13914 | AX25: 1.0151355 | BE25: 13.154275
A26: 21.75-0-3.5-CEW- | C26: 40-20-1.6-ERW 1-FC | J26: 20 | K26: 20 | L26: 12.4 | M26: 4.5 | N26: CEW | O26: CEW | P26: 20-12.4-4.5-CEW-CEW | Q26: Khopoli | R26: =Table11[[#This Row],[Grand Total]] | S26: =VLOOKUP(Table11[[#This Row],[Bucket]],salesforecast[[#All],[Bucket2]:[WIP]],3,0) | T26: =VLOOKUP(Table11[[#This Row],[Bucket]],salesforecast[[#All],[Bucket2]:[WIP]],4,0) | U26: =VLOOKUP(Table11[[#This Row],[Bucket]],salesforecast[[#All],[Bucket2]:[WIP]],5,0) | V26: =VLOOKUP(Table11[[#This Row],[Bucket]],salesforecast[[#All],[Bucket2]:[WIP]],7,0) | W26: =Table11[[#This Row],[Stock LL]]+Table11[[#This Row],[WIP]]+Table11[[#This Row],[Stock CTL]] | X26: =IF((Table11[[#This Row],[Requirement]]-Table11[[#This Row],[Sales]]-Table11[[#This Row],[Total Stock]])<0,0,Table11[[#This Row],[Requirement]]-Table11[[#This Row],[Sales]]-Table11[[#This Row],[Total Stock]]) | Z26: 20 | AA26: 20 | AB26: 12.4 | AC26: 4.5 | AD26: CEW | AE26: CEW | AF26: 20-12.4-4.5-CEW-CEW | AG26: =EXACT(Table11[[#This Row],[Bucket8]],Table11[[#This Row],[Bucket]]) | AO26: 4.2981694 | BE26: 4.2981694
A27: 22.2-0-1.2-- | C27: 39-34-2.5-CEW-CEW | J27: 20 | K27: 20 | L27: 17.16 | M27: 1.42 | N27: CEW | O27: CEW | P27: 20-17.16-1.42-CEW-CEW | Q27: Khopoli | R27: =Table11[[#This Row],[Grand Total]] | S27: =VLOOKUP(Table11[[#This Row],[Bucket]],salesforecast[[#All],[Bucket2]:[WIP]],3,0) | T27: =VLOOKUP(Table11[[#This Row],[Bucket]],salesforecast[[#All],[Bucket2]:[WIP]],4,0) | U27: =VLOOKUP(Table11[[#This Row],[Bucket]],salesforecast[[#All],[Bucket2]:[WIP]],5,0) | V27: =VLOOKUP(Table11[[#This Row],[Bucket]],salesforecast[[#All],[Bucket2]:[WIP]],7,0) | W27: =Table11[[#This Row],[Stock LL]]+Table11[[#This Row],[WIP]]+Table11[[#This Row],[Stock CTL]] | X27: =IF((Table11[[#This Row],[Requirement]]-Table11[[#This Row],[Sales]]-Table11[[#This Row],[Total Stock]])<0,0,Table11[[#This Row],[Requirement]]-Table11[[#This Row],[Sales]]-Table11[[#This Row],[Total Stock]]) | Z27: 20 | AA27: 20 | AB27: 17.16 | AC27: 1.42 | AD27: CEW | AE27: CEW | AF27: 20-17.16-1.42-CEW-CEW | AG27: =EXACT(Table11[[#This Row],[Bucket8]],Table11[[#This Row],[Bucket]]) | AP27: 1.0652395 | BD27: 1.4203193 | BE27: 2.4855588
A28: 22.23-0-1.2-ERW 1- | C28: 40-25-1.6-ERW 1-FC | J28: 21.7 | K28: 21.7 | L28: 16.2 | M28: 2.75 | N28: CEW | O28: CEW | P28: 21.7-16.2-2.75-CEW-CEW | Q28: Khopoli | R28: =Table11[[#This Row],[Grand Total]] | S28: =VLOOKUP(Table11[[#This Row],[Bucket]],salesforecast[[#All],[Bucket2]:[WIP]],3,0) | T28: =VLOOKUP(Table11[[#This Row],[Bucket]],salesforecast[[#All],[Bucket2]:[WIP]],4,0) | U28: =VLOOKUP(Table11[[#This Row],[Bucket]],salesforecast[[#All],[Bucket2]:[WIP]],5,0) | V28: =VLOOKUP(Table11[[#This Row],[Bucket]],salesforecast[[#All],[Bucket2]:[WIP]],7,0) | W28: =Table11[[#This Row],[Stock LL]]+Table11[[#This Row],[WIP]]+Table11[[#This Row],[Stock CTL]] | X28: =IF((Table11[[#This Row],[Requirement]]-Table11[[#This Row],[Sales]]-Table11[[#This Row],[Total Stock]])<0,0,Table11[[#This Row],[Requirement]]-Table11[[#This Row],[Sales]]-Table11[[#This Row],[Total Stock]]) | Z28: 21.7 | AA28: 21.7 | AB28: 16.2 | AC28: 2.75 | AD28: CEW | AE28: CEW | AF28: 21.7-16.2-2.75-CEW-CEW | AG28: =EXACT(Table11[[#This Row],[Bucket8]],Table11[[#This Row],[Bucket]]) | AU28: 3.2113025 | AZ28: 3.853563 | BE28: 7.0648656
A29: 22.23-0-1.2-- | C29: 40-25-1.6-ERW 2-FC | J29: 21.75 | K29: 21.75 | L29: 0 | M29: 3.5 | N29: CEW | O29: CEW | P29: 21.75-0-3.5-CEW-CEW | Q29: Khopoli | R29: =Table11[[#This Row],[Grand Total]] | S29: =VLOOKUP(Table11[[#This Row],[Bucket]],salesforecast[[#All],[Bucket2]:[WIP]],3,0) | T29: =VLOOKUP(Table11[[#This Row],[Bucket]],salesforecast[[#All],[Bucket2]:[WIP]],4,0) | U29: =VLOOKUP(Table11[[#This Row],[Bucket]],salesforecast[[#All],[Bucket2]:[WIP]],5,0) | V29: =VLOOKUP(Table11[[#This Row],[Bucket]],salesforecast[[#All],[Bucket2]:[WIP]],7,0) | W29: =Table11[[#This Row],[Stock LL]]+Table11[[#This Row],[WIP]]+Table11[[#This Row],[Stock CTL]] | X29: =IF((Table11[[#This Row],[Requirement]]-Table11[[#This Row],[Sales]]-Table11[[#This Row],[Total Stock]])<0,0,Table11[[#This Row],[Requirement]]-Table11[[#This Row],[Sales]]-Table11[[#This Row],[Total Stock]]) | Z29: 21.75 | AA29: 21.75 | AB29: 0 | AC29: 3.5 | AD29: CEW | AE29: CEW | AF29: 21.75-0-3.5-CEW-CEW | AG29: =EXACT(Table11[[#This Row],[Bucket8]],Table11[[#This Row],[Bucket]]) | AX29: 3.5598425 | BE29: 3.5598425
A30: 22.23-0-1.6-ERW 1- | C30: 41.28-0-2.6-ERW 1-FC | J30: 22.23 | K30: 22.23 | L30: 0 | M30: 1.2 | N30: ERW 1 | O30: PE | P30: 22.23-0-1.2-ERW 1-PE | Q30: Hosur | R30: =Table11[[#This Row],[Grand Total]] | S30: =VLOOKUP(Table11[[#This Row],[Bucket]],salesforecast[[#All],[Bucket2]:[WIP]],3,0) | T30: =VLOOKUP(Table11[[#This Row],[Bucket]],salesforecast[[#All],[Bucket2]:[WIP]],4,0) | U30: =VLOOKUP(Table11[[#This Row],[Bucket]],salesforecast[[#All],[Bucket2]:[WIP]],5,0) | V30: =VLOOKUP(Table11[[#This Row],[Bucket]],salesforecast[[#All],[Bucket2]:[WIP]],7,0) | W30: =Table11[[#This Row],[Stock LL]]+Table11[[#This Row],[WIP]]+Table11[[#This Row],[Stock CTL]] | X30: =IF((Table11[[#This Row],[Requirement]]-Table11[[#This Row],[Sales]]-Table11[[#This Row],[Total Stock]])<0,0,Table11[[#This Row],[Requirement]]-Table11[[#This Row],[Sales]]-Table11[[#This Row],[Total Stock]]) | Y30: No Commitment | Z30: 22.23 | AA30: 22.23 | AB30: 0 | AC30: 1.2 | AD30: ERW 1 | AE30: PE | AF30: 22.23-0-1.2-ERW 1-PE | AG30: =EXACT(Table11[[#This Row],[Bucket8]],Table11[[#This Row],[Bucket]]) | AI30: 5.782504 | AO30: 0.17417181 | AS30: 0.93306325 | AT30: 2.1945648 | AW30: 1.652144 | AY30: 5.4422469 | AZ30: 4.0681558 | BE30: 20.24685
A31: 22.23-0-2-ERW 1- | C31: 41.28-0-3.2-ERW 1-FC | J31: 22.23 | K31: 22.23 | L31: 0 | M31: 1.6 | N31: ERW 1 | O31: PE | P31: 22.23-0-1.6-ERW 1-PE | Q31: Hosur | R31: =Table11[[#This Row],[Grand Total]] | S31: =VLOOKUP(Table11[[#This Row],[Bucket]],salesforecast[[#All],[Bucket2]:[WIP]],3,0) | T31: =VLOOKUP(Table11[[#This Row],[Bucket]],salesforecast[[#All],[Bucket2]:[WIP]],4,0) | U31: =VLOOKUP(Table11[[#This Row],[Bucket]],salesforecast[[#All],[Bucket2]:[WIP]],5,0) | V31: =VLOOKUP(Table11[[#This Row],[Bucket]],salesforecast[[#All],[Bucket2]:[WIP]],7,0) | W31: =Table11[[#This Row],[Stock LL]]+Table11[[#This Row],[WIP]]+Table11[[#This Row],[Stock CTL]] | X31: =IF((Table11[[#This Row],[Requirement]]-Table11[[#This Row],[Sales]]-Table11[[#This Row],[Total Stock]])<0,0,Table11[[#This Row],[Requirement]]-Table11[[#This Row],[Sales]]-Table11[[#This Row],[Total Stock]]) | Y31: =_xlfn.CONCAT(ROUND(Table11[[#This Row],[Total Stock]]/Table11[[#This Row],[Requirement]]*100,0),"% Coverage. Rest by Week 3") | Z31: 22.23 | AA31: 22.23 | AB31: 0 | AC31: 1.6 | AD31: ERW 1 | AE31: PE | AF31: 22.23-0-1.6-ERW 1-PE | AG31: =EXACT(Table11[[#This Row],[Bucket8]],Table11[[#This Row],[Bucket]]) | AL31: 1.1594002 | AM31: 3.954165 | AO31: 14.632038 | AP31: 4.1364146 | AS31: 15.040472 | AU31: 7.6479734 | AX31: 19.648783 | AY31: 1.7834423 | AZ31: 54.827833 | BE31: 122.83052
A32: (blank) | C32: 42.7-0-3.5-ERW 1-FC | J32: 22.23 | K32: 22.23 | L32: 0 | M32: 1.6 | N32: ERW 2 MAHS | O32: PE | P32: 22.23-0-1.6-ERW 2 MAHS-PE | Q32: Hosur | R32: =Table11[[#This Row],[Grand Total]] | S32: =VLOOKUP(Table11[[#This Row],[Bucket]],salesforecast[[#All],[Bucket2]:[WIP]],3,0) | T32: =VLOOKUP(Table11[[#This Row],[Bucket]],salesforecast[[#All],[Bucket2]:[WIP]],4,0) | U32: =VLOOKUP(Table11[[#This Row],[Bucket]],salesforecast[[#All],[Bucket2]:[WIP]],5,0) | V32: =VLOOKUP(Table11[[#This Row],[Bucket]],salesforecast[[#All],[Bucket2]:[WIP]],7,0) | W32: =Table11[[#This Row],[Stock LL]]+Table11[[#This Row],[WIP]]+Table11[[#This Row],[Stock CTL]] | X32: =IF((Table11[[#This Row],[Requirement]]-Table11[[#This Row],[Sales]]-Table11[[#This Row],[Total Stock]])<0,0,Table11[[#This Row],[Requirement]]-Table11[[#This Row],[Sales]]-Table11[[#This Row],[Total Stock]]) | Y32: =_xlfn.CONCAT(ROUND(Table11[[#This Row],[Total Stock]]/Table11[[#This Row],[Requirement]]*100,0),"% Coverage. Rest by Week 3") | Z32: 22.23 | AA32: 22.23 | AB32: 0 | AC32: 1.6 | AD32: ERW 2 MAHS | AE32: PE | AF32: 22.23-0-1.6-ERW 2 MAHS-PE | AG32: =EXACT(Table11[[#This Row],[Bucket8]],Table11[[#This Row],[Bucket]]) | AW32: 22.821878 | BE32: 22.821878
A33: 22.23-0-2-ERW 2 MAHS-FC | C33: 42.7-0-4-ERW 1-FC | J33: 22.23 | K33: 22.23 | L33: 0 | M33: 2 | N33: ERW 1 | O33: FC | P33: 22.23-0-2-ERW 1-FC | Q33: Hosur | R33: =Table11[[#This Row],[Grand Total]] | S33: =VLOOKUP(Table11[[#This Row],[Bucket]],salesforecast[[#All],[Bucket2]:[WIP]],3,0) | T33: =VLOOKUP(Table11[[#This Row],[Bucket]],salesforecast[[#All],[Bucket2]:[WIP]],4,0) | U33: =VLOOKUP(Table11[[#This Row],[Bucket]],salesforecast[[#All],[Bucket2]:[WIP]],5,0) | V33: =VLOOKUP(Table11[[#This Row],[Bucket]],salesforecast[[#All],[Bucket2]:[WIP]],7,0) | W33: =Table11[[#This Row],[Stock LL]]+Table11[[#This Row],[WIP]]+Table11[[#This Row],[Stock CTL]] | X33: =IF((Table11[[#This Row],[Requirement]]-Table11[[#This Row],[Sales]]-Table11[[#This Row],[Total Stock]])<0,0,Table11[[#This Row],[Requirement]]-Table11[[#This Row],[Sales]]-Table11[[#This Row],[Total Stock]]) | Y33: =_xlfn.CONCAT(ROUND(Table11[[#This Row],[Total Stock]]/Table11[[#This Row],[Requirement]]*100,0),"% Coverage. Rest by Week 3") | Z33: 22.23 | AA33: 22.23 | AB33: 0 | AC33: 2 | AD33: ERW 1 | AE33: FC | AF33: 22.23-0-2-ERW 1-FC | AG33: =EXACT(Table11[[#This Row],[Bucket8]],Table11[[#This Row],[Bucket]]) | AI33: 2.9918956 | AJ33: 8.9756869 | BE33: 11.967582
A34: (blank) | C34: 40-30-1.6-ERW 1-FC | J34: 22.23 | K34: 22.23 | L34: 0 | M34: 2 | N34: ERW 1 | O34: PE | P34: 22.23-0-2-ERW 1-PE | Q34: Hosur | R34: =Table11[[#This Row],[Grand Total]] | S34: =VLOOKUP(Table11[[#This Row],[Bucket]],salesforecast[[#All],[Bucket2]:[WIP]],3,0) | T34: =VLOOKUP(Table11[[#This Row],[Bucket]],salesforecast[[#All],[Bucket2]:[WIP]],4,0) | U34: =VLOOKUP(Table11[[#This Row],[Bucket]],salesforecast[[#All],[Bucket2]:[WIP]],5,0) | V34: =VLOOKUP(Table11[[#This Row],[Bucket]],salesforecast[[#All],[Bucket2]:[WIP]],7,0) | W34: =Table11[[#This Row],[Stock LL]]+Table11[[#This Row],[WIP]]+Table11[[#This Row],[Stock CTL]] | X34: =IF((Table11[[#This Row],[Requirement]]-Table11[[#This Row],[Sales]]-Table11[[#This Row],[Total Stock]])<0,0,Table11[[#This Row],[Requirement]]-Table11[[#This Row],[Sales]]-Table11[[#This Row],[Total Stock]]) | Y34: =_xlfn.CONCAT(ROUND(Table11[[#This Row],[Total Stock]]/Table11[[#This Row],[Requirement]]*100,0),"% Coverage. Rest by Week 3") | Z34: 22.23 | AA34: 22.23 | AB34: 0 | AC34: 2 | AD34: ERW 1 | AE34: PE | AF34: 22.23-0-2-ERW 1-PE | AG34: =EXACT(Table11[[#This Row],[Bucket8]],Table11[[#This Row],[Bucket]]) | AO34: 7.6123798 | AP34: 12.944935 | AS34: 5.0612901 | AW34: 2.762517 | AY34: 16.121331 | AZ34: 2.1940568 | BE34: 46.69651
A35: 22.23-0-2-- | C35: 40-30-2-ERW 1-FC | J35: 22.23 | K35: 22.23 | L35: 0 | M35: 2 | N35: ERW 2 | O35: FC | P35: 22.23-0-2-ERW 2-FC | Q35: Hosur | R35: =Table11[[#This Row],[Grand Total]] | S35: =VLOOKUP(Table11[[#This Row],[Bucket]],salesforecast[[#All],[Bucket2]:[WIP]],3,0) | T35: =VLOOKUP(Table11[[#This Row],[Bucket]],salesforecast[[#All],[Bucket2]:[WIP]],4,0) | U35: =VLOOKUP(Table11[[#This Row],[Bucket]],salesforecast[[#All],[Bucket2]:[WIP]],5,0) | V35: =VLOOKUP(Table11[[#This Row],[Bucket]],salesforecast[[#All],[Bucket2]:[WIP]],7,0) | W35: =Table11[[#This Row],[Stock LL]]+Table11[[#This Row],[WIP]]+Table11[[#This Row],[Stock CTL]] | X35: =IF((Table11[[#This Row],[Requirement]]-Table11[[#This Row],[Sales]]-Table11[[#This Row],[Total Stock]])<0,0,Table11[[#This Row],[Requirement]]-Table11[[#This Row],[Sales]]-Table11[[#This Row],[Total Stock]]) | Z35: 22.23 | AA35: 22.23 | AB35: 0 | AC35: 2 | AD35: ERW 2 | AE35: FC | AF35: 22.23-0-2-ERW 2-FC | AG35: =EXACT(Table11[[#This Row],[Bucket8]],Table11[[#This Row],[Bucket]]) | AX35: 10.43905 | BE35: 10.43905
